MPEI_Bachelor/projects/Лр4/КМ4/FSM_traffic_light_Chushnikov_2yellow/src/timer.v
module timer #(parameter bit = 5) //чтобы быстро менять входную частоту 
				(clk_50MHz, res,clk_1Hz,cnt2, Load);

input  clk_50MHz, res, Load;

output 	 reg  clk_1Hz; //делим частоту 
output 	 reg  [bit:0]cnt2; //для подсчета количества прошедших секунд

reg [bit:0] cnt; 

always @(posedge clk_50MHz, negedge res) //Блок для получения 1 секунды
if (!res) 
begin
		cnt <= 0;
		clk_1Hz <= 0;
end

else if (cnt == 25)
begin
		cnt <= 0;
		clk_1Hz <= ~clk_1Hz;
end

else 
		cnt <=cnt + 1'b1; 

always @(posedge clk_50MHz, negedge res) //Блок для счетчика секунд
if (!res)  
		cnt2 <= 0; 
else if (!Load)
		cnt2 <= 0;
else if (cnt == 0 && clk_1Hz)
		cnt2 <= cnt2 + 1;
else 
		cnt2 <= cnt2;
	
endmodule

MPEI_Bachelor/projects/Лр4/КМ4/FSM_traffic_light_Chushnikov_2yellow/src/traffic_light.v
module traffic_light(clk, res, out_state);

input clk, res;
output [1:0] out_state;

localparam RED = 0, YELLOW1 = 1, GREEN = 2, YELLOW2 = 3;

reg [1:0] state, next_state;
reg [63:0] txstate;

always @(state)
	case (state)
		RED     : txstate = "RED";
		YELLOW1 : txstate = "YELLOW";
		GREEN   : txstate = "GREEN";
		YELLOW2 : txstate = "YELLOW2";
	endcase

wire [5:0] timer_second;
reg  timer_second_reset;

timer one_second(.clk_50MHz(clk), .res(res), .Load(timer_second_reset), .cnt2(timer_second)); //Подключаем таймер
   	
always @(*) //Логика автомата
begin
    case (state)
        RED:
    		begin
				timer_second_reset = 1;
    		    if (timer_second == 40)

                    begin
    				    timer_second_reset = 0;
    				    next_state = YELLOW1;
    				end
				 else next_state = RED;
    		end
    	YELLOW1:
    		begin
				timer_second_reset = 1;
    		    if (timer_second == 3)
    				begin
    	                timer_second_reset = 0;
    				    next_state = GREEN;
    			    end
					else next_state = YELLOW1;
    		end
    	GREEN:
    		begin
				timer_second_reset = 1;
    		    if (timer_second == 21)
    	  			begin
    			  		timer_second_reset = 0;
    				    next_state = YELLOW2;
    				end
				 else next_state = GREEN;  	 
    		end
    	YELLOW2:
    		begin
				timer_second_reset = 1;
    		    if (timer_second == 3)
    				begin
    	                timer_second_reset = 0;
    				    next_state = RED;
    			    end
				  else next_state = YELLOW2;
    		end		
		default : next_state = RED;
	endcase
end

always @(posedge clk, negedge res) 
begin
if (!res)
 	state <= RED;
else
	state <= next_state;
end

assign out_state = state;

endmodule

MPEI_Bachelor/projects/Лр4/КМ4/FSM_traffic_light_Chushnikov_2yellow/src/traffic_light_top.v
module traffic_light_top(clk, res,led0, led1, led2);

input clk, res;
output led0, led1, led2;
	 
localparam RED = 0, YELLOW1 = 1, GREEN = 2, YELLOW2 = 3;

wire [1:0] state;

traffic_light lights(.clk(clk), .out_state(state), .res(res));
	 
// Логика для светодиодов
assign led0 = state == RED ? 1 : 0;

assign led1 = (state == YELLOW1) || (state == YELLOW2) ? 1 : 0;

assign led2 = state == GREEN ? 1 : 0;

endmodule

MPEI_Bachelor/projects/Лр4/КМ4/FSM_traffic_light_Chushnikov_2yellow/src/tb_traffic_light_top.v
`include "traffic_light_top.v"
`timescale 1ns / 1ns

module tb_traffic_light_top;

reg clk, res;

wire led0, led1, led2;

traffic_light_top DUT (.clk(clk), .res(res), .led0(led0), .led1(led1), .led2(led2));

initial begin                                                  
  clk = 0;
  $display("Running testbench");
end         
      
initial begin
res = 1;
repeat (2) #1 res = ~res;
end	  

always 
  #1	  clk =  ! clk;                                                 

initial begin
	#30000 $display("Testbench is OK!");
         $finish;
end

//Для симуляция в Iverilog		 
initial begin            
    $dumpfile("qqq.vcd");
    $dumpvars;
end

endmodule

MPEI_Bachelor/projects/Лр4/КМ4/FSM_traffic_light_Chushnikov_2yellow/simulation/modelsim/qqq.vcd
$date
	Thu Dec 01 01:19:59 2022
$end
$version
	ModelSim Version 2020.1
$end
$timescale
	1ps
$end

$scope module tb_traffic_light_top $end
$var reg 1 ! clk $end
$var reg 1 " res $end
$var wire 1 # led0 $end
$var wire 1 $ led1 $end
$var wire 1 % led2 $end

$scope module DUT $end
$var parameter 32 & RED $end
$var parameter 32 ' YELLOW1 $end
$var parameter 32 ( GREEN $end
$var parameter 32 ) YELLOW2 $end
$var wire 1 * clk $end
$var wire 1 + res $end
$var wire 1 # led0 $end
$var wire 1 $ led1 $end
$var wire 1 % led2 $end
$var wire 1 , state [1] $end
$var wire 1 - state [0] $end

$scope module lights $end
$var parameter 32 . RED $end
$var parameter 32 / YELLOW1 $end
$var parameter 32 0 GREEN $end
$var parameter 32 1 YELLOW2 $end
$var wire 1 * clk $end
$var wire 1 + res $end
$var wire 1 , out_state [1] $end
$var wire 1 - out_state [0] $end
$var reg 2 2 state [1:0] $end
$var reg 2 3 next_state [1:0] $end
$var reg 64 4 txstate [63:0] $end
$var wire 1 5 timer_second [5] $end
$var wire 1 6 timer_second [4] $end
$var wire 1 7 timer_second [3] $end
$var wire 1 8 timer_second [2] $end
$var wire 1 9 timer_second [1] $end
$var wire 1 : timer_second [0] $end
$var reg 1 ; timer_second_reset $end

$scope module one_second $end
$var parameter 32 < bit $end
$var wire 1 * clk_50MHz $end
$var wire 1 + res $end
$var wire 1 = Load $end
$var reg 1 > clk_1Hz $end
$var reg 6 ? cnt2 [5:0] $end
$var reg 6 @ cnt [5:0] $end
$upscope $end
$upscope $end
$upscope $end
$upscope $end
$enddefinitions $end
#0
$dumpvars
0!
1"
bx 2
bx 3
bx 4
x;
x>
bx ?
bx @
b0 &
b1 '
b10 (
b11 )
b0 .
b1 /
b10 0
b11 1
b101 <
x#
x$
x%
x-
x,
x:
x9
x8
x7
x6
x5
1+
0*
x=
$end
#1000
0"
1!
0+
1*
b0 @
0>
b0 ?
b0 2
0-
0,
0%
0$
1#
0:
09
08
07
06
05
b10100100100010101000100 4
1;
b0 3
1=
#2000
1"
0!
1+
0*
#3000
1!
1*
b1 @
#4000
0!
0*
#5000
1!
1*
b10 @
#6000
0!
0*
#7000
1!
1*
b11 @
#8000
0!
0*
#9000
1!
1*
b100 @
#10000
0!
0*
#11000
1!
1*
b101 @
#12000
0!
0*
#13000
1!
1*
b110 @
#14000
0!
0*
#15000
1!
1*
b111 @
#16000
0!
0*
#17000
1!
1*
b1000 @
#18000
0!
0*
#19000
1!
1*
b1001 @
#20000
0!
0*
#21000
1!
1*
b1010 @
#22000
0!
0*
#23000
1!
1*
b1011 @
#24000
0!
0*
#25000
1!
1*
b1100 @
#26000
0!
0*
#27000
1!
1*
b1101 @
#28000
0!
0*
#29000
1!
1*
b1110 @
#30000
0!
0*
#31000
1!
1*
b1111 @
#32000
0!
0*
#33000
1!
1*
b10000 @
#34000
0!
0*
#35000
1!
1*
b10001 @
#36000
0!
0*
#37000
1!
1*
b10010 @
#38000
0!
0*
#39000
1!
1*
b10011 @
#40000
0!
0*
#41000
1!
1*
b10100 @
#42000
0!
0*
#43000
1!
1*
b10101 @
#44000
0!
0*
#45000
1!
1*
b10110 @
#46000
0!
0*
#47000
1!
1*
b10111 @
#48000
0!
0*
#49000
1!
1*
b11000 @
#50000
0!
0*
#51000
1!
1*
b11001 @
#52000
0!
0*
#53000
1!
1*
b0 @
1>
#54000
0!
0*
#55000
1!
1*
b1 @
b1 ?
1:
#56000
0!
0*
#57000
1!
1*
b10 @
#58000
0!
0*
#59000
1!
1*
b11 @
#60000
0!
0*
#61000
1!
1*
b100 @
#62000
0!
0*
#63000
1!
1*
b101 @
#64000
0!
0*
#65000
1!
1*
b110 @
#66000
0!
0*
#67000
1!
1*
b111 @
#68000
0!
0*
#69000
1!
1*
b1000 @
#70000
0!
0*
#71000
1!
1*
b1001 @
#72000
0!
0*
#73000
1!
1*
b1010 @
#74000
0!
0*
#75000
1!
1*
b1011 @
#76000
0!
0*
#77000
1!
1*
b1100 @
#78000
0!
0*
#79000
1!
1*
b1101 @
#80000
0!
0*
#81000
1!
1*
b1110 @
#82000
0!
0*
#83000
1!
1*
b1111 @
#84000
0!
0*
#85000
1!
1*
b10000 @
#86000
0!
0*
#87000
1!
1*
b10001 @
#88000
0!
0*
#89000
1!
1*
b10010 @
#90000
0!
0*
#91000
1!
1*
b10011 @
#92000
0!
0*
#93000
1!
1*
b10100 @
#94000
0!
0*
#95000
1!
1*
b10101 @
#96000
0!
0*
#97000
1!
1*
b10110 @
#98000
0!
0*
#99000
1!
1*
b10111 @
#100000
0!
0*
#101000
1!
1*
b11000 @
#102000
0!
0*
#103000
1!
1*
b11001 @
#104000
0!
0*
#105000
1!
1*
b0 @
0>
#106000
0!
0*
#107000
1!
1*
b1 @
#108000
0!
0*
#109000
1!
1*
b10 @
#110000
0!
0*
#111000
1!
1*
b11 @
#112000
0!
0*
#113000
1!
1*
b100 @
#114000
0!
0*
#115000
1!
1*
b101 @
#116000
0!
0*
#117000
1!
1*
b110 @
#118000
0!
0*
#119000
1!
1*
b111 @
#120000
0!
0*
#121000
1!
1*
b1000 @
#122000
0!
0*
#123000
1!
1*
b1001 @
#124000
0!
0*
#125000
1!
1*
b1010 @
#126000
0!
0*
#127000
1!
1*
b1011 @
#128000
0!
0*
#129000
1!
1*
b1100 @
#130000
0!
0*
#131000
1!
1*
b1101 @
#132000
0!
0*
#133000
1!
1*
b1110 @
#134000
0!
0*
#135000
1!
1*
b1111 @
#136000
0!
0*
#137000
1!
1*
b10000 @
#138000
0!
0*
#139000
1!
1*
b10001 @
#140000
0!
0*
#141000
1!
1*
b10010 @
#142000
0!
0*
#143000
1!
1*
b10011 @
#144000
0!
0*
#145000
1!
1*
b10100 @
#146000
0!
0*
#147000
1!
1*
b10101 @
#148000
0!
0*
#149000
1!
1*
b10110 @
#150000
0!
0*
#151000
1!
1*
b10111 @
#152000
0!
0*
#153000
1!
1*
b11000 @
#154000
0!
0*
#155000
1!
1*
b11001 @
#156000
0!
0*
#157000
1!
1*
b0 @
1>
#158000
0!
0*
#159000
1!
1*
b1 @
b10 ?
0:
19
#160000
0!
0*
#161000
1!
1*
b10 @
#162000
0!
0*
#163000
1!
1*
b11 @
#164000
0!
0*
#165000
1!
1*
b100 @
#166000
0!
0*
#167000
1!
1*
b101 @
#168000
0!
0*
#169000
1!
1*
b110 @
#170000
0!
0*
#171000
1!
1*
b111 @
#172000
0!
0*
#173000
1!
1*
b1000 @
#174000
0!
0*
#175000
1!
1*
b1001 @
#176000
0!
0*
#177000
1!
1*
b1010 @
#178000
0!
0*
#179000
1!
1*
b1011 @
#180000
0!
0*
#181000
1!
1*
b1100 @
#182000
0!
0*
#183000
1!
1*
b1101 @
#184000
0!
0*
#185000
1!
1*
b1110 @
#186000
0!
0*
#187000
1!
1*
b1111 @
#188000
0!
0*
#189000
1!
1*
b10000 @
#190000
0!
0*
#191000
1!
1*
b10001 @
#192000
0!
0*
#193000
1!
1*
b10010 @
#194000
0!
0*
#195000
1!
1*
b10011 @
#196000
0!
0*
#197000
1!
1*
b10100 @
#198000
0!
0*
#199000
1!
1*
b10101 @
#200000
0!
0*
#201000
1!
1*
b10110 @
#202000
0!
0*
#203000
1!
1*
b10111 @
#204000
0!
0*
#205000
1!
1*
b11000 @
#206000
0!
0*
#207000
1!
1*
b11001 @
#208000
0!
0*
#209000
1!
1*
b0 @
0>
#210000
0!
0*
#211000
1!
1*
b1 @
#212000
0!
0*
#213000
1!
1*
b10 @
#214000
0!
0*
#215000
1!
1*
b11 @
#216000
0!
0*
#217000
1!
1*
b100 @
#218000
0!
0*
#219000
1!
1*
b101 @
#220000
0!
0*
#221000
1!
1*
b110 @
#222000
0!
0*
#223000
1!
1*
b111 @
#224000
0!
0*
#225000
1!
1*
b1000 @
#226000
0!
0*
#227000
1!
1*
b1001 @
#228000
0!
0*
#229000
1!
1*
b1010 @
#230000
0!
0*
#231000
1!
1*
b1011 @
#232000
0!
0*
#233000
1!
1*
b1100 @
#234000
0!
0*
#235000
1!
1*
b1101 @
#236000
0!
0*
#237000
1!
1*
b1110 @
#238000
0!
0*
#239000
1!
1*
b1111 @
#240000
0!
0*
#241000
1!
1*
b10000 @
#242000
0!
0*
#243000
1!
1*
b10001 @
#244000
0!
0*
#245000
1!
1*
b10010 @
#246000
0!
0*
#247000
1!
1*
b10011 @
#248000
0!
0*
#249000
1!
1*
b10100 @
#250000
0!
0*
#251000
1!
1*
b10101 @
#252000
0!
0*
#253000
1!
1*
b10110 @
#254000
0!
0*
#255000
1!
1*
b10111 @
#256000
0!
0*
#257000
1!
1*
b11000 @
#258000
0!
0*
#259000
1!
1*
b11001 @
#260000
0!
0*
#261000
1!
1*
b0 @
1>
#262000
0!
0*
#263000
1!
1*
b1 @
b11 ?
1:
#264000
0!
0*
#265000
1!
1*
b10 @
#266000
0!
0*
#267000
1!
1*
b11 @
#268000
0!
0*
#269000
1!
1*
b100 @
#270000
0!
0*
#271000
1!
1*
b101 @
#272000
0!
0*
#273000
1!
1*
b110 @
#274000
0!
0*
#275000
1!
1*
b111 @
#276000
0!
0*
#277000
1!
1*
b1000 @
#278000
0!
0*
#279000
1!
1*
b1001 @
#280000
0!
0*
#281000
1!
1*
b1010 @
#282000
0!
0*
#283000
1!
1*
b1011 @
#284000
0!
0*
#285000
1!
1*
b1100 @
#286000
0!
0*
#287000
1!
1*
b1101 @
#288000
0!
0*
#289000
1!
1*
b1110 @
#290000
0!
0*
#291000
1!
1*
b1111 @
#292000
0!
0*
#293000
1!
1*
b10000 @
#294000
0!
0*
#295000
1!
1*
b10001 @
#296000
0!
0*
#297000
1!
1*
b10010 @
#298000
0!
0*
#299000
1!
1*
b10011 @
#300000
0!
0*
#301000
1!
1*
b10100 @
#302000
0!
0*
#303000
1!
1*
b10101 @
#304000
0!
0*
#305000
1!
1*
b10110 @
#306000
0!
0*
#307000
1!
1*
b10111 @
#308000
0!
0*
#309000
1!
1*
b11000 @
#310000
0!
0*
#311000
1!
1*
b11001 @
#312000
0!
0*
#313000
1!
1*
b0 @
0>
#314000
0!
0*
#315000
1!
1*
b1 @
#316000
0!
0*
#317000
1!
1*
b10 @
#318000
0!
0*
#319000
1!
1*
b11 @
#320000
0!
0*
#321000
1!
1*
b100 @
#322000
0!
0*
#323000
1!
1*
b101 @
#324000
0!
0*
#325000
1!
1*
b110 @
#326000
0!
0*
#327000
1!
1*
b111 @
#328000
0!
0*
#329000
1!
1*
b1000 @
#330000
0!
0*
#331000
1!
1*
b1001 @
#332000
0!
0*
#333000
1!
1*
b1010 @
#334000
0!
0*
#335000
1!
1*
b1011 @
#336000
0!
0*
#337000
1!
1*
b1100 @
#338000
0!
0*
#339000
1!
1*
b1101 @
#340000
0!
0*
#341000
1!
1*
b1110 @
#342000
0!
0*
#343000
1!
1*
b1111 @
#344000
0!
0*
#345000
1!
1*
b10000 @
#346000
0!
0*
#347000
1!
1*
b10001 @
#348000
0!
0*
#349000
1!
1*
b10010 @
#350000
0!
0*
#351000
1!
1*
b10011 @
#352000
0!
0*
#353000
1!
1*
b10100 @
#354000
0!
0*
#355000
1!
1*
b10101 @
#356000
0!
0*
#357000
1!
1*
b10110 @
#358000
0!
0*
#359000
1!
1*
b10111 @
#360000
0!
0*
#361000
1!
1*
b11000 @
#362000
0!
0*
#363000
1!
1*
b11001 @
#364000
0!
0*
#365000
1!
1*
b0 @
1>
#366000
0!
0*
#367000
1!
1*
b1 @
b100 ?
0:
09
18
#368000
0!
0*
#369000
1!
1*
b10 @
#370000
0!
0*
#371000
1!
1*
b11 @
#372000
0!
0*
#373000
1!
1*
b100 @
#374000
0!
0*
#375000
1!
1*
b101 @
#376000
0!
0*
#377000
1!
1*
b110 @
#378000
0!
0*
#379000
1!
1*
b111 @
#380000
0!
0*
#381000
1!
1*
b1000 @
#382000
0!
0*
#383000
1!
1*
b1001 @
#384000
0!
0*
#385000
1!
1*
b1010 @
#386000
0!
0*
#387000
1!
1*
b1011 @
#388000
0!
0*
#389000
1!
1*
b1100 @
#390000
0!
0*
#391000
1!
1*
b1101 @
#392000
0!
0*
#393000
1!
1*
b1110 @
#394000
0!
0*
#395000
1!
1*
b1111 @
#396000
0!
0*
#397000
1!
1*
b10000 @
#398000
0!
0*
#399000
1!
1*
b10001 @
#400000
0!
0*
#401000
1!
1*
b10010 @
#402000
0!
0*
#403000
1!
1*
b10011 @
#404000
0!
0*
#405000
1!
1*
b10100 @
#406000
0!
0*
#407000
1!
1*
b10101 @
#408000
0!
0*
#409000
1!
1*
b10110 @
#410000
0!
0*
#411000
1!
1*
b10111 @
#412000
0!
0*
#413000
1!
1*
b11000 @
#414000
0!
0*
#415000
1!
1*
b11001 @
#416000
0!
0*
#417000
1!
1*
b0 @
0>
#418000
0!
0*
#419000
1!
1*
b1 @
#420000
0!
0*
#421000
1!
1*
b10 @
#422000
0!
0*
#423000
1!
1*
b11 @
#424000
0!
0*
#425000
1!
1*
b100 @
#426000
0!
0*
#427000
1!
1*
b101 @
#428000
0!
0*
#429000
1!
1*
b110 @
#430000
0!
0*
#431000
1!
1*
b111 @
#432000
0!
0*
#433000
1!
1*
b1000 @
#434000
0!
0*
#435000
1!
1*
b1001 @
#436000
0!
0*
#437000
1!
1*
b1010 @
#438000
0!
0*
#439000
1!
1*
b1011 @
#440000
0!
0*
#441000
1!
1*
b1100 @
#442000
0!
0*
#443000
1!
1*
b1101 @
#444000
0!
0*
#445000
1!
1*
b1110 @
#446000
0!
0*
#447000
1!
1*
b1111 @
#448000
0!
0*
#449000
1!
1*
b10000 @
#450000
0!
0*
#451000
1!
1*
b10001 @
#452000
0!
0*
#453000
1!
1*
b10010 @
#454000
0!
0*
#455000
1!
1*
b10011 @
#456000
0!
0*
#457000
1!
1*
b10100 @
#458000
0!
0*
#459000
1!
1*
b10101 @
#460000
0!
0*
#461000
1!
1*
b10110 @
#462000
0!
0*
#463000
1!
1*
b10111 @
#464000
0!
0*
#465000
1!
1*
b11000 @
#466000
0!
0*
#467000
1!
1*
b11001 @
#468000
0!
0*
#469000
1!
1*
b0 @
1>
#470000
0!
0*
#471000
1!
1*
b1 @
b101 ?
1:
#472000
0!
0*
#473000
1!
1*
b10 @
#474000
0!
0*
#475000
1!
1*
b11 @
#476000
0!
0*
#477000
1!
1*
b100 @
#478000
0!
0*
#479000
1!
1*
b101 @
#480000
0!
0*
#481000
1!
1*
b110 @
#482000
0!
0*
#483000
1!
1*
b111 @
#484000
0!
0*
#485000
1!
1*
b1000 @
#486000
0!
0*
#487000
1!
1*
b1001 @
#488000
0!
0*
#489000
1!
1*
b1010 @
#490000
0!
0*
#491000
1!
1*
b1011 @
#492000
0!
0*
#493000
1!
1*
b1100 @
#494000
0!
0*
#495000
1!
1*
b1101 @
#496000
0!
0*
#497000
1!
1*
b1110 @
#498000
0!
0*
#499000
1!
1*
b1111 @
#500000
0!
0*
#501000
1!
1*
b10000 @
#502000
0!
0*
#503000
1!
1*
b10001 @
#504000
0!
0*
#505000
1!
1*
b10010 @
#506000
0!
0*
#507000
1!
1*
b10011 @
#508000
0!
0*
#509000
1!
1*
b10100 @
#510000
0!
0*
#511000
1!
1*
b10101 @
#512000
0!
0*
#513000
1!
1*
b10110 @
#514000
0!
0*
#515000
1!
1*
b10111 @
#516000
0!
0*
#517000
1!
1*
b11000 @
#518000
0!
0*
#519000
1!
1*
b11001 @
#520000
0!
0*
#521000
1!
1*
b0 @
0>
#522000
0!
0*
#523000
1!
1*
b1 @
#524000
0!
0*
#525000
1!
1*
b10 @
#526000
0!
0*
#527000
1!
1*
b11 @
#528000
0!
0*
#529000
1!
1*
b100 @
#530000
0!
0*
#531000
1!
1*
b101 @
#532000
0!
0*
#533000
1!
1*
b110 @
#534000
0!
0*
#535000
1!
1*
b111 @
#536000
0!
0*
#537000
1!
1*
b1000 @
#538000
0!
0*
#539000
1!
1*
b1001 @
#540000
0!
0*
#541000
1!
1*
b1010 @
#542000
0!
0*
#543000
1!
1*
b1011 @
#544000
0!
0*
#545000
1!
1*
b1100 @
#546000
0!
0*
#547000
1!
1*
b1101 @
#548000
0!
0*
#549000
1!
1*
b1110 @
#550000
0!
0*
#551000
1!
1*
b1111 @
#552000
0!
0*
#553000
1!
1*
b10000 @
#554000
0!
0*
#555000
1!
1*
b10001 @
#556000
0!
0*
#557000
1!
1*
b10010 @
#558000
0!
0*
#559000
1!
1*
b10011 @
#560000
0!
0*
#561000
1!
1*
b10100 @
#562000
0!
0*
#563000
1!
1*
b10101 @
#564000
0!
0*
#565000
1!
1*
b10110 @
#566000
0!
0*
#567000
1!
1*
b10111 @
#568000
0!
0*
#569000
1!
1*
b11000 @
#570000
0!
0*
#571000
1!
1*
b11001 @
#572000
0!
0*
#573000
1!
1*
b0 @
1>
#574000
0!
0*
#575000
1!
1*
b1 @
b110 ?
0:
19
#576000
0!
0*
#577000
1!
1*
b10 @
#578000
0!
0*
#579000
1!
1*
b11 @
#580000
0!
0*
#581000
1!
1*
b100 @
#582000
0!
0*
#583000
1!
1*
b101 @
#584000
0!
0*
#585000
1!
1*
b110 @
#586000
0!
0*
#587000
1!
1*
b111 @
#588000
0!
0*
#589000
1!
1*
b1000 @
#590000
0!
0*
#591000
1!
1*
b1001 @
#592000
0!
0*
#593000
1!
1*
b1010 @
#594000
0!
0*
#595000
1!
1*
b1011 @
#596000
0!
0*
#597000
1!
1*
b1100 @
#598000
0!
0*
#599000
1!
1*
b1101 @
#600000
0!
0*
#601000
1!
1*
b1110 @
#602000
0!
0*
#603000
1!
1*
b1111 @
#604000
0!
0*
#605000
1!
1*
b10000 @
#606000
0!
0*
#607000
1!
1*
b10001 @
#608000
0!
0*
#609000
1!
1*
b10010 @
#610000
0!
0*
#611000
1!
1*
b10011 @
#612000
0!
0*
#613000
1!
1*
b10100 @
#614000
0!
0*
#615000
1!
1*
b10101 @
#616000
0!
0*
#617000
1!
1*
b10110 @
#618000
0!
0*
#619000
1!
1*
b10111 @
#620000
0!
0*
#621000
1!
1*
b11000 @
#622000
0!
0*
#623000
1!
1*
b11001 @
#624000
0!
0*
#625000
1!
1*
b0 @
0>
#626000
0!
0*
#627000
1!
1*
b1 @
#628000
0!
0*
#629000
1!
1*
b10 @
#630000
0!
0*
#631000
1!
1*
b11 @
#632000
0!
0*
#633000
1!
1*
b100 @
#634000
0!
0*
#635000
1!
1*
b101 @
#636000
0!
0*
#637000
1!
1*
b110 @
#638000
0!
0*
#639000
1!
1*
b111 @
#640000
0!
0*
#641000
1!
1*
b1000 @
#642000
0!
0*
#643000
1!
1*
b1001 @
#644000
0!
0*
#645000
1!
1*
b1010 @
#646000
0!
0*
#647000
1!
1*
b1011 @
#648000
0!
0*
#649000
1!
1*
b1100 @
#650000
0!
0*
#651000
1!
1*
b1101 @
#652000
0!
0*
#653000
1!
1*
b1110 @
#654000
0!
0*
#655000
1!
1*
b1111 @
#656000
0!
0*
#657000
1!
1*
b10000 @
#658000
0!
0*
#659000
1!
1*
b10001 @
#660000
0!
0*
#661000
1!
1*
b10010 @
#662000
0!
0*
#663000
1!
1*
b10011 @
#664000
0!
0*
#665000
1!
1*
b10100 @
#666000
0!
0*
#667000
1!
1*
b10101 @
#668000
0!
0*
#669000
1!
1*
b10110 @
#670000
0!
0*
#671000
1!
1*
b10111 @
#672000
0!
0*
#673000
1!
1*
b11000 @
#674000
0!
0*
#675000
1!
1*
b11001 @
#676000
0!
0*
#677000
1!
1*
b0 @
1>
#678000
0!
0*
#679000
1!
1*
b1 @
b111 ?
1:
#680000
0!
0*
#681000
1!
1*
b10 @
#682000
0!
0*
#683000
1!
1*
b11 @
#684000
0!
0*
#685000
1!
1*
b100 @
#686000
0!
0*
#687000
1!
1*
b101 @
#688000
0!
0*
#689000
1!
1*
b110 @
#690000
0!
0*
#691000
1!
1*
b111 @
#692000
0!
0*
#693000
1!
1*
b1000 @
#694000
0!
0*
#695000
1!
1*
b1001 @
#696000
0!
0*
#697000
1!
1*
b1010 @
#698000
0!
0*
#699000
1!
1*
b1011 @
#700000
0!
0*
#701000
1!
1*
b1100 @
#702000
0!
0*
#703000
1!
1*
b1101 @
#704000
0!
0*
#705000
1!
1*
b1110 @
#706000
0!
0*
#707000
1!
1*
b1111 @
#708000
0!
0*
#709000
1!
1*
b10000 @
#710000
0!
0*
#711000
1!
1*
b10001 @
#712000
0!
0*
#713000
1!
1*
b10010 @
#714000
0!
0*
#715000
1!
1*
b10011 @
#716000
0!
0*
#717000
1!
1*
b10100 @
#718000
0!
0*
#719000
1!
1*
b10101 @
#720000
0!
0*
#721000
1!
1*
b10110 @
#722000
0!
0*
#723000
1!
1*
b10111 @
#724000
0!
0*
#725000
1!
1*
b11000 @
#726000
0!
0*
#727000
1!
1*
b11001 @
#728000
0!
0*
#729000
1!
1*
b0 @
0>
#730000
0!
0*
#731000
1!
1*
b1 @
#732000
0!
0*
#733000
1!
1*
b10 @
#734000
0!
0*
#735000
1!
1*
b11 @
#736000
0!
0*
#737000
1!
1*
b100 @
#738000
0!
0*
#739000
1!
1*
b101 @
#740000
0!
0*
#741000
1!
1*
b110 @
#742000
0!
0*
#743000
1!
1*
b111 @
#744000
0!
0*
#745000
1!
1*
b1000 @
#746000
0!
0*
#747000
1!
1*
b1001 @
#748000
0!
0*
#749000
1!
1*
b1010 @
#750000
0!
0*
#751000
1!
1*
b1011 @
#752000
0!
0*
#753000
1!
1*
b1100 @
#754000
0!
0*
#755000
1!
1*
b1101 @
#756000
0!
0*
#757000
1!
1*
b1110 @
#758000
0!
0*
#759000
1!
1*
b1111 @
#760000
0!
0*
#761000
1!
1*
b10000 @
#762000
0!
0*
#763000
1!
1*
b10001 @
#764000
0!
0*
#765000
1!
1*
b10010 @
#766000
0!
0*
#767000
1!
1*
b10011 @
#768000
0!
0*
#769000
1!
1*
b10100 @
#770000
0!
0*
#771000
1!
1*
b10101 @
#772000
0!
0*
#773000
1!
1*
b10110 @
#774000
0!
0*
#775000
1!
1*
b10111 @
#776000
0!
0*
#777000
1!
1*
b11000 @
#778000
0!
0*
#779000
1!
1*
b11001 @
#780000
0!
0*
#781000
1!
1*
b0 @
1>
#782000
0!
0*
#783000
1!
1*
b1 @
b1000 ?
0:
09
08
17
#784000
0!
0*
#785000
1!
1*
b10 @
#786000
0!
0*
#787000
1!
1*
b11 @
#788000
0!
0*
#789000
1!
1*
b100 @
#790000
0!
0*
#791000
1!
1*
b101 @
#792000
0!
0*
#793000
1!
1*
b110 @
#794000
0!
0*
#795000
1!
1*
b111 @
#796000
0!
0*
#797000
1!
1*
b1000 @
#798000
0!
0*
#799000
1!
1*
b1001 @
#800000
0!
0*
#801000
1!
1*
b1010 @
#802000
0!
0*
#803000
1!
1*
b1011 @
#804000
0!
0*
#805000
1!
1*
b1100 @
#806000
0!
0*
#807000
1!
1*
b1101 @
#808000
0!
0*
#809000
1!
1*
b1110 @
#810000
0!
0*
#811000
1!
1*
b1111 @
#812000
0!
0*
#813000
1!
1*
b10000 @
#814000
0!
0*
#815000
1!
1*
b10001 @
#816000
0!
0*
#817000
1!
1*
b10010 @
#818000
0!
0*
#819000
1!
1*
b10011 @
#820000
0!
0*
#821000
1!
1*
b10100 @
#822000
0!
0*
#823000
1!
1*
b10101 @
#824000
0!
0*
#825000
1!
1*
b10110 @
#826000
0!
0*
#827000
1!
1*
b10111 @
#828000
0!
0*
#829000
1!
1*
b11000 @
#830000
0!
0*
#831000
1!
1*
b11001 @
#832000
0!
0*
#833000
1!
1*
b0 @
0>
#834000
0!
0*
#835000
1!
1*
b1 @
#836000
0!
0*
#837000
1!
1*
b10 @
#838000
0!
0*
#839000
1!
1*
b11 @
#840000
0!
0*
#841000
1!
1*
b100 @
#842000
0!
0*
#843000
1!
1*
b101 @
#844000
0!
0*
#845000
1!
1*
b110 @
#846000
0!
0*
#847000
1!
1*
b111 @
#848000
0!
0*
#849000
1!
1*
b1000 @
#850000
0!
0*
#851000
1!
1*
b1001 @
#852000
0!
0*
#853000
1!
1*
b1010 @
#854000
0!
0*
#855000
1!
1*
b1011 @
#856000
0!
0*
#857000
1!
1*
b1100 @
#858000
0!
0*
#859000
1!
1*
b1101 @
#860000
0!
0*
#861000
1!
1*
b1110 @
#862000
0!
0*
#863000
1!
1*
b1111 @
#864000
0!
0*
#865000
1!
1*
b10000 @
#866000
0!
0*
#867000
1!
1*
b10001 @
#868000
0!
0*
#869000
1!
1*
b10010 @
#870000
0!
0*
#871000
1!
1*
b10011 @
#872000
0!
0*
#873000
1!
1*
b10100 @
#874000
0!
0*
#875000
1!
1*
b10101 @
#876000
0!
0*
#877000
1!
1*
b10110 @
#878000
0!
0*
#879000
1!
1*
b10111 @
#880000
0!
0*
#881000
1!
1*
b11000 @
#882000
0!
0*
#883000
1!
1*
b11001 @
#884000
0!
0*
#885000
1!
1*
b0 @
1>
#886000
0!
0*
#887000
1!
1*
b1 @
b1001 ?
1:
#888000
0!
0*
#889000
1!
1*
b10 @
#890000
0!
0*
#891000
1!
1*
b11 @
#892000
0!
0*
#893000
1!
1*
b100 @
#894000
0!
0*
#895000
1!
1*
b101 @
#896000
0!
0*
#897000
1!
1*
b110 @
#898000
0!
0*
#899000
1!
1*
b111 @
#900000
0!
0*
#901000
1!
1*
b1000 @
#902000
0!
0*
#903000
1!
1*
b1001 @
#904000
0!
0*
#905000
1!
1*
b1010 @
#906000
0!
0*
#907000
1!
1*
b1011 @
#908000
0!
0*
#909000
1!
1*
b1100 @
#910000
0!
0*
#911000
1!
1*
b1101 @
#912000
0!
0*
#913000
1!
1*
b1110 @
#914000
0!
0*
#915000
1!
1*
b1111 @
#916000
0!
0*
#917000
1!
1*
b10000 @
#918000
0!
0*
#919000
1!
1*
b10001 @
#920000
0!
0*
#921000
1!
1*
b10010 @
#922000
0!
0*
