MPEI_Bachelor/projects/Лр4/КМ4/Register/register.v
module register(clk, res, set, D, outstate, M);

input     clk, res; 
input [2:0]    set;
input [15:0]     D; // Ввод начального значения
input [3:0]      M;

reg [15:0]   Q; // Результат
output  [15:0] outstate;

localparam LOAD = 0, LOG_RIGHT = 1, LOG_LEFT = 2, ARIF_RIGHT = 3, ARIF_LEFT = 4;

reg [2:0] state, nextstate;

//логика переключений
always @(posedge clk, negedge res)
    if(!res)
        state <= LOAD;
    else
        state <= nextstate;

//логика работы автомата
always @(*)
    case(state)
        LOAD:  
            if (set == 0) begin
				   Q = D;
					nextstate = LOAD; end
            else                                // Выбор действия в начальном состоянии
                case(set)
                    1: nextstate = LOG_RIGHT;
                    2: nextstate = LOG_LEFT;
                    3: nextstate = ARIF_RIGHT;
                    4: nextstate = ARIF_LEFT;
                    default : nextstate = LOAD;
            endcase
        LOG_RIGHT: 
            if (set == 1) begin
                Q = D >> M;
					 nextstate = LOG_RIGHT; end
            else 
                case(set)
                    0: nextstate = LOAD;
                    2: nextstate = LOG_LEFT;
                    3: nextstate = ARIF_RIGHT;
                    4: nextstate = ARIF_LEFT;
                    default : nextstate = LOG_RIGHT;
                endcase            
        LOG_LEFT:  
            if (set == 2) begin
                Q = D << M;
					 nextstate = LOG_LEFT; end
            else 
                case(set)
                    0: nextstate = LOAD;
                    1: nextstate = LOG_RIGHT;
                    3: nextstate = ARIF_RIGHT;
                    4: nextstate = ARIF_LEFT;
                    default : nextstate = LOG_LEFT;
                endcase            
        ARIF_RIGHT:
            if (set == 3) begin
                Q = D >>> M;
					 nextstate = ARIF_RIGHT; end
            else 
                case(set)
                    0: nextstate = LOAD;
                    1: nextstate = LOG_RIGHT;
                    2: nextstate = LOG_LEFT;
                    4: nextstate = ARIF_LEFT;
                    default : nextstate = ARIF_RIGHT;
                endcase      
        ARIF_LEFT:
            if (set == 4) begin
                Q = D <<< M;
					 					 nextstate = ARIF_LEFT; end
            else 
                case(set)
                    0: nextstate = LOAD;
                    1: nextstate = LOG_RIGHT;
                    2: nextstate = LOG_LEFT;
                    3: nextstate = ARIF_RIGHT;
                    default : nextstate = ARIF_LEFT;
                endcase                           
        default : nextstate = LOAD;
    endcase

//логика формирования выхода
assign outstate = Q;

endmodule

MPEI_Bachelor/projects/Лр4/КМ4/Register/tb_register.v
`include "register.v"
`timescale 1ns / 1ns
module tb_register  ();

reg clk, res;
reg [15:0] D;
reg [3:0] M;
reg [2:0] set;
reg enable;

wire [15:0] Q;

register DUT (.clk(clk), .res(res), .M(M), .D(D), .set(set), .outstate(Q));

initial begin
  clk = 0;
  forever #5 clk = ~clk;
end

initial begin
  res = 1;
  repeat(2) #1 res = ~res;
end

initial begin
M = 3; // Количество сдвигаемых разрядов
D  =  16'b0010_0110_1001; // Входное число

end

// Задаем состояние автомата
initial begin
        set = 0;
    #30 set = 1;
    #30 set = 2;
    #30 set = 3;
    #30 set = 4;
end

initial begin
	#200  $display("Testbench is OK!");
          $finish;
end

//Для симуляция в Iverilog		 
initial begin            
    $dumpfile("qqq.vcd");
    $dumpvars;
end
endmodule

MPEI_Bachelor/projects/Лр4/КМ4/Register/qqq.vcd
$date
	Thu Dec 08 16:30:51 2022
$end
$version
	Icarus Verilog
$end
$timescale
	1ns
$end
$scope module tb_register $end
$var wire 16 ! Q [15:0] $end
$var reg 16 " D [15:0] $end
$var reg 4 # M [3:0] $end
$var reg 1 $ clk $end
$var reg 1 % res $end
$var reg 3 & set [2:0] $end
$scope module DUT $end
$var wire 16 ' D [15:0] $end
$var wire 4 ( M [3:0] $end
$var wire 1 $ clk $end
$var wire 16 ) outstate [15:0] $end
$var wire 1 % res $end
$var wire 3 * set [2:0] $end
$var parameter 32 + ARIF_LEFT $end
$var parameter 32 , ARIF_RIGHT $end
$var parameter 32 - LOAD $end
$var parameter 32 . LOG_LEFT $end
$var parameter 32 / LOG_RIGHT $end
$var reg 16 0 Q [15:0] $end
$var reg 3 1 nextstate [2:0] $end
$var reg 3 2 state [2:0] $end
$upscope $end
$upscope $end
$enddefinitions $end
$comment Show the parameter values. $end
$dumpall
b1 /
b10 .
b0 -
b11 ,
b100 +
$end
#0
$dumpvars
bx 2
b0 1
bx 0
b0 *
bx )
b11 (
b1001101001 '
b0 &
1%
0$
b11 #
b1001101001 "
bx !
$end
#1
b1001101001 !
b1001101001 )
b1001101001 0
b0 2
0%
#2
1%
#5
1$
#10
0$
#15
1$
#20
0$
#25
1$
#30
b1 1
0$
b1 &
b1 *
#35
b1001101 !
b1001101 )
b1001101 0
b1 2
1$
#40
0$
#45
1$
#50
0$
#55
1$
#60
b10 1
0$
b10 &
b10 *
#65
b1001101001000 !
b1001101001000 )
b1001101001000 0
b10 2
1$
#70
0$
#75
1$
#80
0$
#85
1$
#90
b11 1
0$
b11 &
b11 *
#95
b1001101 !
b1001101 )
b1001101 0
b11 2
1$
#100
0$
#105
1$
#110
0$
#115
1$
#120
b100 1
0$
b100 &
b100 *
#125
b1001101001000 !
b1001101001000 )
b1001101001000 0
b100 2
1$
