MPEI_Bachelor/projects/Лр4/КМ4/Universal_Shift_Register_so_vsemi_perehodami/Universal_Shift_Register.v
module Universal_Shift_Register #(parameter WIDTH = 15) // параметр позволяет быстро менять разрядность входного числа
                                (clk, res, D, out_state, set, M, enable);

localparam parall_out = 1, logic_shft_left = 2, logic_shft_right = 3, ring_shft_left = 4, ring_shft_right = 5, serial_out  = 6;

input [WIDTH:0] D; //Входное число
input     [2:0] set; //Выбор действия
input       res, clk;
input    [WIDTH:0] M; //Количество сдвигаемых разрядов
input enable;

reg [WIDTH:0] Q; //Результат 
reg [2:0] state, next_state;

output [WIDTH:0] out_state; 

always @(posedge clk, negedge res) 
begin
  if (!res)
    state <= parall_out;
  else
    state <= next_state;
end

always @(*) //Логика автомата
    case (state)
        parall_out:  
            if (set == 1) 
				begin
				   Q = D;
					next_state = parall_out; 
				end
            else                                // Выбор действия в начальном состоянии
                case(set)
                    2: next_state = logic_shft_left;
                    3: next_state = logic_shft_right;
                    4: next_state = ring_shft_left;
                    5: next_state = ring_shft_right;
					6: next_state = serial_out;
                    default : next_state = parall_out;
            endcase
        logic_shft_left:
            if (set == 2) 
				begin
				    Q = D << M; //Логический сдвиг влево на М разрадов
					next_state = logic_shft_left; 
				end
            else                                // Выбор действия в начальном состоянии
                case(set)
                    1: next_state = parall_out;
                    3: next_state = logic_shft_right;
                    4: next_state = ring_shft_left;
                    5: next_state = ring_shft_right;
					6: next_state = serial_out;
                    default : next_state = parall_out;
				endcase
    	logic_shft_right:
    		if(set == 3)
    			begin
    	            Q = D >> M; //Логический сдвиг вправо на М разрадов
                    next_state = ring_shft_right;
    		    end
			else
                case(set)
                    1: next_state = parall_out;
					2: next_state = logic_shft_left;
                    4: next_state = ring_shft_left;
                    5: next_state = ring_shft_right;
					6: next_state = serial_out;
                    default : next_state = parall_out;
				endcase
        ring_shft_left:
    		if(set == 4)
                begin
                    Q = {D[WIDTH-2:0], D[WIDTH-1]}; // Кольцевой сдвиг влево 
                    next_state = ring_shft_left;
    			end
			else
				case(set)
                    1: next_state = parall_out;
					2: next_state = logic_shft_left;
                    3: next_state = logic_shft_right;
                    5: next_state = ring_shft_right;
					6: next_state = serial_out;
                    default : next_state = parall_out;
				endcase
    	ring_shft_right:
    		if(set == 5)
    				begin
    	                Q = {D[0], D[WIDTH-1:1]}; // Кольцевой сдвиг вправо 
                        next_state = ring_shft_right;
    			    end
			else	
				case(set)
                    1: next_state = parall_out;
					2: next_state = logic_shft_left;
                    3: next_state = logic_shft_right;
                    4: next_state = ring_shft_left;
					6: next_state = serial_out;
                    default : next_state = parall_out;
				endcase 
		serial_out:
    		if(set == 6) // Последовательный вывод
    				begin
						next_state = serial_out;
						Q = qQ[0];
    			    end
			else 
			    case(set)
                    1: next_state = parall_out;
					2: next_state = logic_shft_left;
                    3: next_state = logic_shft_right;
                    4: next_state = ring_shft_left;
                    5: next_state = ring_shft_right;
                    default : next_state = parall_out;
				endcase
		default : next_state = parall_out;
	endcase

reg [WIDTH:0]qQ;

// Логика для последовательного вывода
always @ (posedge clk, negedge res) // По приходу тактового импульса, в выходную переменную будет записываться [0] разряд входного числа
	if (!res)
    	qQ <= 0;
    else if ((set == serial_out) && (enable == 1)) 	// enable служит для разрешения записи входного числа в промежуточную REG переменную qQ
		qQ <= D;  
	else if ((set == serial_out) && (enable == 0)) 
		begin
			qQ <= {qQ[0], qQ[WIDTH:1]}; // Сдвигаем входное число вправо для передачи следующего разряда
		end

// Логика для реализации передачи результата
assign out_state = Q;

endmodule

MPEI_Bachelor/projects/Лр4/КМ4/Universal_Shift_Register_so_vsemi_perehodami/tb_universal_shift_register.v
`include "Universal_Shift_Register.v"
`timescale 1ns / 1ns
module tb_universal_shift_register #(parameter WIDTH = 15)
                                                       ();
reg clk, res;
reg [WIDTH:0] Data, M;
reg [2:0] set;
reg enable;

wire [WIDTH:0] Q;

Universal_Shift_Register DUT (.clk(clk), .res(res), .M(M), .D(Data), .set(set), .out_state(Q), .enable(enable));

initial begin
  clk = 0;
  forever #5 clk = ~clk;
end

initial begin
  res = 1;
  repeat(2) #1 res = ~res;
end

initial begin
  M = 2; // Количество сдвигаемых разрядов при логическом сдвиге
	Data  =  16'b101001011110; // Входное число
end

// Задаем состояние автомата
initial begin
        set = 1;
    #20 set = 2;
    #20 set = 3;
    #20 set = 4;
    #20 set = 5;
    #20 set = 6;
    #50 set = 3;
    #20 set = 4;

end

//Разрешение загрузки для последовательного вывода входного числа
initial  
    begin  
      enable = 1'b0;  
      #100 enable = 1'b1;  
      #10 enable = 1'b0;  
    end  

initial begin
	#200  $display("Testbench is OK!");
        $finish;
end

//Для симуляция в Iverilog		 
initial begin            
    $dumpfile("qqq.vcd");
    $dumpvars;
end
endmodule

MPEI_Bachelor/projects/Лр4/КМ4/Universal_Shift_Register_so_vsemi_perehodami/qqq.vcd
$date
	Sun Dec 18 12:38:53 2022
$end
$version
	Icarus Verilog
$end
$timescale
	1ns
$end
$scope module tb_universal_shift_register $end
$var wire 16 ! Q [15:0] $end
$var parameter 32 " WIDTH $end
$var reg 16 # Data [15:0] $end
$var reg 16 $ M [15:0] $end
$var reg 1 % clk $end
$var reg 1 & enable $end
$var reg 1 ' res $end
$var reg 3 ( set [2:0] $end
$scope module DUT $end
$var wire 16 ) D [15:0] $end
$var wire 16 * M [15:0] $end
$var wire 1 % clk $end
$var wire 1 & enable $end
$var wire 16 + out_state [15:0] $end
$var wire 1 ' res $end
$var wire 3 , set [2:0] $end
$var parameter 32 - WIDTH $end
$var parameter 32 . logic_shft_left $end
$var parameter 32 / logic_shft_right $end
$var parameter 32 0 parall_out $end
$var parameter 32 1 ring_shft_left $end
$var parameter 32 2 ring_shft_right $end
$var parameter 32 3 serial_out $end
$var reg 16 4 Q [15:0] $end
$var reg 3 5 next_state [2:0] $end
$var reg 16 6 qQ [15:0] $end
$var reg 3 7 state [2:0] $end
$upscope $end
$upscope $end
$enddefinitions $end
$comment Show the parameter values. $end
$dumpall
b110 3
b101 2
b100 1
b1 0
b11 /
b10 .
b1111 -
b1111 "
$end
#0
$dumpvars
bx 7
bx 6
b1 5
bx 4
b1 ,
bx +
b10 *
b101001011110 )
b1 (
1'
0&
0%
b10 $
b101001011110 #
bx !
$end
#1
b101001011110 !
b101001011110 +
b101001011110 4
b1 7
b0 6
0'
#2
1'
#5
1%
#10
0%
#15
1%
#20
b10 5
0%
b10 (
b10 ,
#25
b10100101111000 !
b10100101111000 +
b10100101111000 4
b10 7
1%
#30
0%
#35
1%
#40
b11 5
0%
b11 (
b11 ,
#45
b101 5
b1010010111 !
b1010010111 +
b1010010111 4
b11 7
1%
#50
0%
#55
b11 5
b101 7
1%
#60
b100 5
0%
b100 (
b100 ,
#65
b1010010111100 !
b1010010111100 +
b1010010111100 4
b100 7
1%
#70
0%
#75
1%
#80
b101 5
0%
b101 (
b101 ,
#85
b10100101111 !
b10100101111 +
b10100101111 4
b101 7
1%
#90
0%
#95
1%
#100
b110 5
0%
b110 (
b110 ,
1&
#105
b0 !
b0 +
b0 4
b101001011110 6
b110 7
1%
#110
0%
0&
#115
b1 !
b1 +
b1 4
b10100101111 6
1%
#120
0%
#125
b1000001010010111 6
1%
#130
0%
#135
b1100000101001011 6
1%
#140
0%
#145
b1110000010100101 6
1%
#150
b11 5
0%
b11 (
b11 ,
#155
b101 5
b1010010111 !
b1010010111 +
b1010010111 4
b11 7
1%
#160
0%
#165
b11 5
b101 7
1%
#170
b100 5
0%
b100 (
b100 ,
#175
b1010010111100 !
b1010010111100 +
b1010010111100 4
b100 7
1%
