MPEI_Magistracy/Term_2/ASIC_design/FIFO/src/rptr_empty.sv
module rptr_empty
    #(
    parameter ADDRSIZE = 4
    )(
    input  logic                    rclk,
    input  logic                    rrst_n,
    input  logic                    rinc,
    input  logic [ADDRSIZE  :0]     rq2_wptr,
    output logic                    rempty,
    output logic                    arempty,
    output logic [ADDRSIZE-1:0]     raddr,
    output logic [ADDRSIZE  :0]     rptr
    );

    logic [ADDRSIZE:0] rbin;
    logic [ADDRSIZE:0] rgraynext, rbinnext, rgraynextm1;
    logic              arempty_val, rempty_val;

    //-------------------
    // Указатель в коде Грэя
    //-------------------
    always_ff @(posedge rclk or negedge rrst_n) begin
      if (!rrst_n)
        {rbin, rptr} <= '0;
      else
        {rbin, rptr} <= {rbinnext, rgraynext};
    end

    // Указатель адреса чтения (можно использовать двоичный код для обращения к памяти)
    assign raddr     = rbin[ADDRSIZE-1:0];
    assign rbinnext  = rbin + (rinc & ~rempty);
    assign rgraynext = (rbinnext >> 1) ^ rbinnext;
    assign rgraynextm1 = ((rbinnext + 1'b1) >> 1) ^ (rbinnext + 1'b1);

    //---------------------------------------------------------------
    // FIFO пуст, когда указатель следующего rptr == синхронизованный wptr или при reset
    //---------------------------------------------------------------
    assign rempty_val = (rgraynext == rq2_wptr);
    assign arempty_val = (rgraynextm1 == rq2_wptr);

    always_ff @ (posedge rclk or negedge rrst_n) begin
      if (!rrst_n) begin
        arempty <= 1'b0;
        rempty  <= 1'b1;
      end else begin
        arempty <= arempty_val;
        rempty  <= rempty_val;
      end
    end
endmodule

MPEI_Magistracy/Term_two/ASIC_design/FIFO/src/sync_w2r.sv
module sync_w2r
  #(
    parameter ADDRSIZE = 4
    )(
    input  logic                rclk,
    input  logic                rrst_n,
    output logic [ADDRSIZE:0]   rq2_wptr,
    input  logic [ADDRSIZE:0]   wptr
    );

logic [ADDRSIZE:0] rq1_wptr;

always_ff @(posedge rclk or negedge rrst_n) begin
  if (!rrst_n) begin
    {rq2_wptr,rq1_wptr} <= '0;
  end else begin
    {rq2_wptr,rq1_wptr} <= {rq1_wptr,wptr};
  end
end

endmodule

MPEI_Magistracy/Term_two/ASIC_design/FIFO/src/sync_r2w.sv
module sync_r2w
  #(
    parameter ADDRSIZE = 4
  )
  (
    input  logic                wclk,
    input  logic                wrst_n,
    input  logic [ADDRSIZE:0]   rptr,
    output logic [ADDRSIZE:0]   wq2_rptr
  );

  logic [ADDRSIZE:0] wq1_rptr;

  always_ff @(posedge wclk or negedge wrst_n) begin
    if (!wrst_n)
      {wq2_rptr,wq1_rptr} <= '0;
    else
      {wq2_rptr,wq1_rptr} <= {wq1_rptr,rptr};
  end

endmodule

MPEI_Magistracy/Term_two/ASIC_design/FIFO/src/wptr_empty.sv
module wptr_full
	#(
		parameter ADDRSIZE = 4
	)(
		input  logic                    wclk,
		input  logic                    wrst_n,
		input  logic                    winc,
		input  logic [ADDRSIZE  :0]     wq2_rptr,
		output logic                    wfull,
		output logic                    awfull,
    output logic [ADDRSIZE-1:0]     waddr,
    output logic [ADDRSIZE  :0]     wptr
	);

    logic [ADDRSIZE:0] wbin;
    logic [ADDRSIZE:0] wgraynext, wbinnext, wgraynextp1;
    logic              awfull_val, wfull_val;

	// Указатель в коде Грэя
always_ff @(posedge wclk or negedge wrst_n) begin
  if (!wrst_n)
	  {wbin, wptr} <= 0;
  else
	{wbin, wptr} <= {wbinnext, wgraynext};
end

  // Указатель адреса для записи в память (можно использовать двоичный код для обращения к памяти)
assign waddr = wbin[ADDRSIZE-1:0];
assign wbinnext  = wbin + (winc & ~wfull);
assign wgraynext = (wbinnext >> 1) ^ wbinnext;
assign wgraynextp1 = ((wbinnext + 1'b1) >> 1) ^ (wbinnext + 1'b1);

    //------------------------------------------------------------------
    // Упрощённая версия трёх необходимых полных проверок:
    // assign wfull_val=((wgnext[ADDRSIZE] !=wq2_rptr[ADDRSIZE] ) &&
    //                   (wgnext[ADDRSIZE-1]  !=wq2_rptr[ADDRSIZE-1]) &&
    // (wgnext[ADDRSIZE-2:0]==wq2_rptr[ADDRSIZE-2:0]));
    //------------------------------------------------------------------

assign wfull_val = (wgraynext == {~wq2_rptr[ADDRSIZE:ADDRSIZE-1],wq2_rptr[ADDRSIZE-2:0]}); // Полный FIFO
assign awfull_val = (wgraynextp1 == {~wq2_rptr[ADDRSIZE:ADDRSIZE-1],wq2_rptr[ADDRSIZE-2:0]}); // Почти полный FIFO (есть ещё одно место под запись)

always_ff @(posedge wclk or negedge wrst_n) begin
  if (!wrst_n) begin
    awfull <= 1'b0;
    wfull  <= 1'b0;
  end else begin
    awfull <= awfull_val;
  wfull  <= wfull_val;
    end
end
endmodule

MPEI_Magistracy/Term_two/ASIC_design/FIFO/src/fifo_mem.sv
// За основу всего RTL взят код https://github.com/dpretet/async_fifo/

module fifo_mem
    #(
        parameter  DATASIZE = 8,    // Ширина слова
        parameter  ADDRSIZE = 4    // Количество бит адреса
    ) (
        input  logic                wclk,
        input  logic                wclken,
        input  logic [ADDRSIZE-1:0] waddr,
        input  logic [DATASIZE-1:0] wdata,
        input  logic                wfull,
        input  logic                rclk,
        input  logic                rclken,
        input  logic [ADDRSIZE-1:0] raddr,
        output logic [DATASIZE-1:0] rdata
    );

  localparam DEPTH = 1 << ADDRSIZE; // Глубина FIFO-буфера (количество слов)

  logic [DATASIZE-1:0] mem [0:DEPTH-1];
  logic [DATASIZE-1:0] rdata_r;

  always_ff @(posedge wclk) begin // Асинхронная запись данных в неполный FIFO
     if (wclken && !wfull)
       mem[waddr] <= wdata;
  end

  always_ff @(posedge rclk) begin // Асинхронное чтение данных из непустого FIFO
    if (rclken)
       rdata_r <= mem[raddr];
  end
    
  assign rdata = rdata_r;

  genvar idx;
  generate
    for (idx = 0; idx < 16; idx++) begin : dich
        logic [7:0] tmp;
        assign tmp = mem[idx];
    end
  endgenerate

endmodule

MPEI_Magistracy/Term_2/ASIC_design/FIFO/src/top.sv
module top 
#(
    parameter   DATASIZE = 8,    // Ширина слова
                ADDRSIZE = 4    // Количество бит адреса
) 
(
    input  logic [DATASIZE - 1 : 0] WDATA_I,   
    input  logic                    WINC_I,      
    input  logic                    WCLK_I,         
    input  logic                    WRST_N_I,          
    input  logic                    RINC_I,           
    input  logic                    RCLK_I,             
    input  logic                    RRST_N_I,   

    output logic [DATASIZE - 1 : 0] RDATA_O,       
    output logic                    WFULL_O,   
    output logic                    REMPTY_O,         
    output logic                    AREMPTY_O 
);

    logic [ADDRSIZE - 1 : 0 ]       waddr_w;
    logic [ADDRSIZE     : 0 ]       wq2_rptr_w;
    logic [ADDRSIZE     : 0 ]       rq2_wptr_w;
    logic [ADDRSIZE     : 0 ]       wptr_w;
    logic [ADDRSIZE - 1 : 0 ]       raddr_w;
    logic [ADDRSIZE     : 0 ]       rptr_w;
    logic                           wfull_w;
    logic                           wclken_w;
    logic                           rclken_w;

    always_comb begin
        wclken_w = !wfull_w  & WINC_I;
        WFULL_O  = wfull_w;
    end 
    
    fifo_mem
    #(
        .DATASIZE(DATASIZE),
        .ADDRSIZE(ADDRSIZE)
    )
    fifo_mem_inst
    (
        .wclk     ( WCLK_I     ),
        .wclken   ( wclken_w   ),
        .waddr    ( waddr_w    ),
        .wdata    ( WDATA_I    ),
        .wfull    ( wfull_w    ),
        .rclk     ( RCLK_I     ),
        .rclken   ( RINC_I     ),
        .raddr    ( raddr_w    ),
        .rdata    ( RDATA_O    )
    );

    wptr_full
    #(
        .ADDRSIZE ( ADDRSIZE   )
    )
    wptr_full_inst
    (
        .wclk     ( WCLK_I     ),     
        .wrst_n   ( WRST_N_I   ),       
        .winc     ( WINC_I     ),     
        .wq2_rptr ( wq2_rptr_w ),         
        .wfull    ( wfull_w    ),      
        .awfull   (            ),       
        .waddr    ( waddr_w    ),      
        .wptr     ( wptr_w     )       
    );

    sync_r2w
    #(
        .ADDRSIZE(ADDRSIZE)
    )
    sync_r2w_inst
    (
        .wclk     ( WCLK_I     ),
        .wrst_n   ( WRST_N_I   ),
        .rptr     ( rptr_w     ),
        .wq2_rptr ( wq2_rptr_w ) 
    );

    sync_w2r
    #(
        .ADDRSIZE(ADDRSIZE)
    )
    sync_w2r_inst
    (
        .rclk     ( WCLK_I     ),
        .rrst_n   ( WRST_N_I   ),
        .rq2_wptr ( rq2_wptr_w ),
        .wptr     ( wptr_w     ) 
    );

    rptr_empty
    #(
        .ADDRSIZE(ADDRSIZE)
    )
    rptr_empty_inst
    (
        .rclk     ( RCLK_I     ),     
        .rrst_n   ( RRST_N_I   ),   
        .rinc     ( RINC_I     ),     
        .rq2_wptr ( rq2_wptr_w ), 
        .rempty   ( REMPTY_O   ),   
        .arempty  ( AREMPTY_O  ),  
        .raddr    ( raddr_w    ),    
        .rptr     ( rptr_w     )      
    );
endmodule

MPEI_Magistracy/Term_two/ASIC_design/FIFO/tb/tb.sv
`timescale 1ps/1ps
`define WAVES_FILE "dump/wave.vcd"

import fifo_sim_pkg::*;

localparam DEPT_FIFO = 1 << ADDRSIZE;

module tb #(
    parameter DATASIZE = 8,
              ADDRSIZE = 4
) 
(
);
    logic [DATASIZE - 1 : 0] wdata_i;   
    logic                    wfull_o;   
    logic                    winc_i;      
    logic                    wclk_i;         
    logic                    wrst_n_i;          
    logic [DATASIZE - 1 : 0] rdata_o;       
    logic                    rinc_i;           
    logic                    rclk_i;             
    logic                    rrst_n_i;         
    logic                    rempty_o;         
    logic                    arempty_o; 

    int MIN_RST_TIME = 100;
    int MAX_RST_TIME = 150;

    int wrst_time;
    int rrst_time;
    int cnt_data_send;
    int cnt_data_rec;

    int timeout;

    // PLUSARGS
    int TGL_WRST_N = 1;
    int TGL_RRST_N = 1;
    int QTY_DATA   = 5;
    int TEST       = 0; 

    logic [DATASIZE - 1 : 0] wr_data_q [$];
    logic [DATASIZE - 1 : 0] rd_data_q [$];

    logic [DATASIZE-1:0] mem_tb [0:DEPT_FIFO-1];


    top 
    #(
        .DATASIZE  ( DATASIZE  ),
        .ADDRSIZE  ( ADDRSIZE  )
    )
    UUT
    (
        .WDATA_I   ( wdata_i   ), 
        .WFULL_O   ( wfull_o   ),
        .WINC_I    ( winc_i    ),  
        .WCLK_I    ( wclk_i    ),  
        .WRST_N_I  ( wrst_n_i  ),
        .RINC_I    ( rinc_i    ),  
        .RCLK_I    ( rclk_i    ),  
        .RRST_N_I  ( rrst_n_i  ),
        .RDATA_O   ( rdata_o   ), 
        .REMPTY_O  ( rempty_o  ),
        .AREMPTY_O ( arempty_o )
    );
    
    initial begin
        wdata_i   = 0;   
        winc_i    = 1;   
        wclk_i    = 0;   
        rinc_i    = 0;   
        rclk_i    = 0;   
        rinc_i    = 0;
    end

    task gen_clk_rd();
        forever begin
            #(CLK_RD_PERIOD / 2.0) rclk_i = ~rclk_i; //generate clk_rd signal
        end
    endtask

    task gen_clk_wr();
        #10
        forever begin
            #(CLK_WR_PERIOD / 2.0) wclk_i = ~wclk_i; //generate clk_wr signal
        end
    endtask

    task gen_wrst_n();
        wrst_n_i  = 0; 
        #10
        wrst_n_i  = 1; 
        #10
        wrst_n_i  = 0;
        #10

        case (TGL_WRST_N)
            0 : begin
                wrst_n_i = 0;
            end
            1 : begin
                wrst_n_i = 1;
            end
            2 : forever begin
                wrst_time = $urandom_range(MIN_RST_TIME, MAX_RST_TIME);
                wrst_n_i = 0;
                #wrst_time;
                wrst_n_i = 1;
                #wrst_time;
            end 
            default: begin
            end
        endcase
    endtask

    task gen_rrst_n();
        rrst_n_i  = 0;
        #10 
        rrst_n_i  = 1;
        #10
        rrst_n_i  = 0;
        #10

        case (TGL_RRST_N)
            0 : begin
                rrst_n_i = 0;
            end
            1 : begin
                rrst_n_i = 1;
            end
            2 : forever begin
                rrst_time = $urandom_range(MIN_RST_TIME, MAX_RST_TIME);
                rrst_n_i = 0;
                #rrst_time;
                rrst_n_i = 1;
                #rrst_time;
            end 
            default: begin
            end
        endcase
    endtask

    task rd_data();
        forever @(posedge rclk_i) begin
            if(rinc_i) begin
                cnt_data_rec++;
            end
        end
    endtask
    
    task gen_data();
        forever @(negedge wclk_i) begin
            wdata_i = $urandom_range(fifo_sim_pkg::min_data_val, fifo_sim_pkg::max_data_val);
            wr_data_q.push_back(wdata_i);
            cnt_data_send++;
        end
    endtask

    initial begin
        fork
            gen_clk_wr();
            gen_clk_rd();
            gen_wrst_n();
            gen_rrst_n();
            gen_data();
            rd_data();
            en_test();
        join_none
    end

    task en_test();
        forever @(posedge wclk_i) begin
            case (TEST)
                0 : begin
                    winc_i = 1;
                    rinc_i = 1;
                end
                1 : begin
                    if(cnt_data_send == 10) begin
                        // winc_i = 1;
                        rinc_i = 1;
                    end
                    // if(cnt_data_rec == 5) begin
                    //     rinc_i = 0;
                    //     winc_i = 1;
                    // end
                end 
                default: begin
                    $error("INCORRECT TEST_TUPE ! ! ! ! !", TEST);
                    $fatal;
                end
            endcase
        end
    endtask

    initial begin
        $dumpfile(`WAVES_FILE);
        $dumpvars;
        #10000 $finish();
    end
endmodule

MPEI_Magistracy/Term_two/ASIC_design/FIFO/dump/wave.vcd
$date
	Fri May 31 15:03:55 2024
$end
$version
	Icarus Verilog
$end
$timescale
	1ps
$end
$scope module tb $end
$var wire 1 ! wfull_o $end
$var wire 1 " rempty_o $end
$var wire 8 # rdata_o [7:0] $end
$var wire 1 $ arempty_o $end
$var parameter 32 % ADDRSIZE $end
$var parameter 32 & DATASIZE $end
$var reg 1 ' rclk_i $end
$var reg 1 ( rinc_i $end
$var reg 1 ) rrst_n_i $end
$var reg 1 * wclk_i $end
$var reg 8 + wdata_i [7:0] $end
$var reg 1 , winc_i $end
$var reg 1 - wrst_n_i $end
$var integer 32 . MAX_RST_TIME [31:0] $end
$var integer 32 / MIN_RST_TIME [31:0] $end
$var integer 32 0 QTY_DATA [31:0] $end
$var integer 32 1 TEST [31:0] $end
$var integer 32 2 TGL_RRST_N [31:0] $end
$var integer 32 3 TGL_WRST_N [31:0] $end
$var integer 32 4 cnt_data_rec [31:0] $end
$var integer 32 5 cnt_data_send [31:0] $end
$var integer 32 6 rrst_time [31:0] $end
$var integer 32 7 wrst_time [31:0] $end
$scope module UUT $end
$var wire 1 ' RCLK_I $end
$var wire 1 ( RINC_I $end
$var wire 1 ) RRST_N_I $end
$var wire 1 * WCLK_I $end
$var wire 8 8 WDATA_I [7:0] $end
$var wire 1 , WINC_I $end
$var wire 1 - WRST_N_I $end
$var wire 5 9 wq2_rptr_w [4:0] $end
$var wire 5 : wptr_w [4:0] $end
$var wire 1 ; wfull_w $end
$var wire 4 < waddr_w [3:0] $end
$var wire 5 = rq2_wptr_w [4:0] $end
$var wire 5 > rptr_w [4:0] $end
$var wire 4 ? raddr_w [3:0] $end
$var wire 1 " REMPTY_O $end
$var wire 8 @ RDATA_O [7:0] $end
$var wire 1 $ AREMPTY_O $end
$var parameter 32 A ADDRSIZE $end
$var parameter 32 B DATASIZE $end
$var reg 1 ! WFULL_O $end
$var reg 1 C wclken_w $end
$scope module fifo_mem_inst $end
$var wire 1 ' rclk $end
$var wire 1 ( rclken $end
$var wire 8 D rdata [7:0] $end
$var wire 1 * wclk $end
$var wire 1 C wclken $end
$var wire 8 E wdata [7:0] $end
$var wire 1 ; wfull $end
$var wire 4 F waddr [3:0] $end
$var wire 4 G raddr [3:0] $end
$var parameter 32 H ADDRSIZE $end
$var parameter 32 I DATASIZE $end
$var parameter 36 J DEPTH $end
$var reg 8 K rdata_r [7:0] $end
$scope begin dich[0] $end
$var wire 8 L tmp [7:0] $end
$var parameter 2 M idx $end
$upscope $end
$scope begin dich[1] $end
$var wire 8 N tmp [7:0] $end
$var parameter 2 O idx $end
$upscope $end
$scope begin dich[2] $end
$var wire 8 P tmp [7:0] $end
$var parameter 3 Q idx $end
$upscope $end
$scope begin dich[3] $end
$var wire 8 R tmp [7:0] $end
$var parameter 3 S idx $end
$upscope $end
$scope begin dich[4] $end
$var wire 8 T tmp [7:0] $end
$var parameter 4 U idx $end
$upscope $end
$scope begin dich[5] $end
$var wire 8 V tmp [7:0] $end
$var parameter 4 W idx $end
$upscope $end
$scope begin dich[6] $end
$var wire 8 X tmp [7:0] $end
$var parameter 4 Y idx $end
$upscope $end
$scope begin dich[7] $end
$var wire 8 Z tmp [7:0] $end
$var parameter 4 [ idx $end
$upscope $end
$scope begin dich[8] $end
$var wire 8 \ tmp [7:0] $end
$var parameter 5 ] idx $end
$upscope $end
$scope begin dich[9] $end
$var wire 8 ^ tmp [7:0] $end
$var parameter 5 _ idx $end
$upscope $end
$scope begin dich[10] $end
$var wire 8 ` tmp [7:0] $end
$var parameter 5 a idx $end
$upscope $end
$scope begin dich[11] $end
$var wire 8 b tmp [7:0] $end
$var parameter 5 c idx $end
$upscope $end
$scope begin dich[12] $end
$var wire 8 d tmp [7:0] $end
$var parameter 5 e idx $end
$upscope $end
$scope begin dich[13] $end
$var wire 8 f tmp [7:0] $end
$var parameter 5 g idx $end
$upscope $end
$scope begin dich[14] $end
$var wire 8 h tmp [7:0] $end
$var parameter 5 i idx $end
$upscope $end
$scope begin dich[15] $end
$var wire 8 j tmp [7:0] $end
$var parameter 5 k idx $end
$upscope $end
$upscope $end
$scope module rptr_empty_inst $end
$var wire 1 ' rclk $end
$var wire 5 l rgraynext [4:0] $end
$var wire 5 m rgraynextm1 [4:0] $end
$var wire 1 ( rinc $end
$var wire 1 ) rrst_n $end
$var wire 5 n rq2_wptr [4:0] $end
$var wire 1 o rempty_val $end
$var wire 5 p rbinnext [4:0] $end
$var wire 4 q raddr [3:0] $end
$var wire 1 r arempty_val $end
$var parameter 32 s ADDRSIZE $end
$var reg 1 $ arempty $end
$var reg 5 t rbin [4:0] $end
$var reg 1 " rempty $end
$var reg 5 u rptr [4:0] $end
$upscope $end
$scope module sync_r2w_inst $end
$var wire 5 v rptr [4:0] $end
$var wire 1 * wclk $end
$var wire 1 - wrst_n $end
$var parameter 32 w ADDRSIZE $end
$var reg 5 x wq1_rptr [4:0] $end
$var reg 5 y wq2_rptr [4:0] $end
$upscope $end
$scope module sync_w2r_inst $end
$var wire 1 * rclk $end
$var wire 1 - rrst_n $end
$var wire 5 z wptr [4:0] $end
$var parameter 32 { ADDRSIZE $end
$var reg 5 | rq1_wptr [4:0] $end
$var reg 5 } rq2_wptr [4:0] $end
$upscope $end
$scope module wptr_full_inst $end
$var wire 1 * wclk $end
$var wire 5 ~ wgraynext [4:0] $end
$var wire 5 !" wgraynextp1 [4:0] $end
$var wire 1 , winc $end
$var wire 5 "" wq2_rptr [4:0] $end
$var wire 1 - wrst_n $end
$var wire 1 #" wfull_val $end
$var wire 5 $" wbinnext [4:0] $end
$var wire 4 %" waddr [3:0] $end
$var wire 1 &" awfull_val $end
$var parameter 32 '" ADDRSIZE $end
$var reg 1 (" awfull $end
$var reg 5 )" wbin [4:0] $end
$var reg 1 ; wfull $end
$var reg 5 *" wptr [4:0] $end
$upscope $end
$upscope $end
$scope task en_test $end
$upscope $end
$scope task gen_clk_rd $end
$upscope $end
$scope task gen_clk_wr $end
$upscope $end
$scope task gen_data $end
$upscope $end
$scope task gen_rrst_n $end
$upscope $end
$scope task gen_wrst_n $end
$upscope $end
$scope task rd_data $end
$upscope $end
$upscope $end
$enddefinitions $end
$comment Show the parameter values. $end
$dumpall
b100 '"
b100 {
b100 w
b100 s
b1111 k
b1110 i
b1101 g
b1100 e
b1011 c
b1010 a
b1001 _
b1000 ]
b111 [
b110 Y
b101 W
b100 U
b11 S
b10 Q
b1 O
b0 M
b10000 J
b1000 I
b100 H
b1000 B
b100 A
b1000 &
b100 %
$end
#0
$dumpvars
b0 *"
b0 )"
0("
0&"
b0 %"
b1 $"
0#"
b0 ""
b11 !"
b1 ~
b0 }
b0 |
b0 z
b0 y
b0 x
b0 v
b0 u
b0 t
0r
b0 q
b0 p
1o
b0 n
b1 m
b0 l
bx j
bx h
bx f
bx d
bx b
bx `
bx ^
bx \
bx Z
bx X
bx V
bx T
bx R
bx P
bx N
bx L
bx K
b0 G
b0 F
b0 E
bx D
1C
bx @
b0 ?
b0 >
b0 =
b0 <
0;
b0 :
b0 9
b0 8
b0 7
b0 6
b0 5
b0 4
b1 3
b1 2
b0 1
b101 0
b1100100 /
b10010110 .
0-
1,
b0 +
0*
0)
0(
0'
0$
bx #
1"
0!
$end
#10
1'
1-
1)
#20
b0 L
1(
1*
0'
0-
0)
#30
b0 #
b0 @
b0 D
b0 K
b1 5
b10010010 +
b10010010 8
b10010010 E
b1 4
0*
1'
1-
1)
#40
b1 <
b1 F
b1 %"
b10 !"
b11 ~
b10010010 L
b10 $"
b1 )"
b1 :
b1 z
b1 *"
1*
0'
#50
b10010010 #
b10010010 @
b10010010 D
b10010010 K
b10 5
b1000000 +
b1000000 8
b1000000 E
b10 4
0*
1'
#60
b10 <
b10 F
b10 %"
b110 !"
b10 ~
b1000000 N
b1 |
b11 $"
b10 )"
b11 :
b11 z
b11 *"
1*
0'
#70
b11 5
b100 +
b100 8
b100 E
b11 4
0*
1'
#80
b11 <
b11 F
b11 %"
b111 !"
b110 ~
b100 P
b100 $"
b11 )"
b10 :
b10 z
b10 *"
1r
0o
b1 =
b1 n
b1 }
b11 |
1*
0'
#90
0r
b11 m
1o
b1 l
b1 p
0"
1$
b100 5
b110001 +
b110001 8
b110001 E
b100 4
0*
1'
#100
b100 <
b100 F
b100 %"
b101 !"
b111 ~
b110001 R
1r
0o
b11 =
b11 n
b11 }
b10 |
b101 $"
b100 )"
b110 :
b110 z
b110 *"
1*
0'
#110
1o
b1 ?
b1 G
b1 q
0r
b10 m
b11 l
b10 p
b1 t
b1 >
b1 u
b1 v
b101 5
b10000110 +
b10000110 8
b10000110 E
b101 4
0*
1'
#120
b101 <
b101 F
b101 %"
b100 !"
b101 ~
b10000110 T
b110 $"
b101 )"
b111 :
b111 z
b111 *"
b1 x
1r
0o
b10 =
b10 n
b10 }
b110 |
1*
0'
#130
b10 ?
b10 G
b10 q
0r
b110 m
1o
b10 l
b1000000 #
b1000000 @
b1000000 D
b1000000 K
b11 p
b10 t
b11 >
b11 u
b11 v
b110 5
b11000110 +
b11000110 8
b11000110 E
b110 4
0*
1'
#140
b110 <
b110 F
b110 %"
b1100 !"
b100 ~
b11000110 V
1r
0o
b110 =
b110 n
b110 }
b111 |
b1 9
b1 y
b1 ""
b11 x
b111 $"
b110 )"
b101 :
b101 z
b101 *"
1*
0'
#150
1o
b11 ?
b11 G
b11 q
0r
b111 m
b110 l
b100 #
b100 @
b100 D
b100 K
b100 p
b11 t
b10 >
b10 u
b10 v
b111 5
b110010 +
b110010 8
b110010 E
b111 4
0*
1'
#160
b111 <
b111 F
b111 %"
b1101 !"
b1100 ~
b110010 X
b1000 $"
b111 )"
b100 :
b100 z
b100 *"
b11 9
b11 y
b11 ""
b10 x
1r
0o
b111 =
b111 n
b111 }
b101 |
1*
0'
#170
b100 ?
b100 G
b100 q
0r
b101 m
1o
b111 l
b110001 #
b110001 @
b110001 D
b110001 K
b101 p
b100 t
b110 >
b110 u
b110 v
b1000 5
b1001 +
b1001 8
b1001 E
b1000 4
0*
1'
#180
b1000 <
b1000 F
b1000 %"
b1111 !"
b1101 ~
b1001 Z
1r
0o
b101 =
b101 n
b101 }
b100 |
b10 9
b10 y
b10 ""
b110 x
b1001 $"
b1000 )"
b1100 :
b1100 z
b1100 *"
1*
0'
#190
1o
b101 ?
b101 G
b101 q
0r
b100 m
b101 l
b10000110 #
b10000110 @
b10000110 D
b10000110 K
b110 p
b101 t
b111 >
b111 u
b111 v
b1001 5
b10000000 +
b10000000 8
b10000000 E
b1001 4
0*
1'
#200
b1001 <
b1001 F
b1001 %"
b1110 !"
b1111 ~
b10000000 \
b1010 $"
b1001 )"
b1101 :
b1101 z
b1101 *"
b110 9
b110 y
b110 ""
b111 x
1r
0o
b100 =
b100 n
b100 }
b1100 |
1*
0'
#210
b110 ?
b110 G
b110 q
0r
b1100 m
1o
b100 l
b11000110 #
b11000110 @
b11000110 D
b11000110 K
b111 p
b110 t
b101 >
b101 u
b101 v
b1010 5
b10000110 +
b10000110 8
b10000110 E
b1010 4
0*
1'
#220
b1010 <
b1010 F
b1010 %"
b1010 !"
b1110 ~
b10000110 ^
1r
0o
b1100 =
b1100 n
b1100 }
b1101 |
b111 9
b111 y
b111 ""
b101 x
b1011 $"
b1010 )"
b1111 :
b1111 z
b1111 *"
1*
0'
#230
1o
b111 ?
b111 G
b111 q
0r
b1101 m
b1100 l
b110010 #
b110010 @
b110010 D
b110010 K
b1000 p
b111 t
b100 >
b100 u
b100 v
b1011 5
b10111011 +
b10111011 8
b10111011 E
b1011 4
0*
1'
#240
b1011 <
b1011 F
b1011 %"
b1011 !"
b1010 ~
b10111011 `
b1100 $"
b1011 )"
b1110 :
b1110 z
b1110 *"
b101 9
b101 y
b101 ""
b100 x
1r
0o
b1101 =
b1101 n
b1101 }
b1111 |
1*
0'
#250
b1000 ?
b1000 G
b1000 q
0r
b1111 m
1o
b1101 l
b1001 #
b1001 @
b1001 D
b1001 K
b1001 p
b1000 t
b1100 >
b1100 u
b1100 v
b1100 5
b10011110 +
b10011110 8
b10011110 E
b1100 4
0*
1'
#260
b1100 <
b1100 F
b1100 %"
b1001 !"
b1011 ~
b10011110 b
1r
0o
b1111 =
b1111 n
b1111 }
b1110 |
b100 9
b100 y
b100 ""
b1100 x
b1101 $"
b1100 )"
b1010 :
b1010 z
b1010 *"
1*
0'
#270
1o
b1001 ?
b1001 G
b1001 q
0r
b1110 m
b1111 l
b10000000 #
b10000000 @
b10000000 D
b10000000 K
b1010 p
b1001 t
b1101 >
b1101 u
b1101 v
b1101 5
b11110110 +
b11110110 8
b11110110 E
b1101 4
0*
1'
#280
b1101 <
b1101 F
b1101 %"
b1000 !"
b1001 ~
b11110110 d
b1110 $"
b1101 )"
b1011 :
b1011 z
b1011 *"
b1100 9
b1100 y
b1100 ""
b1101 x
1r
0o
b1110 =
b1110 n
b1110 }
b1010 |
1*
0'
#290
b1010 ?
b1010 G
b1010 q
0r
b1010 m
1o
b1110 l
b10000110 #
b10000110 @
b10000110 D
b10000110 K
b1011 p
b1010 t
b1111 >
b1111 u
b1111 v
b1110 5
b11000110 +
b11000110 8
b11000110 E
b1110 4
0*
1'
#300
b1110 <
b1110 F
b1110 %"
b11000 !"
b1000 ~
b11000110 f
1r
0o
b1010 =
b1010 n
b1010 }
b1011 |
b1101 9
b1101 y
b1101 ""
b1111 x
b1111 $"
b1110 )"
b1001 :
b1001 z
b1001 *"
1*
0'
#310
1o
b1011 ?
b1011 G
b1011 q
0r
b1011 m
b1010 l
b10111011 #
b10111011 @
b10111011 D
b10111011 K
b1100 p
b1011 t
b1110 >
b1110 u
b1110 v
b1111 5
b11111100 +
b11111100 8
b11111100 E
b1111 4
0*
1'
#320
b1111 <
b1111 F
b1111 %"
b11001 !"
0#"
b11000 ~
b11111100 h
b10000 $"
b1111 )"
b1000 :
b1000 z
b1000 *"
b1111 9
b1111 y
b1111 ""
b1110 x
1r
0o
b1011 =
b1011 n
b1011 }
b1001 |
1*
0'
#330
b1100 ?
b1100 G
b1100 q
0r
b1001 m
1o
b1011 l
b10011110 #
b10011110 @
b10011110 D
b10011110 K
b1101 p
b1100 t
b1010 >
b1010 u
b1010 v
b10000 5
b1100011 +
b1100011 8
b1100011 E
b10000 4
0*
1'
#340
b0 <
b0 F
b0 %"
b11011 !"
b11001 ~
b1100011 j
1r
0o
b1001 =
b1001 n
b1001 }
b1000 |
b1110 9
b1110 y
b1110 ""
b1010 x
b10001 $"
b10000 )"
b11000 :
b11000 z
b11000 *"
1*
0'
#350
1o
b1101 ?
b1101 G
b1101 q
0r
b1000 m
b1001 l
b11110110 #
b11110110 @
b11110110 D
b11110110 K
b1110 p
b1101 t
b1011 >
b1011 u
b1011 v
b10001 5
b1100010 +
b1100010 8
b1100010 E
b10001 4
0*
1'
#360
b1 <
b1 F
b1 %"
b11010 !"
b11011 ~
b1100010 L
b10010 $"
b10001 )"
b11001 :
b11001 z
b11001 *"
b1010 9
b1010 y
b1010 ""
b1011 x
1r
0o
b1000 =
b1000 n
b1000 }
b11000 |
1*
0'
#370
b1110 ?
b1110 G
b1110 q
0r
b11000 m
1o
b1000 l
b11000110 #
b11000110 @
b11000110 D
b11000110 K
b1111 p
b1110 t
b1001 >
b1001 u
b1001 v
b10010 5
b1010101 +
b1010101 8
b1010101 E
b10010 4
0*
1'
#380
b10 <
b10 F
b10 %"
b11110 !"
b11010 ~
b1010101 N
1r
0o
b11000 =
b11000 n
b11000 }
b11001 |
b1011 9
b1011 y
b1011 ""
b1001 x
b10011 $"
b10010 )"
b11011 :
b11011 z
b11011 *"
1*
0'
#390
1o
b1111 ?
b1111 G
b1111 q
0r
b11001 m
b11000 l
b11111100 #
b11111100 @
b11111100 D
b11111100 K
b10000 p
b1111 t
b1000 >
b1000 u
b1000 v
b10011 5
b11110010 +
b11110010 8
b11110010 E
b10011 4
0*
1'
#400
b11 <
b11 F
b11 %"
b11111 !"
b11110 ~
b11110010 P
b10100 $"
b10011 )"
b11010 :
b11010 z
b11010 *"
b1001 9
b1001 y
b1001 ""
b1000 x
1r
0o
b11001 =
b11001 n
b11001 }
b11011 |
1*
0'
#410
b0 ?
b0 G
b0 q
0r
b11011 m
1o
b11001 l
b1100011 #
b1100011 @
b1100011 D
b1100011 K
b10001 p
b10000 t
b11000 >
b11000 u
b11000 v
b10100 5
b111011 +
b111011 8
b111011 E
b10100 4
0*
1'
#420
b100 <
b100 F
b100 %"
b11101 !"
b11111 ~
b111011 R
1r
0o
b11011 =
b11011 n
b11011 }
b11010 |
b1000 9
b1000 y
b1000 ""
b11000 x
b10101 $"
b10100 )"
b11110 :
b11110 z
b11110 *"
1*
0'
