MPEI_Bachelor/projects/Лр4/КМ4/FSM_traffic_light_btn_red/src/timer.v
module timer #(parameter bit = 5) //чтобы быстро менять входную частоту 
				(clk_50MHz, res,clk_1Hz);

input   clk_50MHz, res;

output  reg clk_1Hz; //делим частоту 

reg [bit:0] cnt; 

always @(posedge clk_50MHz, negedge res) //Блок для получения 1 секунды
if (!res) 
begin
		cnt <= 0;
		clk_1Hz <= 0;
end

else if (cnt == 25)
begin
		cnt <= 0;
		clk_1Hz <= ~clk_1Hz;
end

else 
		cnt = cnt + 1'b1; 

endmodule

MPEI_Bachelor/projects/Лр4/КМ4/FSM_traffic_light_btn_red/src/traffic_light.v
`include "timer.v"
module traffic_light(clk, res, out_state, btn);

input clk, res, btn;

output [1:0] out_state;

localparam RED = 0, GREEN = 1, YELLOW = 2;

reg [1:0] state, next_state;
reg [63:0] txstate;
reg [5:0] cnt;

wire clk_1Hz;

timer one_second(.clk_50MHz(clk), .res(res), .clk_1Hz(clk_1Hz));
//Счетчик секунд
always @(posedge clk_1Hz, negedge res)
begin
if (!res)
 	cnt <= 0;
//Условие сброса счетчика
else if ((state == RED && cnt == 40) || (state == YELLOW && cnt == 3) || ((state == GREEN) && cnt == 21))
   cnt <= 0;
else 
	cnt <= cnt + 1;
end

//Логика переключения из красного в зеленый по нажатию кнопки
reg [1:0] cnt1;
always @(posedge btn, posedge clk_1Hz)
    if (btn && state == RED)
        cnt1 <= cnt1 + 1;
	else
		cnt1 <= 0;
//Факт переходов
always @(posedge clk_1Hz, negedge res)
begin
if (!res)
 	state <= RED;
else
	state <= next_state;
end
//Логика переходов автомата
always @(*)
	case(state)
		RED     : 
				if(cnt == 40)
					next_state = GREEN;
				else if (cnt1 == 3)
					next_state = GREEN;
				else 
					next_state = RED;
		GREEN   : next_state = (cnt ==21) ? YELLOW : GREEN;
		YELLOW : next_state = (cnt ==3) ? RED : YELLOW;
	endcase
//Выходная логика
assign out_state = state;

endmodule

MPEI_Bachelor/projects/Лр4/КМ4/FSM_traffic_light_btn_red/src/traffic_light_top.v
`include "traffic_light.v"
module traffic_light_top(clk,led0, led1, led2, res, btn);

input clk, res, btn;

output led0, led1, led2;
	 
localparam RED = 0, GREEN = 1, YELLOW = 2;

wire [1:0] state;

traffic_light DUT1(.clk(clk), .out_state(state), .res(res), .btn(btn));

assign led0 = state == RED ? 1 : 0;
assign led1 = state == YELLOW ? 1 : 0;
assign led2 = state == GREEN ? 1 : 0;

endmodule

MPEI_Bachelor/projects/Лр4/КМ4/FSM_traffic_light_btn_red/src/tb_traffic_light_top.v
`include "traffic_light_top.v"
`timescale 1ns / 1ns

module tb_traffic_light_top;

reg clk, res, btn;

wire led0, led1, led2;

traffic_light_top DUT (.clk(clk), .res(res), .btn(btn), .led0(led0), .led1(led1), .led2(led2));
initial 
  begin
    res = 1;
    repeat (2) #1 res = ~res;
  end	 

initial 
  begin                                                  
    clk = 0;
    btn = 0;
    $display("Running testbench");
  end         
      
//Нажимаем кнопку для перехода из красного в зеленый
initial  
  begin 
    #4000  btn = 1;
    #4010  btn = 0; 
    #15000 btn = 1;
    #5000  btn = 0;
  end

always 
  #3 clk =  ! clk;                                                 

initial begin
	#50000 $display("Testbench is OK!");
         $finish;
end

initial begin            
    $dumpfile("qqq.vcd");
    $dumpvars;
end

endmodule

MPEI_Bachelor/projects/Лр4/КМ4/FSM_traffic_light_btn_red/src/qqq.vcd
$date
	Sun Dec 11 23:16:52 2022
$end
$version
	Icarus Verilog
$end
$timescale
	1ns
$end
$scope module tb_traffic_light_top $end
$var wire 1 ! led2 $end
$var wire 1 " led1 $end
$var wire 1 # led0 $end
$var reg 1 $ btn $end
$var reg 1 % clk $end
$var reg 1 & res $end
$scope module DUT $end
$var wire 1 $ btn $end
$var wire 1 % clk $end
$var wire 1 & res $end
$var wire 2 ' state [1:0] $end
$var wire 1 ! led2 $end
$var wire 1 " led1 $end
$var wire 1 # led0 $end
$var parameter 32 ( GREEN $end
$var parameter 32 ) RED $end
$var parameter 32 * YELLOW $end
$scope module DUT1 $end
$var wire 1 $ btn $end
$var wire 1 % clk $end
$var wire 1 & res $end
$var wire 2 + out_state [1:0] $end
$var wire 1 , clk_1Hz $end
$var parameter 32 - GREEN $end
$var parameter 32 . RED $end
$var parameter 32 / YELLOW $end
$var reg 6 0 cnt [5:0] $end
$var reg 2 1 cnt1 [1:0] $end
$var reg 2 2 next_state [1:0] $end
$var reg 2 3 state [1:0] $end
$scope module one_second $end
$var wire 1 % clk_50MHz $end
$var wire 1 & res $end
$var parameter 32 4 bit $end
$var reg 1 , clk_1Hz $end
$var reg 6 5 cnt [5:0] $end
$upscope $end
$upscope $end
$upscope $end
$upscope $end
$enddefinitions $end
$comment Show the parameter values. $end
$dumpall
b101 4
b10 /
b0 .
b1 -
b10 *
b0 )
b1 (
$end
#0
$dumpvars
bx 5
bx 3
bx 2
bx 1
bx 0
x,
bx +
bx '
1&
0%
0$
x#
x"
x!
$end
#1
0!
0"
1#
b0 2
0,
b0 5
b0 0
b0 '
b0 +
b0 3
0&
#2
1&
#3
b1 5
1%
#6
0%
#9
b10 5
1%
#12
0%
#15
b11 5
1%
#18
0%
#21
b100 5
1%
#24
0%
#27
b101 5
1%
#30
0%
#33
b110 5
1%
#36
0%
#39
b111 5
1%
#42
0%
#45
b1000 5
1%
#48
0%
#51
b1001 5
1%
#54
0%
#57
b1010 5
1%
#60
0%
#63
b1011 5
1%
#66
0%
#69
b1100 5
1%
#72
0%
#75
b1101 5
1%
#78
0%
#81
b1110 5
1%
#84
0%
#87
b1111 5
1%
#90
0%
#93
b10000 5
1%
#96
0%
#99
b10001 5
1%
#102
0%
#105
b10010 5
1%
#108
0%
#111
b10011 5
1%
#114
0%
#117
b10100 5
1%
#120
0%
#123
b10101 5
1%
#126
0%
#129
b10110 5
1%
#132
0%
#135
b10111 5
1%
#138
0%
#141
b11000 5
1%
#144
0%
#147
b11001 5
1%
#150
0%
#153
b0 1
b1 0
1,
b0 5
1%
#156
0%
#159
b1 5
1%
#162
0%
#165
b10 5
1%
#168
0%
#171
b11 5
1%
#174
0%
#177
b100 5
1%
#180
0%
#183
b101 5
1%
#186
0%
#189
b110 5
1%
#192
0%
#195
b111 5
1%
#198
0%
#201
b1000 5
1%
#204
0%
#207
b1001 5
1%
#210
0%
#213
b1010 5
1%
#216
0%
#219
b1011 5
1%
#222
0%
#225
b1100 5
1%
#228
0%
#231
b1101 5
1%
#234
0%
#237
b1110 5
1%
#240
0%
#243
b1111 5
1%
#246
0%
#249
b10000 5
1%
#252
0%
#255
b10001 5
1%
#258
0%
#261
b10010 5
1%
#264
0%
#267
b10011 5
1%
#270
0%
#273
b10100 5
1%
#276
0%
#279
b10101 5
1%
#282
0%
#285
b10110 5
1%
#288
0%
#291
b10111 5
1%
#294
0%
#297
b11000 5
1%
#300
0%
#303
b11001 5
1%
#306
0%
#309
0,
b0 5
1%
#312
0%
#315
b1 5
1%
#318
0%
#321
b10 5
1%
#324
0%
#327
b11 5
1%
#330
0%
#333
b100 5
1%
#336
0%
#339
b101 5
1%
#342
0%
#345
b110 5
1%
#348
0%
#351
b111 5
1%
#354
0%
#357
b1000 5
1%
#360
0%
#363
b1001 5
1%
#366
0%
#369
b1010 5
1%
#372
0%
#375
b1011 5
1%
#378
0%
#381
b1100 5
1%
#384
0%
#387
b1101 5
1%
#390
0%
#393
b1110 5
1%
#396
0%
#399
b1111 5
1%
#402
0%
#405
b10000 5
1%
#408
0%
#411
b10001 5
1%
#414
0%
#417
b10010 5
1%
#420
0%
#423
b10011 5
1%
#426
0%
#429
b10100 5
1%
#432
0%
#435
b10101 5
1%
#438
0%
#441
b10110 5
1%
#444
0%
#447
b10111 5
1%
#450
0%
#453
b11000 5
1%
#456
0%
#459
b11001 5
1%
#462
0%
#465
b10 0
1,
b0 5
1%
#468
0%
#471
b1 5
1%
#474
0%
#477
b10 5
1%
#480
0%
#483
b11 5
1%
#486
0%
#489
b100 5
1%
#492
0%
#495
b101 5
1%
#498
0%
#501
b110 5
1%
#504
0%
#507
b111 5
1%
#510
0%
#513
b1000 5
1%
#516
0%
#519
b1001 5
1%
#522
0%
#525
b1010 5
1%
#528
0%
#531
b1011 5
1%
#534
0%
#537
b1100 5
1%
#540
0%
#543
b1101 5
1%
#546
0%
#549
b1110 5
1%
#552
0%
#555
b1111 5
1%
#558
0%
#561
b10000 5
1%
#564
0%
#567
b10001 5
1%
#570
0%
#573
b10010 5
1%
#576
0%
#579
b10011 5
1%
#582
0%
#585
b10100 5
1%
#588
0%
#591
b10101 5
1%
#594
0%
#597
b10110 5
1%
#600
0%
#603
b10111 5
1%
#606
0%
#609
b11000 5
1%
#612
0%
#615
b11001 5
1%
#618
0%
#621
0,
b0 5
1%
#624
0%
#627
b1 5
1%
#630
0%
#633
b10 5
1%
#636
0%
#639
b11 5
1%
#642
0%
#645
b100 5
1%
#648
0%
#651
b101 5
1%
#654
0%
#657
b110 5
1%
#660
0%
#663
b111 5
1%
#666
0%
#669
b1000 5
1%
#672
0%
#675
b1001 5
1%
#678
0%
#681
b1010 5
1%
#684
0%
#687
b1011 5
1%
#690
0%
#693
b1100 5
1%
#696
0%
#699
b1101 5
1%
#702
0%
#705
b1110 5
1%
#708
0%
#711
b1111 5
1%
#714
0%
#717
b10000 5
1%
#720
0%
#723
b10001 5
1%
#726
0%
#729
b10010 5
1%
#732
0%
#735
b10011 5
1%
#738
0%
#741
b10100 5
1%
#744
0%
#747
b10101 5
1%
#750
0%
#753
b10110 5
1%
#756
0%
#759
b10111 5
1%
#762
0%
#765
b11000 5
1%
#768
0%
#771
b11001 5
1%
#774
0%
#777
b11 0
1,
b0 5
1%
#780
0%
#783
b1 5
1%
#786
0%
#789
b10 5
1%
#792
0%
#795
b11 5
1%
#798
0%
#801
b100 5
1%
#804
0%
#807
b101 5
1%
#810
0%
#813
b110 5
1%
#816
0%
#819
b111 5
1%
#822
0%
#825
b1000 5
1%
#828
0%
#831
b1001 5
1%
#834
0%
#837
b1010 5
1%
#840
0%
#843
b1011 5
1%
#846
0%
#849
b1100 5
1%
#852
0%
#855
b1101 5
1%
#858
0%
#861
b1110 5
1%
#864
0%
#867
b1111 5
1%
#870
0%
#873
b10000 5
1%
#876
0%
#879
b10001 5
1%
#882
0%
#885
b10010 5
1%
#888
0%
#891
b10011 5
1%
#894
0%
#897
b10100 5
1%
#900
0%
#903
b10101 5
1%
#906
0%
#909
b10110 5
1%
#912
0%
#915
b10111 5
1%
#918
0%
#921
b11000 5
1%
#924
0%
#927
b11001 5
1%
#930
0%
#933
0,
b0 5
1%
#936
0%
#939
b1 5
1%
#942
0%
#945
b10 5
1%
#948
0%
#951
b11 5
1%
#954
0%
#957
b100 5
1%
#960
0%
#963
b101 5
1%
#966
0%
#969
b110 5
1%
#972
0%
#975
b111 5
1%
#978
0%
#981
b1000 5
1%
#984
0%
#987
b1001 5
1%
#990
0%
#993
b1010 5
1%
#996
0%
#999
b1011 5
1%
#1002
0%
#1005
b1100 5
1%
#1008
0%
#1011
b1101 5
1%
#1014
0%
#1017
b1110 5
1%
#1020
0%
#1023
b1111 5
1%
#1026
0%
#1029
b10000 5
1%
#1032
0%
#1035
b10001 5
1%
#1038
0%
#1041
b10010 5
1%
#1044
0%
#1047
b10011 5
1%
#1050
0%
#1053
b10100 5
1%
#1056
0%
#1059
b10101 5
1%
#1062
0%
#1065
b10110 5
1%
#1068
0%
#1071
b10111 5
1%
#1074
0%
#1077
b11000 5
1%
#1080
0%
#1083
b11001 5
1%
#1086
0%
#1089
b100 0
1,
b0 5
1%
#1092
0%
#1095
b1 5
1%
#1098
0%
#1101
b10 5
1%
#1104
0%
#1107
b11 5
1%
#1110
0%
#1113
b100 5
1%
#1116
0%
#1119
b101 5
1%
#1122
0%
#1125
b110 5
1%
#1128
0%
#1131
b111 5
1%
#1134
0%
#1137
b1000 5
1%
#1140
0%
#1143
b1001 5
1%
#1146
0%
#1149
b1010 5
1%
#1152
0%
#1155
b1011 5
1%
#1158
0%
#1161
b1100 5
1%
#1164
0%
#1167
b1101 5
1%
#1170
0%
#1173
b1110 5
1%
#1176
0%
#1179
b1111 5
1%
#1182
0%
#1185
b10000 5
1%
#1188
0%
#1191
b10001 5
1%
#1194
0%
#1197
b10010 5
1%
#1200
0%
#1203
b10011 5
1%
#1206
0%
#1209
b10100 5
1%
#1212
0%
#1215
b10101 5
1%
#1218
0%
#1221
b10110 5
1%
#1224
0%
#1227
b10111 5
1%
#1230
0%
#1233
b11000 5
1%
#1236
0%
#1239
b11001 5
1%
#1242
0%
#1245
0,
b0 5
1%
#1248
0%
#1251
b1 5
1%
#1254
0%
#1257
b10 5
1%
#1260
0%
#1263
b11 5
1%
#1266
0%
#1269
b100 5
1%
#1272
0%
#1275
b101 5
1%
#1278
0%
#1281
b110 5
1%
#1284
0%
#1287
b111 5
1%
#1290
0%
#1293
b1000 5
1%
#1296
0%
#1299
b1001 5
1%
#1302
0%
#1305
b1010 5
1%
#1308
0%
#1311
b1011 5
1%
#1314
0%
#1317
b1100 5
1%
#1320
0%
#1323
b1101 5
1%
#1326
0%
#1329
b1110 5
1%
#1332
0%
#1335
b1111 5
1%
#1338
0%
#1341
b10000 5
1%
#1344
0%
#1347
b10001 5
1%
#1350
0%
#1353
b10010 5
1%
#1356
0%
#1359
b10011 5
1%
#1362
0%
#1365
b10100 5
1%
#1368
0%
#1371
b10101 5
1%
#1374
0%
#1377
b10110 5
1%
#1380
0%
#1383
b10111 5
1%
#1386
0%
#1389
b11000 5
1%
#1392
0%
#1395
b11001 5
1%
#1398
0%
#1401
b101 0
1,
b0 5
1%
#1404
0%
#1407
b1 5
1%
#1410
0%
#1413
b10 5
1%
#1416
0%
#1419
b11 5
1%
#1422
0%
#1425
b100 5
1%
#1428
0%
#1431
b101 5
1%
#1434
0%
#1437
b110 5
1%
#1440
0%
#1443
b111 5
1%
#1446
0%
#1449
b1000 5
1%
#1452
0%
#1455
b1001 5
1%
#1458
0%
#1461
b1010 5
1%
#1464
0%
#1467
b1011 5
1%
#1470
0%
#1473
b1100 5
1%
#1476
0%
#1479
b1101 5
1%
#1482
0%
#1485
b1110 5
1%
#1488
0%
#1491
b1111 5
1%
#1494
0%
#1497
b10000 5
1%
#1500
0%
#1503
b10001 5
1%
#1506
0%
#1509
b10010 5
1%
#1512
0%
#1515
b10011 5
1%
#1518
0%
#1521
b10100 5
1%
#1524
0%
#1527
b10101 5
1%
#1530
0%
#1533
b10110 5
1%
#1536
0%
#1539
b10111 5
1%
#1542
0%
#1545
b11000 5
1%
#1548
0%
#1551
b11001 5
1%
#1554
0%
#1557
0,
b0 5
1%
#1560
0%
#1563
b1 5
1%
#1566
0%
#1569
b10 5
1%
#1572
0%
#1575
b11 5
1%
#1578
0%
#1581
b100 5
1%
#1584
0%
#1587
b101 5
1%
#1590
0%
#1593
b110 5
1%
#1596
0%
#1599
b111 5
1%
#1602
0%
#1605
b1000 5
1%
#1608
0%
#1611
b1001 5
1%
#1614
0%
#1617
b1010 5
1%
#1620
0%
#1623
b1011 5
1%
#1626
0%
#1629
b1100 5
1%
#1632
0%
#1635
b1101 5
1%
#1638
0%
#1641
b1110 5
1%
#1644
0%
#1647
b1111 5
1%
#1650
0%
#1653
b10000 5
1%
#1656
0%
#1659
b10001 5
1%
#1662
0%
#1665
b10010 5
1%
#1668
0%
#1671
b10011 5
1%
#1674
0%
#1677
b10100 5
1%
#1680
0%
#1683
b10101 5
1%
#1686
0%
#1689
b10110 5
1%
#1692
0%
#1695
b10111 5
1%
#1698
0%
#1701
b11000 5
1%
#1704
0%
#1707
b11001 5
1%
#1710
0%
#1713
b110 0
1,
b0 5
1%
#1716
0%
#1719
b1 5
1%
#1722
0%
#1725
b10 5
1%
#1728
0%
#1731
b11 5
1%
#1734
0%
#1737
b100 5
1%
#1740
0%
#1743
b101 5
1%
#1746
0%
#1749
b110 5
1%
#1752
0%
#1755
b111 5
1%
#1758
0%
#1761
b1000 5
1%
#1764
0%
#1767
b1001 5
1%
#1770
0%
#1773
b1010 5
1%
#1776
0%
#1779
b1011 5
1%
#1782
0%
#1785
b1100 5
1%
#1788
0%
#1791
b1101 5
1%
#1794
0%
#1797
b1110 5
1%
#1800
0%
#1803
b1111 5
1%
#1806
0%
#1809
b10000 5
1%
#1812
0%
#1815
b10001 5
1%
#1818
0%
#1821
b10010 5
1%
#1824
0%
#1827
b10011 5
1%
#1830
0%
#1833
b10100 5
1%
#1836
0%
#1839
b10101 5
1%
#1842
0%
#1845
b10110 5
1%
#1848
0%
#1851
b10111 5
1%
#1854
0%
#1857
b11000 5
1%
#1860
0%
#1863
b11001 5
1%
#1866
0%
#1869
0,
b0 5
1%
#1872
0%
#1875
b1 5
1%
#1878
0%
#1881
b10 5
1%
#1884
0%
#1887
b11 5
1%
#1890
0%
#1893
b100 5
1%
#1896
0%
#1899
b101 5
1%
#1902
0%
#1905
b110 5
1%
#1908
0%
#1911
b111 5
1%
#1914
0%
#1917
b1000 5
1%
#1920
0%
#1923
b1001 5
1%
#1926
0%
#1929
b1010 5
1%
#1932
0%
#1935
b1011 5
1%
#1938
0%
#1941
b1100 5
1%
#1944
0%
#1947
b1101 5
1%
#1950
0%
#1953
b1110 5
1%
#1956
0%
#1959
b1111 5
1%
#1962
0%
#1965
b10000 5
1%
#1968
0%
#1971
b10001 5
1%
#1974
0%
#1977
b10010 5
1%
#1980
0%
#1983
b10011 5
1%
#1986
0%
#1989
b10100 5
1%
#1992
0%
#1995
b10101 5
1%
#1998
0%
#2001
b10110 5
1%
#2004
0%
#2007
b10111 5
1%
#2010
0%
#2013
b11000 5
1%
#2016
0%
#2019
b11001 5
1%
#2022
0%
#2025
b111 0
1,
b0 5
1%
#2028
0%
#2031
b1 5
1%
#2034
0%
#2037
b10 5
1%
#2040
0%
#2043
b11 5
1%
#2046
0%
#2049
b100 5
1%
#2052
0%
#2055
b101 5
1%
#2058
0%
#2061
b110 5
1%
#2064
0%
#2067
b111 5
1%
#2070
0%
#2073
b1000 5
1%
#2076
0%
#2079
b1001 5
1%
#2082
0%
#2085
b1010 5
1%
#2088
0%
#2091
b1011 5
1%
#2094
0%
#2097
b1100 5
1%
#2100
0%
#2103
b1101 5
1%
#2106
0%
#2109
b1110 5
1%
#2112
0%
#2115
b1111 5
1%
#2118
0%
#2121
b10000 5
1%
#2124
0%
#2127
b10001 5
1%
#2130
0%
#2133
b10010 5
1%
#2136
0%
#2139
b10011 5
1%
#2142
0%
#2145
b10100 5
1%
#2148
0%
#2151
b10101 5
1%
#2154
0%
#2157
b10110 5
1%
#2160
0%
#2163
b10111 5
1%
#2166
0%
#2169
b11000 5
1%
#2172
0%
#2175
b11001 5
1%
#2178
0%
#2181
0,
b0 5
1%
#2184
0%
#2187
b1 5
1%
#2190
0%
#2193
b10 5
1%
#2196
0%
#2199
b11 5
1%
#2202
0%
#2205
b100 5
1%
#2208
0%
#2211
b101 5
1%
#2214
0%
#2217
b110 5
1%
#2220
0%
#2223
b111 5
1%
#2226
0%
#2229
b1000 5
1%
#2232
0%
#2235
b1001 5
1%
#2238
0%
#2241
b1010 5
1%
#2244
0%
#2247
b1011 5
1%
#2250
0%
#2253
b1100 5
1%
#2256
0%
#2259
b1101 5
1%
#2262
0%
#2265
b1110 5
1%
#2268
0%
#2271
b1111 5
1%
#2274
0%
#2277
b10000 5
1%
#2280
0%
#2283
b10001 5
1%
#2286
0%
#2289
b10010 5
1%
#2292
0%
#2295
b10011 5
1%
#2298
0%
#2301
b10100 5
1%
#2304
0%
#2307
b10101 5
1%
#2310
0%
#2313
b10110 5
1%
#2316
0%
#2319
b10111 5
1%
#2322
0%
#2325
b11000 5
1%
#2328
0%
#2331
b11001 5
1%
#2334
0%
#2337
b1000 0
1,
b0 5
1%
#2340
0%
#2343
b1 5
1%
#2346
0%
#2349
b10 5
1%
#2352
0%
#2355
b11 5
1%
#2358
0%
#2361
b100 5
1%
#2364
0%
#2367
b101 5
1%
#2370
0%
#2373
b110 5
1%
#2376
0%
#2379
b111 5
1%
#2382
0%
#2385
b1000 5
1%
#2388
0%
#2391
b1001 5
1%
#2394
0%
#2397
b1010 5
1%
#2400
0%
#2403
b1011 5
1%
#2406
0%
#2409
b1100 5
1%
#2412
0%
#2415
b1101 5
1%
#2418
0%
#2421
b1110 5
1%
#2424
0%
#2427
b1111 5
1%
#2430
0%
#2433
b10000 5
1%
#2436
0%
#2439
b10001 5
1%
#2442
0%
#2445
b10010 5
1%
#2448
0%
#2451
b10011 5
1%
#2454
0%
#2457
b10100 5
1%
#2460
0%
#2463
b10101 5
1%
#2466
0%
#2469
b10110 5
1%
#2472
0%
#2475
b10111 5
1%
#2478
0%
#2481
b11000 5
1%
#2484
0%
#2487
b11001 5
1%
#2490
0%
#2493
0,
b0 5
1%
#2496
0%
#2499
b1 5
1%
#2502
0%
#2505
b10 5
1%
#2508
0%
#2511
b11 5
1%
#2514
0%
#2517
b100 5
1%
#2520
0%
#2523
b101 5
1%
#2526
0%
#2529
b110 5
1%
#2532
0%
#2535
b111 5
1%
#2538
0%
#2541
b1000 5
1%
#2544
0%
#2547
b1001 5
1%
#2550
0%
#2553
b1010 5
1%
#2556
0%
#2559
b1011 5
1%
#2562
0%
#2565
b1100 5
1%
#2568
0%
#2571
b1101 5
1%
#2574
0%
#2577
b1110 5
1%
#2580
0%
#2583
b1111 5
1%
#2586
0%
#2589
b10000 5
1%
#2592
0%
#2595
b10001 5
1%
#2598
0%
#2601
b10010 5
1%
#2604
0%
#2607
b10011 5
1%
#2610
0%
#2613
b10100 5
1%
#2616
0%
#2619
b10101 5
1%
#2622
0%
#2625
b10110 5
1%
#2628
0%
#2631
b10111 5
1%
#2634
0%
#2637
b11000 5
1%
#2640
0%
#2643
b11001 5
1%
#2646
0%
#2649
b1001 0
1,
b0 5
1%
#2652
0%
#2655
b1 5
1%
#2658
0%
#2661
b10 5
1%
#2664
0%
#2667
b11 5
1%
#2670
0%
#2673
b100 5
1%
#2676
0%
#2679
b101 5
1%
#2682
0%
#2685
b110 5
1%
#2688
0%
#2691
b111 5
1%
#2694
0%
#2697
b1000 5
1%
#2700
0%
#2703
b1001 5
1%
#2706
0%
#2709
b1010 5
1%
#2712
0%
#2715
b1011 5
1%
#2718
0%
#2721
b1100 5
1%
#2724
0%
#2727
b1101 5
1%
#2730
0%
#2733
b1110 5
1%
#2736
0%
#2739
b1111 5
1%
#2742
0%
#2745
b10000 5
1%
#2748
0%
#2751
b10001 5
1%
#2754
0%
#2757
b10010 5
1%
#2760
0%
#2763
b10011 5
1%
#2766
0%
#2769
b10100 5
1%
#2772
0%
#2775
b10101 5
1%
#2778
0%
#2781
b10110 5
1%
#2784
0%
#2787
b10111 5
1%
#2790
0%
#2793
b11000 5
1%
#2796
0%
#2799
b11001 5
1%
#2802
0%
#2805
0,
b0 5
1%
#2808
0%
#2811
b1 5
1%
#2814
0%
#2817
b10 5
1%
#2820
0%
#2823
b11 5
1%
#2826
0%
#2829
b100 5
1%
#2832
0%
#2835
b101 5
1%
#2838
0%
#2841
b110 5
1%
#2844
0%
#2847
b111 5
1%
#2850
0%
#2853
b1000 5
1%
#2856
0%
#2859
b1001 5
1%
#2862
0%
#2865
b1010 5
1%
#2868
0%
#2871
b1011 5
1%
#2874
0%
#2877
b1100 5
1%
#2880
0%
#2883
b1101 5
1%
#2886
0%
#2889
b1110 5
1%
#2892
0%
#2895
b1111 5
1%
#2898
0%
#2901
b10000 5
1%
#2904
0%
#2907
b10001 5
1%
#2910
0%
#2913
b10010 5
1%
#2916
0%
#2919
b10011 5
1%
#2922
0%
#2925
b10100 5
1%
#2928
0%
#2931
b10101 5
1%
#2934
0%
#2937
b10110 5
1%
#2940
0%
#2943
b10111 5
1%
#2946
0%
#2949
b11000 5
1%
#2952
0%
#2955
b11001 5
1%
#2958
0%
#2961
b1010 0
1,
b0 5
1%
#2964
0%
#2967
b1 5
1%
#2970
0%
#2973
b10 5
1%
#2976
0%
#2979
b11 5
1%
#2982
0%
#2985
b100 5
1%
#2988
0%
#2991
b101 5
1%
#2994
0%
#2997
b110 5
1%
#3000
0%
#3003
b111 5
1%
#3006
0%
#3009
b1000 5
1%
#3012
0%
#3015
b1001 5
1%
#3018
0%
#3021
b1010 5
1%
#3024
0%
#3027
b1011 5
1%
#3030
0%
#3033
b1100 5
1%
#3036
0%
#3039
b1101 5
1%
#3042
0%
#3045
b1110 5
1%
#3048
0%
#3051
b1111 5
1%
#3054
0%
#3057
b10000 5
1%
#3060
0%
#3063
b10001 5
1%
#3066
0%
#3069
b10010 5
1%
#3072
0%
#3075
b10011 5
1%
#3078
0%
#3081
b10100 5
1%
#3084
0%
#3087
b10101 5
1%
#3090
0%
#3093
b10110 5
1%
#3096
0%
#3099
b10111 5
1%
#3102
0%
#3105
b11000 5
1%
#3108
0%
#3111
b11001 5
1%
#3114
0%
#3117
0,
b0 5
1%
#3120
0%
#3123
b1 5
1%
#3126
0%
#3129
b10 5
1%
#3132
0%
#3135
b11 5
1%
#3138
0%
#3141
b100 5
1%
#3144
0%
#3147
b101 5
1%
#3150
0%
#3153
b110 5
1%
#3156
0%
#3159
b111 5
1%
#3162
0%
#3165
b1000 5
1%
#3168
0%
#3171
b1001 5
1%
#3174
0%
#3177
b1010 5
1%
#3180
0%
#3183
b1011 5
1%
#3186
0%
#3189
b1100 5
1%
#3192
0%
#3195
b1101 5
1%
#3198
0%
#3201
b1110 5
1%
#3204
0%
#3207
b1111 5
1%
#3210
0%
#3213
b10000 5
1%
#3216
0%
#3219
b10001 5
1%
#3222
0%
#3225
b10010 5
1%
#3228
0%
#3231
b10011 5
1%
#3234
0%
#3237
b10100 5
1%
#3240
0%
#3243
b10101 5
1%
#3246
0%
#3249
b10110 5
1%
#3252
0%
#3255
b10111 5
1%
#3258
0%
#3261
b11000 5
1%
#3264
0%
#3267
b11001 5
1%
#3270
0%
#3273
b1011 0
1,
b0 5
1%
#3276
0%
#3279
b1 5
1%
#3282
0%
#3285
b10 5
1%
#3288
0%
#3291
b11 5
1%
#3294
0%
#3297
b100 5
1%
#3300
0%
#3303
b101 5
1%
#3306
0%
#3309
b110 5
1%
#3312
0%
#3315
b111 5
1%
#3318
0%
#3321
b1000 5
1%
#3324
0%
#3327
b1001 5
1%
#3330
0%
#3333
b1010 5
1%
#3336
0%
#3339
b1011 5
1%
#3342
0%
#3345
b1100 5
1%
#3348
0%
#3351
b1101 5
1%
#3354
0%
#3357
b1110 5
1%
#3360
0%
#3363
b1111 5
1%
#3366
0%
#3369
b10000 5
1%
#3372
0%
#3375
b10001 5
1%
#3378
0%
#3381
b10010 5
1%
#3384
0%
#3387
b10011 5
1%
#3390
0%
#3393
b10100 5
1%
#3396
0%
#3399
b10101 5
1%
#3402
0%
#3405
b10110 5
1%
#3408
0%
#3411
b10111 5
1%
#3414
0%
#3417
b11000 5
1%
#3420
0%
#3423
b11001 5
1%
#3426
0%
#3429
0,
b0 5
1%
#3432
0%
#3435
b1 5
1%
#3438
0%
#3441
b10 5
1%
#3444
0%
#3447
b11 5
1%
#3450
0%
#3453
b100 5
1%
#3456
0%
#3459
b101 5
1%
#3462
0%
#3465
b110 5
1%
#3468
0%
#3471
b111 5
1%
#3474
0%
#3477
b1000 5
1%
#3480
0%
#3483
b1001 5
1%
#3486
0%
#3489
b1010 5
1%
#3492
0%
#3495
b1011 5
1%
#3498
0%
#3501
b1100 5
1%
#3504
0%
#3507
b1101 5
1%
#3510
0%
#3513
b1110 5
1%
#3516
0%
#3519
b1111 5
1%
#3522
0%
#3525
b10000 5
1%
#3528
0%
#3531
b10001 5
1%
#3534
0%
#3537
b10010 5
1%
#3540
0%
#3543
b10011 5
1%
#3546
0%
#3549
b10100 5
1%
#3552
0%
#3555
b10101 5
1%
#3558
0%
#3561
b10110 5
1%
#3564
0%
#3567
b10111 5
1%
#3570
0%
#3573
b11000 5
1%
#3576
0%
#3579
b11001 5
1%
#3582
0%
#3585
b1100 0
1,
b0 5
1%
#3588
0%
#3591
b1 5
1%
#3594
0%
#3597
b10 5
1%
#3600
0%
#3603
b11 5
1%
#3606
0%
#3609
b100 5
1%
#3612
0%
#3615
b101 5
1%
#3618
0%
#3621
b110 5
1%
#3624
0%
#3627
b111 5
1%
#3630
0%
#3633
b1000 5
1%
#3636
0%
#3639
b1001 5
1%
#3642
0%
#3645
b1010 5
1%
#3648
0%
#3651
b1011 5
1%
#3654
0%
#3657
b1100 5
1%
#3660
0%
#3663
b1101 5
1%
#3666
0%
#3669
b1110 5
1%
#3672
0%
#3675
b1111 5
1%
#3678
0%
#3681
b10000 5
1%
#3684
0%
#3687
b10001 5
1%
#3690
0%
#3693
b10010 5
1%
#3696
0%
#3699
b10011 5
1%
#3702
0%
#3705
b10100 5
1%
#3708
0%
#3711
b10101 5
1%
#3714
0%
#3717
b10110 5
1%
#3720
0%
#3723
b10111 5
1%
#3726
0%
#3729
b11000 5
1%
#3732
0%
#3735
b11001 5
1%
#3738
0%
#3741
0,
b0 5
1%
#3744
0%
#3747
b1 5
1%
#3750
0%
#3753
b10 5
1%
#3756
0%
#3759
b11 5
1%
#3762
0%
#3765
b100 5
1%
#3768
0%
#3771
b101 5
1%
#3774
0%
#3777
b110 5
1%
#3780
0%
#3783
b111 5
1%
#3786
0%
#3789
b1000 5
1%
#3792
0%
#3795
b1001 5
1%
#3798
0%
#3801
b1010 5
1%
#3804
0%
#3807
b1011 5
1%
#3810
0%
#3813
b1100 5
1%
#3816
0%
#3819
b1101 5
1%
#3822
0%
#3825
b1110 5
1%
#3828
0%
#3831
b1111 5
1%
#3834
0%
#3837
b10000 5
1%
#3840
0%
#3843
b10001 5
1%
#3846
0%
