MPEI_Bachelor/bachelor's work/ALU/src/ALU.v
module ALU (clk, res, A, B, out, select);

input      clk, res;                        // Системный такт и сброс
input [3:0] A, B;                           // Входные операнды
input [4:0] select;                         // Выбор операции

output reg [7:0] out;                       // Результат

initial out = 0;                            // Убираем неопределенность на выходе

always @(posedge clk, negedge res)  
if (!res)   
    out = 0;    
else    
    case (select)   
        1:  out <= A + B;                   // Сложение
        2:  out <= A - B;                   // Вычитание А - В
        3:  out <= B - A;                   // Вычитание В - А
        4:  out <= A * B;                   // Умножение
        5:  out <= A & B;                   // Побитовое И
        6:  out <= A | B;                   // Побитовое ИЛИ
        7:  out <= A ^ B;                   // Исключающее ИЛИ
        8:  out <= A >> 1;                  // Логический сдвиг вправо A
        9:  out <= A << 1;                  // Логический сдвиг влево  A
        10: out <= B >> 1;                  // Логический сдвиг вправо B
        11: out <= B << 1;                  // Логический сдвиг влево  B
        12: out <= {1'b0, A[3:1]};          // Арифметичекий сдвиг вправо A
        13: out <= {1'b0, B[3:1]};          // Арифметичекий сдвиг вправо В      
        14: out <= (A == B) ? 1 : 0;        // Если А = В, то out = 1
        15: out <= (A > B) ? 1 : 0;         // Если А больше В, то out = 1
        default: out = A + B;
    endcase

endmodule

MPEI_Bachelor/energy_hope/iverilog/tb_ALU.v
`include "ALU.v"
`timescale 1ns / 1ps  

module tb_alu;
 reg clk, res;
 reg[3:0] A, B;
 reg[4:0] select;

 wire[7:0] out;

 integer i;
 ALU DUT(.A(A), .B(B), .select(select), .out(out), .clk(clk), .res(res));

initial                           // Задаем начальные значения такта и сброса
begin                                                    
  clk = 0; 
  res = 1; 
  $display("Running testbench"); 
end          
 
always                            // Задаем вечный такт каждые 5нс
  #5	   
  clk = !clk;   
 
//initial begin                     // Блок бля сброса выходного регистра                                            
//  #150 
//  res = 0;  
//  #100 
//  res = 1;    
//end   
 
initial  
begin  
  A = 4'b0100;                    // Задаем начальные значения входных операндов
  B = 4'b1001; 
  select = 0;                     // Начальное значение выбора операции
 
  for (i = 0; i <= 14; i = i + 1) // Цикл для последовательного перебора выбора операции (для удобной проверки)
    begin 
      select = select + 1;
      #20;                        // Каждые 20 нс операция меняется
    end;  
end

initial                           // Блок для изменения входных операндов и кол-ва сдвигаемых разрядов
begin
      #160
      A = 4'b1101;
      B = 4'b1111;
      #100
      A = 4'b1001;
      B = 4'b0110;  
  end

initial                           // Блок для изменения значения выбора операции
begin                             // После последовательного прогона всех операций можем выбрать любую из них
      #340                  
      select = 12;
      #20
      select = 13;       
  end

initial begin                     // Блок, где можно задать время тестирования  
	$monitor ("At time %t 'A'=%b and 'B'=%b and 'select'=%d and 'out'=%b",$time,A,B,select,out);
#400 $display("Testbench is OK!");
     $finish;         
end

initial begin                     // Блок для симуляции в Iverilog                 
     $dumpfile("qqq.vcd");
     $dumpvars;
end

endmodule

MPEI_Bachelor/bachelor's work/ALU/src/qqq.vcd
$date
	Tue Jun 06 03:33:39 2023
$end
$version
	Icarus Verilog
$end
$timescale
	1ps
$end
$scope module tb_alu $end
$var wire 8 ! out [7:0] $end
$var reg 4 " A [3:0] $end
$var reg 4 # B [3:0] $end
$var reg 1 $ clk $end
$var reg 1 % res $end
$var reg 5 & select [4:0] $end
$var integer 32 ' i [31:0] $end
$scope module DUT $end
$var wire 4 ( A [3:0] $end
$var wire 4 ) B [3:0] $end
$var wire 1 $ clk $end
$var wire 1 % res $end
$var wire 5 * select [4:0] $end
$var reg 8 + out [7:0] $end
$upscope $end
$upscope $end
$enddefinitions $end
$comment Show the parameter values. $end
$dumpall
$end
#0
$dumpvars
b0 +
b1 *
b1001 )
b100 (
b0 '
b1 &
1%
0$
b1001 #
b100 "
b0 !
$end
#5000
b1101 !
b1101 +
1$
#10000
0$
#15000
1$
#20000
0$
b10 &
b10 *
b1 '
#25000
b11111011 !
b11111011 +
1$
#30000
0$
#35000
1$
#40000
0$
b11 &
b11 *
b10 '
#45000
b101 !
b101 +
1$
#50000
0$
#55000
1$
#60000
0$
b100 &
b100 *
b11 '
#65000
b100100 !
b100100 +
1$
#70000
0$
#75000
1$
#80000
0$
b101 &
b101 *
b100 '
#85000
b0 !
b0 +
1$
#90000
0$
#95000
1$
#100000
0$
b110 &
b110 *
b101 '
#105000
b1101 !
b1101 +
1$
#110000
0$
#115000
1$
#120000
0$
b111 &
b111 *
b110 '
#125000
1$
#130000
0$
#135000
1$
#140000
0$
b1000 &
b1000 *
b111 '
#145000
b10 !
b10 +
1$
#150000
0$
#155000
1$
#160000
0$
b1001 &
b1001 *
b1000 '
b1111 #
b1111 )
b1101 "
b1101 (
#165000
b11010 !
b11010 +
1$
#170000
0$
#175000
1$
#180000
0$
b1010 &
b1010 *
b1001 '
#185000
b111 !
b111 +
1$
#190000
0$
#195000
1$
#200000
0$
b1011 &
b1011 *
b1010 '
#205000
b11110 !
b11110 +
1$
#210000
0$
#215000
1$
#220000
0$
b1100 &
b1100 *
b1011 '
#225000
b110 !
b110 +
1$
#230000
0$
#235000
1$
#240000
0$
b1101 &
b1101 *
b1100 '
#245000
b111 !
b111 +
1$
#250000
0$
#255000
1$
#260000
0$
b1110 &
b1110 *
b1101 '
b110 #
b110 )
b1001 "
b1001 (
#265000
b0 !
b0 +
1$
#270000
0$
#275000
1$
#280000
0$
b1111 &
b1111 *
b1110 '
#285000
b1 !
b1 +
1$
#290000
0$
#295000
1$
#300000
0$
b1111 '
#305000
1$
#310000
0$
#315000
1$
#320000
0$
#325000
1$
#330000
0$
#335000
1$
#340000
0$
b1100 &
b1100 *
#345000
b100 !
b100 +
1$
#350000
0$
#355000
1$
#360000
0$
b1101 &
b1101 *
#365000
b11 !
b11 +
1$
