MPEI_Bachelor/projects/Лр4/КМ4/Snail_FSM_000/SnailFSM_Mealey_000.v
module SnailFSM_Mealey_000(D, _rst, clk, Q);

//Поиск последовательности 000

localparam SAD = 0, WAIT1 = 1, WAIT2 = 2;

input D;
input _rst, clk;

output reg Q;

reg [1:0] state, nextstate;

reg Q_nonsynch;

reg [63:0] txstate;

always @( state )
  case ( state )
	 SAD    : txstate = "SAD";
	 WAIT1  : txstate = "WAIT1";
   WAIT2  : txstate = "WAIT2";
  endcase

always @(posedge clk, negedge _rst) begin
  if ( !_rst )
    state <= SAD;
  else
    state <= nextstate;
end

always @(*) begin
  case ( state )
    SAD   : nextstate = (( !D ) ? WAIT1 : SAD );   //если D = 0, то nextstate = WAIT1, иначе nextstate = SAD
	  WAIT1 : nextstate = (( !D ) ? WAIT2 : SAD );   //если D = 0, то nextstate = WAIT2, иначе nextstate не меняется
    WAIT2 : nextstate = (( !D ) ? WAIT1 : SAD );   //если D = 0, то nextstate = WAIT1, иначе nextstate = SAD
    default : nextstate = SAD;
  endcase
end


always @(*) begin
  case ( state )
    SAD       : Q_nonsynch = 0;
    WAIT1     : Q_nonsynch = 0;
    WAIT2     : Q_nonsynch = (!D) ? 1'b1 : 1'b0;
    default   : Q_nonsynch = 0;
  endcase
end

always @(posedge clk or negedge _rst)
  if (!_rst)
    Q <= 0;
  else
    Q <= Q_nonsynch;

//assign Q = (D == 1'b1 && state == WAIT1);
endmodule

MPEI_Bachelor/projects/Лр4/КМ4/Snail_FSM_000/SnailFSM_Moore_000.v
module SnailFSM_Moore_000(D, _rst, clk, Q);

//Поиск последовательности 000

localparam SAD = 0, HOPE1 = 1, HOPE2 = 2, HOORAY = 3;

input D;
input _rst, clk;

output reg Q;

reg [1:0] state, nextstate;

reg Q_nonsynch;

reg [63:0] txstate;

always @( state )
  case ( state )
	 SAD     : txstate = "SAD";
	 HOPE1   : txstate = "HOPE1";
	 HOPE2   : txstate = "HOPE2";
   HOORAY  : txstate = "HOORAY";
  endcase

always @(posedge clk, negedge _rst) begin
  if ( !_rst )
    state <= SAD;
  else
    state <= nextstate;
end

always @(*) begin
  case ( state )
    SAD          : nextstate = (( !D ) ? HOPE1   : SAD );      //если D = 0, то nextstate = HOPE1,  иначе nextstate = SAD
    HOPE1        : nextstate = (( !D ) ? HOPE2   : HOPE1 );    //если D = 0, то nextstate = HOPE2,  иначе nextstate не меняется
    HOPE2        : nextstate = (( !D ) ? HOORAY  : SAD );      //если D = 0, то nextstate = HOORAY, иначе nextstate = SAD
	  HOORAY       : nextstate = (( !D ) ? HOPE1   : SAD );   
    default      : nextstate = SAD;
  endcase
end


always @(*) begin
  case ( state )
    SAD, HOPE1, HOPE2 : Q_nonsynch = 0;
    HOORAY            : Q_nonsynch = 1;
    default           : Q_nonsynch = 0;
  endcase
end

always @(posedge clk or negedge _rst)
  if (!_rst)
    Q <= 0;
  else
    Q <= Q_nonsynch;

endmodule

MPEI_Bachelor/projects/Лр4/КМ4/Snail_FSM_000/tb_SnailFSM_000.v
//`include "SnailFSM_Mealey_000.v"
`include "SnailFSM_Moore_000.v"
`timescale 1ns / 1ns

module tb_SnailFSM_000;

reg D, _rst, clk;
wire Q;

wire [63:0] state = DUT.txstate;

//SnailFSM_Mealey_000 DUT (D, _rst, clk, Q);
SnailFSM_Moore_000 DUT (D, _rst, clk, Q);

initial begin
  clk = 0;
  forever #5 clk = ~clk;
end

initial begin
  _rst = 1;
  repeat(2) #1 _rst = ~_rst;
end

initial begin
  D = 0;
end

always @(posedge clk) #3 D = $random;

initial
  #700 $finish;

initial begin            
    $dumpfile("qqq.vcd");
    $dumpvars;
end

endmodule

MPEI_Bachelor/projects/Лр4/КМ4/Snail_FSM_000/qqq.vcd
$date
	Fri Dec 16 22:02:04 2022
$end
$version
	Icarus Verilog
$end
$timescale
	1ns
$end
$scope module tb_SnailFSM_000 $end
$var wire 64 ! state [63:0] $end
$var wire 1 " Q $end
$var reg 1 # D $end
$var reg 1 $ _rst $end
$var reg 1 % clk $end
$scope module DUT $end
$var wire 1 # D $end
$var wire 1 $ _rst $end
$var wire 1 % clk $end
$var parameter 32 & HOORAY $end
$var parameter 32 ' HOPE1 $end
$var parameter 32 ( HOPE2 $end
$var parameter 32 ) SAD $end
$var reg 1 " Q $end
$var reg 1 * Q_nonsynch $end
$var reg 2 + nextstate [1:0] $end
$var reg 2 , state [1:0] $end
$var reg 64 - txstate [63:0] $end
$upscope $end
$upscope $end
$enddefinitions $end
$comment Show the parameter values. $end
$dumpall
b0 )
b10 (
b1 '
b11 &
$end
#0
$dumpvars
bx -
bx ,
b0 +
x*
0%
1$
0#
x"
bx !
$end
#1
0*
b10100110100000101000100 !
b10100110100000101000100 -
b1 +
b0 ,
0"
0$
#2
1$
#5
b100100001001111010100000100010100110001 !
b100100001001111010100000100010100110001 -
b10 +
b1 ,
1%
#10
0%
#15
b100100001001111010100000100010100110010 !
b100100001001111010100000100010100110010 -
b11 +
b10 ,
1%
#18
b0 +
1#
#20
0%
#25
b10100110100000101000100 !
b10100110100000101000100 -
b0 ,
1%
#30
0%
#35
1%
#40
0%
#45
1%
#50
0%
#55
1%
#60
0%
#65
1%
#70
0%
#75
1%
#78
b1 +
0#
#80
0%
#85
b100100001001111010100000100010100110001 !
b100100001001111010100000100010100110001 -
b10 +
b1 ,
1%
#88
b1 +
1#
#90
0%
#95
1%
#100
0%
#105
1%
#108
b10 +
0#
#110
0%
#115
b100100001001111010100000100010100110010 !
b100100001001111010100000100010100110010 -
b11 +
b10 ,
1%
#118
b0 +
1#
#120
0%
#125
b10100110100000101000100 !
b10100110100000101000100 -
b0 ,
1%
#130
0%
#135
1%
#138
b1 +
0#
#140
0%
#145
b100100001001111010100000100010100110001 !
b100100001001111010100000100010100110001 -
b10 +
b1 ,
1%
#148
b1 +
1#
#150
0%
#155
1%
#158
b10 +
0#
#160
0%
#165
b100100001001111010100000100010100110010 !
b100100001001111010100000100010100110010 -
b11 +
b10 ,
1%
#168
b0 +
1#
#170
0%
#175
b10100110100000101000100 !
b10100110100000101000100 -
b0 ,
1%
#178
b1 +
0#
#180
0%
#185
b100100001001111010100000100010100110001 !
b100100001001111010100000100010100110001 -
b10 +
b1 ,
1%
#188
b1 +
1#
#190
0%
#195
1%
#200
0%
#205
1%
#208
b10 +
0#
#210
0%
#215
b100100001001111010100000100010100110010 !
b100100001001111010100000100010100110010 -
b11 +
b10 ,
1%
#218
b0 +
1#
#220
0%
#225
b10100110100000101000100 !
b10100110100000101000100 -
b0 ,
1%
#228
b1 +
0#
#230
0%
#235
b100100001001111010100000100010100110001 !
b100100001001111010100000100010100110001 -
b10 +
b1 ,
1%
#240
0%
#245
b100100001001111010100000100010100110010 !
b100100001001111010100000100010100110010 -
b11 +
b10 ,
1%
#250
0%
#255
b10010000100111101001111010100100100000101011001 !
b10010000100111101001111010100100100000101011001 -
1*
b1 +
b11 ,
1%
#258
b0 +
1#
#260
0%
#265
0*
b10100110100000101000100 !
b10100110100000101000100 -
1"
b0 ,
1%
#268
b1 +
0#
#270
0%
#275
b100100001001111010100000100010100110001 !
b100100001001111010100000100010100110001 -
b10 +
b1 ,
0"
1%
#278
b1 +
1#
#280
0%
#285
1%
#290
0%
#295
1%
#300
0%
#305
1%
#310
0%
#315
1%
#318
b10 +
0#
#320
0%
#325
b100100001001111010100000100010100110010 !
b100100001001111010100000100010100110010 -
b11 +
b10 ,
1%
#330
0%
#335
b10010000100111101001111010100100100000101011001 !
b10010000100111101001111010100100100000101011001 -
1*
b1 +
b11 ,
1%
#340
0%
#345
0*
b100100001001111010100000100010100110001 !
b100100001001111010100000100010100110001 -
b10 +
1"
b1 ,
1%
#350
0%
#355
b100100001001111010100000100010100110010 !
b100100001001111010100000100010100110010 -
b11 +
b10 ,
0"
1%
#358
b0 +
1#
#360
0%
#365
b10100110100000101000100 !
b10100110100000101000100 -
b0 ,
1%
#368
b1 +
0#
#370
0%
#375
b100100001001111010100000100010100110001 !
b100100001001111010100000100010100110001 -
b10 +
b1 ,
1%
#378
b1 +
1#
#380
0%
#385
1%
#390
0%
#395
1%
#400
0%
#405
1%
#410
0%
#415
1%
#420
0%
#425
1%
#428
b10 +
0#
#430
0%
#435
b100100001001111010100000100010100110010 !
b100100001001111010100000100010100110010 -
b11 +
b10 ,
1%
#440
0%
#445
b10010000100111101001111010100100100000101011001 !
b10010000100111101001111010100100100000101011001 -
1*
b1 +
b11 ,
1%
#448
b0 +
1#
#450
0%
#455
0*
b10100110100000101000100 !
b10100110100000101000100 -
b0 ,
1"
1%
#460
0%
#465
0"
1%
#470
0%
#475
1%
#478
b1 +
0#
#480
0%
#485
b100100001001111010100000100010100110001 !
b100100001001111010100000100010100110001 -
b10 +
b1 ,
1%
#490
0%
#495
b100100001001111010100000100010100110010 !
b100100001001111010100000100010100110010 -
b11 +
b10 ,
1%
#500
0%
#505
b10010000100111101001111010100100100000101011001 !
b10010000100111101001111010100100100000101011001 -
1*
b1 +
b11 ,
1%
#510
0%
#515
0*
b100100001001111010100000100010100110001 !
b100100001001111010100000100010100110001 -
b10 +
b1 ,
1"
1%
#520
0%
#525
b100100001001111010100000100010100110010 !
b100100001001111010100000100010100110010 -
b11 +
0"
b10 ,
1%
#528
b0 +
1#
#530
0%
#535
b10100110100000101000100 !
b10100110100000101000100 -
b0 ,
1%
#538
b1 +
0#
#540
0%
#545
b100100001001111010100000100010100110001 !
b100100001001111010100000100010100110001 -
b10 +
b1 ,
1%
#550
0%
#555
b100100001001111010100000100010100110010 !
b100100001001111010100000100010100110010 -
b11 +
b10 ,
1%
#558
b0 +
1#
#560
0%
#565
b10100110100000101000100 !
b10100110100000101000100 -
b0 ,
1%
#570
0%
#575
1%
#578
b1 +
0#
#580
0%
#585
b100100001001111010100000100010100110001 !
b100100001001111010100000100010100110001 -
b10 +
b1 ,
1%
#590
0%
#595
b100100001001111010100000100010100110010 !
b100100001001111010100000100010100110010 -
b11 +
b10 ,
1%
#600
0%
#605
1*
b10010000100111101001111010100100100000101011001 !
b10010000100111101001111010100100100000101011001 -
b1 +
b11 ,
1%
#610
0%
#615
b100100001001111010100000100010100110001 !
b100100001001111010100000100010100110001 -
0*
b10 +
b1 ,
1"
1%
#620
0%
#625
b100100001001111010100000100010100110010 !
b100100001001111010100000100010100110010 -
b11 +
0"
b10 ,
1%
#628
b0 +
1#
#630
0%
#635
b10100110100000101000100 !
b10100110100000101000100 -
b0 ,
1%
#640
0%
#645
1%
#650
0%
#655
1%
#660
0%
#665
1%
#670
0%
#675
1%
#678
b1 +
0#
#680
0%
#685
b100100001001111010100000100010100110001 !
b100100001001111010100000100010100110001 -
b10 +
b1 ,
1%
#690
0%
#695
b100100001001111010100000100010100110010 !
b100100001001111010100000100010100110010 -
b11 +
b10 ,
1%
#698
b0 +
1#
