MPEI_Magistracy/Term_1/digital_design/KM_1_adders/Example/Ripple_carry_adder/f_adder.sv
module f_adder (A,B,P,S,C);
    input  logic   A;
    input  logic   B;
    input  logic   P;
    output logic   S;
    output logic   C;
    
    assign {C, S}= A+B+P;
endmodule

MPEI_Magistracy/Term_one/digital_design/KM_1_adders/Example/Ripple_carry_adder/ripple_carry_adder.sv
`include "f_adder.sv"
module ripple_carry_adder
# (
    parameter W = 8
)
(
    input                     carry_in,
    input  logic [W - 1 : 0]  A,
    input  logic [W - 1 : 0]  B,
    input  logic              CLK_i,
    input  logic              RST_N_I,
    output logic [W - 1 : 0]  S,
    output                    carry_out,
    output logic [W     : 0]  full_add
);
    logic  [W : 0] carry;

    logic [ W-1 : 0 ] A_ff;
    logic [ W-1 : 0 ] B_ff;
    logic             P_ff;
    logic             C_ff;
    logic [ W-1 : 0 ] S_ff;
    logic [ W-1 : 0 ] A_ff_w;
    logic [ W-1 : 0 ] B_ff_w;
    logic [ W   : 0 ] P_ff_w;
    logic [ W-1 : 0 ] S_ff_w;

    always_ff @(posedge CLK_i or negedge RST_N_I) begin
            if(!RST_N_I) begin
                A_ff <= 0;
                B_ff <= 0;
                P_ff <= 0;
                S_ff <= 0;
                C_ff <= 0;
            end
            else begin
                A_ff <= A;
                B_ff <= B;
                P_ff <= carry_in;
                S_ff <= S_ff_w;
                C_ff <= carry[W];
            end
        end

    assign carry[0]  = P_ff;
    assign A_ff_w    = A_ff;
    assign B_ff_w    = B_ff;
    assign S         = S_ff;
    assign carry_out = C_ff;
    generate
    genvar i;
        for (i = 0; i <= W - 1; i = i + 1) begin : stage
            f_adder 
            FA(
                .A (A_ff_w [i] ),
                .B (B_ff_w [i] ),
                .S (S_ff_w [i] ),
                .P (carry[i] ),
                .C(carry[i + 1])
            );
        end
    endgenerate

assign full_add = {carry_out, S};
endmodule

MPEI_Magistracy/Term_1/digital_design/KM_1_adders/Example/Ripple_carry_adder/ripple_carry_adder_tb.sv
`include "ripple_carry_adder.sv"
`timescale 1 ps/ 1 ps

module ripple_carry_adder_tb
    #(
        parameter W = 8 
    );

    logic               CLK_i;
    logic               RST_N_I;

    logic [ W-1 : 0 ]   A_i;
    logic [ W-1 : 0 ]   B_i;
    logic [ W-1 : 0 ]   S_o;
    logic [ W   : 0 ]   full_add;
    logic               P_i; 
    logic               C_o; 
           
    ripple_carry_adder
    #( .W(W) 
    )
    UUT (.CLK_i(CLK_i), .RST_N_I(RST_N_I), 
         .A(A_i), .B(B_i), .carry_in(P_i), 
         .S(S_o), .carry_out(C_o), .full_add(full_add)
    );
        initial begin
            $display("Running testbench");
            CLK_i = 0;
            A_i   = 0;
            B_i   = 0;
            P_i   = 0;
        end
        always #5  CLK_i =  !CLK_i; 

        initial begin
            RST_N_I = 1;
            repeat (2) #1 RST_N_I = !RST_N_I;
            end      
        initial begin
            for (int i = 0; i <= 2**W; i++) begin
              A_i = $urandom_range(0, 2**W);
              B_i = $urandom_range(0, 2**W);;   
              P_i = $urandom_range(0, 1);
              #10;                     
            end
        end
        initial begin
            #50000 $display("Testbench is OK!");
                   $finish;
        end

        initial begin
            $dumpfile("qqq.vcd");
            $dumpvars;
        end
endmodule

MPEI_Magistracy/Term_1/digital_design/KM_1_adders/Example/Ripple_carry_adder/qqq.vcd
$date
	Mon Sep 25 06:38:14 2023
$end
$version
	Icarus Verilog
$end
$timescale
	1ps
$end
$scope module ripple_carry_adder_tb $end
$var wire 9 ! full_add [8:0] $end
$var wire 8 " S_o [7:0] $end
$var wire 1 # C_o $end
$var parameter 32 $ W $end
$var reg 8 % A_i [7:0] $end
$var reg 8 & B_i [7:0] $end
$var reg 1 ' CLK_i $end
$var reg 1 ( P_i $end
$var reg 1 ) RST_N_I $end
$scope module UUT $end
$var wire 8 * A [7:0] $end
$var wire 8 + A_ff_w [7:0] $end
$var wire 8 , B [7:0] $end
$var wire 8 - B_ff_w [7:0] $end
$var wire 1 ' CLK_i $end
$var wire 1 ) RST_N_I $end
$var wire 1 ( carry_in $end
$var wire 1 # carry_out $end
$var wire 9 . full_add [8:0] $end
$var wire 9 / carry [8:0] $end
$var wire 8 0 S_ff_w [7:0] $end
$var wire 8 1 S [7:0] $end
$var parameter 32 2 W $end
$var reg 8 3 A_ff [7:0] $end
$var reg 8 4 B_ff [7:0] $end
$var reg 1 # C_ff $end
$var reg 1 5 P_ff $end
$var reg 8 6 S_ff [7:0] $end
$scope begin stage[0] $end
$var parameter 2 7 i $end
$scope module FA $end
$var wire 1 8 A $end
$var wire 1 9 B $end
$var wire 1 : P $end
$var wire 1 ; S $end
$var wire 1 < C $end
$upscope $end
$upscope $end
$scope begin stage[1] $end
$var parameter 2 = i $end
$scope module FA $end
$var wire 1 > A $end
$var wire 1 ? B $end
$var wire 1 @ P $end
$var wire 1 A S $end
$var wire 1 B C $end
$upscope $end
$upscope $end
$scope begin stage[2] $end
$var parameter 3 C i $end
$scope module FA $end
$var wire 1 D A $end
$var wire 1 E B $end
$var wire 1 F P $end
$var wire 1 G S $end
$var wire 1 H C $end
$upscope $end
$upscope $end
$scope begin stage[3] $end
$var parameter 3 I i $end
$scope module FA $end
$var wire 1 J A $end
$var wire 1 K B $end
$var wire 1 L P $end
$var wire 1 M S $end
$var wire 1 N C $end
$upscope $end
$upscope $end
$scope begin stage[4] $end
$var parameter 4 O i $end
$scope module FA $end
$var wire 1 P A $end
$var wire 1 Q B $end
$var wire 1 R P $end
$var wire 1 S S $end
$var wire 1 T C $end
$upscope $end
$upscope $end
$scope begin stage[5] $end
$var parameter 4 U i $end
$scope module FA $end
$var wire 1 V A $end
$var wire 1 W B $end
$var wire 1 X P $end
$var wire 1 Y S $end
$var wire 1 Z C $end
$upscope $end
$upscope $end
$scope begin stage[6] $end
$var parameter 4 [ i $end
$scope module FA $end
$var wire 1 \ A $end
$var wire 1 ] B $end
$var wire 1 ^ P $end
$var wire 1 _ S $end
$var wire 1 ` C $end
$upscope $end
$upscope $end
$scope begin stage[7] $end
$var parameter 4 a i $end
$scope module FA $end
$var wire 1 b A $end
$var wire 1 c B $end
$var wire 1 d P $end
$var wire 1 e S $end
$var wire 1 f C $end
$upscope $end
$upscope $end
$upscope $end
$scope begin $ivl_for_loop0 $end
$var integer 32 g i [31:0] $end
$upscope $end
$upscope $end
$enddefinitions $end
$comment Show the parameter values. $end
$dumpall
b111 a
b110 [
b101 U
b100 O
b11 I
b10 C
b1 =
b0 7
b1000 2
b1000 $
$end
#0
$dumpvars
b0 g
xf
xe
xd
xc
xb
x`
x_
x^
x]
x\
xZ
xY
xX
xW
xV
xT
xS
xR
xQ
xP
xN
xM
xL
xK
xJ
xH
xG
xF
xE
xD
xB
xA
x@
x?
x>
x<
x;
x:
x9
x8
bx 6
x5
bx 4
bx 3
bx 1
bx 0
bx /
bx .
bx -
b1000000 ,
bx +
b10010010 *
1)
0(
0'
b1000000 &
b10010010 %
x#
bx "
bx !
$end
#1
0e
0f
0d
0_
0`
0^
0Y
0Z
0X
0S
0T
0R
0M
0N
0L
0G
0H
0F
0A
0B
0@
b0 0
0;
0<
0:
09
0?
0E
0K
0Q
0W
0]
0c
08
0>
0D
0J
0P
0V
0\
0b
0#
b0 !
b0 .
b0 "
b0 1
b0 6
b0 /
05
b0 -
b0 4
b0 +
b0 3
0)
#2
1)
#5
1_
1A
1S
b11010010 0
1e
1]
1>
1P
1b
b1000000 -
b1000000 4
b10010010 +
b10010010 3
1'
#10
0'
1(
b10000111 &
b10000111 ,
b110010 %
b110010 *
b1 g
#15
1M
1L
1H
1@
1F
1<
1A
1B
0G
0_
b10111010 0
1Y
1:
19
1?
1E
0]
1c
1V
0b
b11010010 !
b11010010 .
b11010010 "
b11010010 1
b11010010 6
b1111 /
15
b10000111 -
b10000111 4
b110010 +
b110010 3
1'
#20
0'
b1001 &
b1001 ,
b10 g
#25
0_
0^
1Y
0Z
0X
1S
0T
0L
0R
0A
1G
0H
1M
b111 /
0N
b111100 0
0e
0?
0E
1K
0c
b10111010 !
b10111010 .
b10111010 "
b10111010 1
b10111010 6
b1001 -
b1001 4
1'
#30
0'
b10111011 &
b10111011 ,
b10000111 %
b10000111 *
b11 g
#35
1_
1^
0Y
1Z
1X
0S
1T
1R
0M
1N
1L
1A
1f
1;
b1000011 0
0G
b101111111 /
1H
1?
1Q
1W
1c
18
1D
0P
0V
1b
b111100 !
b111100 .
b111100 "
b111100 1
b111100 6
b10111011 -
b10111011 4
b10000111 +
b10000111 3
1'
#40
0'
b11000110 &
b11000110 ,
b11110111 %
b11110111 *
b100 g
#45
0_
0^
1Y
0Z
0X
1S
0T
1e
0R
1d
0;
1G
b10111110 0
1M
0N
b110001111 /
1`
09
1E
0K
0Q
0W
1]
1P
1V
1\
1#
b101000011 !
b101000011 .
b1000011 "
b1000011 1
b1000011 6
b11000110 -
b11000110 4
b11110111 +
b11110111 3
1'
#50
0'
0(
b1100011 &
b1100011 ,
b1100011 %
b1100011 *
b101 g
#55
0M
1_
0L
1^
0H
0Y
1Z
0f
b11000110 0
0S
0:
19
0E
1W
0c
0D
0P
0b
b110111110 !
b110111110 .
b10111110 "
b10111110 1
b10111110 6
b11000110 /
05
b1100011 -
b1100011 4
b1100011 +
b1100011 3
1'
#60
0'
b111100 &
b111100 ,
b11110011 %
b11110011 *
b110 g
#65
0S
0F
0R
0B
0N
1Y
0@
0L
1X
1;
0<
1A
1G
0H
1M
1T
0_
b101111 0
0e
b111100000 /
1f
09
0?
1E
1K
1Q
0]
1P
1b
0#
b11000110 !
b11000110 .
b11000110 "
b11000110 1
b11000110 6
b111100 -
b111100 4
b11110011 +
b11110011 3
1'
#70
0'
b11111010 &
b11111010 ,
b11001000 %
b11001000 *
b111 g
#75
1^
1Z
1R
1X
0G
1_
1e
0;
0M
1N
0S
b111110000 /
1T
b11000010 0
0Y
1?
0E
1]
1c
08
0>
1J
0P
0V
1#
b100101111 !
b100101111 .
b101111 "
b101111 1
b101111 6
b11111010 -
b11111010 4
b11001000 +
b11001000 3
1'
#80
0'
1(
b1100011 &
b1100011 ,
b1110100 %
b1110100 *
b1000 g
#85
1M
1L
1H
1F
0X
0A
1B
1S
0T
1@
0R
1<
0f
0G
0N
b11011000 0
0Y
1:
19
0K
0Q
0c
1D
0J
1P
1V
0b
b111000010 !
b111000010 .
b11000010 "
b11000010 1
b11000010 6
b11001111 /
15
b1100011 -
b1100011 4
b1110100 +
b1110100 3
1'
#90
0'
0(
b10110 &
b10110 ,
b1011110 %
b1011110 *
b1001 g
#95
0e
0d
1Y
0`
0@
1X
1R
0^
0<
1G
1S
1T
1_
0A
b1110100 0
0M
1N
0Z
0:
09
1E
1Q
0W
0]
1>
1J
0V
0#
b11011000 !
b11011000 .
b11011000 "
b11011000 1
b11011000 6
b111100 /
05
b10110 -
b10110 4
b1011110 +
b1011110 3
1'
#100
0'
b10000101 &
b10000101 ,
b110010 %
b110010 *
b1010 g
#105
0L
0X
0H
0T
0F
0R
0^
1;
1A
0B
1S
1e
1G
0M
0N
1Y
b0 /
0Z
b10110111 0
0_
19
0?
0Q
1c
0D
0J
1V
0\
b1110100 !
b1110100 .
b1110100 "
b1110100 1
b1110100 6
b10000101 -
b10000101 4
b110010 +
b110010 3
1'
#110
0'
b11010110 &
b11010110 ,
b10010000 %
b10010000 *
b1011 g
#115
1X
0;
0S
1T
1_
1Y
b1100110 0
0e
b100100000 /
1f
09
1?
1Q
1]
0>
0V
1b
b10110111 !
b10110111 .
b10110111 "
b10110111 1
b10110111 6
b11010110 -
b11010110 4
b10010000 +
b10010000 3
1'
#120
0'
b1001 &
b1001 ,
b1001011 %
b1001011 *
b1100 g
#125
1F
0A
1B
1S
0Y
1@
1R
0X
1<
b1010100 0
1G
1N
0T
b10110 /
0f
19
0?
0E
1K
0Q
0]
0c
18
1>
1J
0P
1\
0b
1#
b101100110 !
b101100110 .
b1100110 "
b1100110 1
b1100110 6
b1001 -
b1001 4
b1001011 +
b1001011 3
1'
#130
0'
b10110110 &
b10110110 ,
b101001 %
b101001 *
b1101 g
#135
0F
1A
0B
0Y
0@
0L
0R
0X
1^
1;
0<
1G
0H
1M
0N
1S
0T
b1000000 /
1Z
1e
b11011111 0
1_
09
1?
1E
0K
1Q
1W
1c
0>
1V
0\
0#
b1010100 !
b1010100 .
b1010100 "
b1010100 1
b1010100 6
b10110110 -
b10110110 4
b101001 +
b101001 3
1'
#140
0'
1(
b1010111 &
b1010111 ,
b1 %
b1 *
b1110 g
#145
1L
0G
1H
1F
0A
1B
1@
0d
0^
1<
1_
0`
0e
b1011001 0
1M
0Z
1:
19
0W
1]
0c
0J
0V
b11011111 !
b11011111 .
b11011111 "
b11011111 1
b11011111 6
b1111 /
15
b1010111 -
b1010111 4
b1 +
b1 3
1'
#150
0'
b10010010 &
b10010010 ,
b1101000 %
b1101000 *
b1111 g
#155
0f
0d
1_
0`
0^
0Z
0F
0X
1A
0B
1S
0T
0@
0L
0R
0<
0G
0H
1e
1M
b1 /
0N
b11111011 0
1Y
09
0E
0]
1c
08
1J
1V
1\
b1011001 !
b1011001 .
b1011001 "
b1011001 1
b1011001 6
b10010010 -
b10010010 4
b1101000 +
b1101000 3
1'
#160
0'
b11110 &
b11110 ,
b1100101 %
b1100101 *
b10000 g
#165
1d
0_
1`
1^
0Y
1Z
1X
0S
1T
1G
1R
1F
0M
1N
0A
1B
1L
1@
1H
1e
b10000100 0
0;
b11111111 /
1<
1E
1K
0c
18
1D
0J
b11111011 !
b11111011 .
b11111011 "
b11111011 1
b11111011 6
b11110 -
b11110 4
b1100101 +
b1100101 3
1'
#170
0'
0(
b10100001 &
b10100001 ,
b11000101 %
b11000101 *
b10001 g
#175
0e
0d
1_
0`
0L
0^
0H
1Y
0Z
0F
0R
0X
1A
0B
1G
0M
0N
b1100110 0
0S
0T
1f
0:
19
0?
0E
0K
0Q
1W
1c
0V
1b
b10000100 !
b10000100 .
b10000100 "
b10000100 1
b10000100 6
b100000010 /
05
b10100001 -
b10100001 4
b11000101 +
b11000101 3
1'
#180
0'
1(
b1000100 &
b1000100 ,
b10111100 %
b10111100 *
b10010 g
#185
1d
0_
1`
1^
0Y
1Z
1X
1T
1R
1N
0A
1L
0@
0G
1H
0e
1f
1;
0<
0M
b1 0
0S
1:
09
1E
0W
1]
0c
08
1J
1P
1V
0\
1#
b101100110 !
b101100110 .
b1100110 "
b1100110 1
b1100110 6
b111111001 /
15
b1000100 -
b1000100 4
b10111100 +
b10111100 3
1'
#190
0'
b11100100 &
b11100100 ,
b11011011 %
b11011011 *
b10011 g
#195
1^
0Y
1Z
1X
0S
1T
1F
1R
1B
0M
1N
1@
1L
1e
0;
1<
0A
0G
b111111111 /
1H
b11000000 0
1_
1W
1c
18
1>
0D
0V
1\
b100000001 !
b100000001 .
b1 "
b1 1
b1 6
b11100100 -
b11100100 4
b11011011 +
b11011011 3
1'
#200
0'
0(
b10010101 &
b10010101 ,
b1011110 %
b1011110 *
b10100 g
#205
0f
0d
0F
0`
1A
0B
0^
0@
1S
1Y
0Z
1_
1;
0<
0G
b11110011 0
1e
0:
19
1Q
0W
0]
08
1D
0b
b111000000 !
b111000000 .
b11000000 "
b11000000 1
b11000000 6
b111000 /
05
b10010101 -
b10010101 4
b1011110 +
b1011110 3
1'
#210
0'
1(
b11000011 &
b11000011 ,
b111000 %
b111000 *
b10101 g
#215
0X
1G
0T
1e
0f
1F
0R
0d
0A
1B
1M
0N
1_
0`
1@
0L
0^
0;
1<
1S
0H
b11111100 0
1Y
0Z
1:
1?
0E
0Q
1]
0>
0D
1V
0\
0#
b11110011 !
b11110011 .
b11110011 "
b11110011 1
b11110011 6
b111 /
15
b11000011 -
b11000011 4
b111000 +
b111000 3
1'
#220
0'
0(
b10011101 &
b10011101 ,
b11101 %
b11101 *
b10110 g
#225
0G
0F
1R
1X
1L
1A
0B
1M
1N
1S
1T
0_
1H
b10111010 0
1Y
0:
0?
1E
1K
1Q
0]
18
1D
0V
b11111100 !
b11111100 .
b11111100 "
b11111100 1
b11111100 6
b111010 /
05
b10011101 -
b10011101 4
b11101 +
b11101 3
1'
#230
0'
1(
b11111001 &
b11111001 ,
b10001011 %
b10001011 *
b10111 g
#235
1d
1`
1G
0M
1^
1F
0L
1;
0Y
1Z
0_
0A
1B
0H
0S
b10000101 0
1e
1f
1:
0E
1W
1]
1>
0D
0P
1b
b10111010 !
b10111010 .
b10111010 "
b10111010 1
b10111010 6
b111110111 /
15
b11111001 -
b11111001 4
b10001011 +
b10001011 3
1'
#240
0'
b10100110 &
b10100110 ,
b10110001 %
b10110001 *
b11000 g
#245
0X
1M
0e
1S
0T
1L
0d
0R
0;
0G
1H
1_
0`
b101001111 /
0N
b1011000 0
0Y
09
1?
1E
0K
0Q
0]
0>
0J
1P
1V
1#
b110000101 !
b110000101 .
b10000101 "
b10000101 1
b10000101 6
b10100110 -
b10100110 4
b10110001 +
b10110001 3
1'
#250
0'
0(
b11111101 &
b11111101 ,
b11001000 %
b11001000 *
b11001 g
#255
0M
0L
1X
1G
0H
0S
1T
1_
1e
0F
0@
1R
1^
1d
0A
0B
1;
0<
1N
b11000101 0
0Y
1Z
1`
0:
19
0?
1K
1Q
1]
08
1J
0P
0V
1\
b101011000 !
b101011000 .
b1011000 "
b1011000 1
b1011000 6
b111110000 /
05
b11111101 -
b11111101 4
b11001000 +
b11001000 3
1'
#260
0'
b101110 &
b101110 ,
b1010000 %
b1010000 *
b11010 g
#265
0e
0d
0`
0^
1Y
0Z
0X
1S
0T
0R
0;
1A
1_
0f
b1111110 0
1M
b0 /
0N
09
1?
0Q
0]
0c
0J
1P
0b
b111000101 !
b111000101 .
b11000101 "
b11000101 1
b11000101 6
b101110 -
b101110 4
b1010000 +
b1010000 3
1'
#270
0'
b100100 &
b100100 ,
b11000101 %
b11000101 *
b11011 g
#275
1L
0A
1M
1;
0G
b1000 /
1H
0S
b11101001 0
1e
0?
0K
18
1D
0P
1b
0#
b1111110 !
b1111110 .
b1111110 "
b1111110 1
b1111110 6
b100100 -
b100100 4
b11000101 +
b11000101 3
1'
#280
0'
1(
b101000 &
b101000 ,
b1101100 %
b1101100 *
b11100 g
#285
1d
0M
1S
0_
1`
0L
1R
1^
1G
0H
1N
0Y
1Z
b10010101 0
1e
1:
0E
1K
08
1J
1V
0b
b11101001 !
b11101001 .
b11101001 "
b11101001 1
b11101001 6
b11010001 /
15
b101000 -
b101000 4
b1101100 +
b1101100 3
1'
#290
0'
b1100001 &
b1100001 ,
b10000110 %
b10000110 *
b11101 g
#295
1M
1L
0G
1H
1F
0d
1B
0S
1_
0`
1@
0R
0^
0;
1<
0A
0N
1Y
0Z
b11101000 0
1e
b1111 /
0f
19
0K
1]
1>
0J
0V
0\
1b
b10010101 !
b10010101 .
b10010101 "
b10010101 1
b10010101 6
b1100001 -
b1100001 4
b10000110 +
b10000110 3
1'
#300
0'
b10011111 &
b10011111 ,
b111011 %
b111011 *
b11110 g
#305
1^
0Y
1Z
1S
1X
1R
1A
1T
1_
b11011011 0
1;
b1111111 /
1N
1?
1E
1K
1Q
0W
0]
1c
18
0D
1J
1P
1V
0b
b11101000 !
b11101000 .
b11101000 "
b11101000 1
b11101000 6
b10011111 -
b10011111 4
b111011 +
b111011 3
1'
#310
0'
b10110111 &
b10110111 ,
b111111 %
b111111 *
b11111 g
#315
0M
1Y
b11110111 0
1G
0K
1W
1D
b11011011 !
b11011011 .
b11011011 "
b11011011 1
b11011011 6
b10110111 -
b10110111 4
b111111 +
b111111 3
1'
#320
0'
b1101010 &
b1101010 ,
b10010000 %
b10010000 *
b100000 g
#325
0^
0Z
0X
0G
0T
0F
0R
0B
1M
0N
1e
0f
0@
0L
0d
0<
0H
1S
1_
b1 /
0`
1A
b11111011 0
1Y
09
0E
1K
0Q
1]
0c
08
0>
0D
0J
0V
1b
b11110111 !
b11110111 .
b11110111 "
b11110111 1
b11110111 6
b1101010 -
b1101010 4
b10010000 +
b10010000 3
1'
#330
0'
b10101110 &
b10101110 ,
b111100 %
b111100 *
b100001 g
#335
1X
0S
1T
1L
1R
1^
1H
1_
1M
1N
b11101011 0
1Y
b1111001 /
1Z
1E
0]
1c
1D
1J
1V
0b
b11111011 !
b11111011 .
b11111011 "
b11111011 1
b11111011 6
b10101110 -
b10101110 4
b111100 +
b111100 3
1'
#340
0'
b10010101 &
b10010101 ,
b100000 %
b100000 *
b100010 g
#345
0_
0^
0Z
0X
1S
0T
0M
1@
0R
0L
0;
1<
1A
0N
1Y
b10110110 0
1G
b11 /
0H
19
0?
0K
1Q
0W
0D
0J
0P
b11101011 !
b11101011 .
b11101011 "
b11101011 1
b11101011 6
b10010101 -
b10010101 4
b100000 +
b100000 3
1'
#350
0'
0(
b1000111 &
b1000111 ,
b1000011 %
b1000011 *
b100011 g
#355
1M
1L
0G
1H
1d
1F
0S
1`
1e
1B
b10001010 0
0Y
0:
1?
0Q
1]
0c
18
1>
0V
1\
b10110110 !
b10110110 .
b10110110 "
b10110110 1
b10110110 6
b10001110 /
05
b1000111 -
b1000111 4
b1000011 +
b1000011 3
1'
#360
0'
1(
b10011 &
b10011 ,
b11111110 %
b11111110 *
b100100 g
#365
1^
1Z
1S
1X
1d
1R
1T
0_
1`
0M
1N
0Y
b10010 0
0e
1f
1:
0E
1Q
0]
08
1D
1J
1P
1V
1b
b10001010 !
b10001010 .
b10001010 "
b10001010 1
b10001010 6
b111111111 /
15
b10011 -
b10011 4
b11111110 +
b11111110 3
1'
#370
0'
0(
b10111 &
b10111 ,
b1010001 %
b1010001 *
b100101 g
#375
0d
0S
1_
0`
0R
0^
0A
1M
0N
1Y
0Z
b1101000 0
0e
0f
0:
1E
18
0>
0D
0J
0V
0b
1#
b100010010 !
b100010010 .
b10010 "
b10010 1
b10010 6
b101110 /
05
b10111 -
b10111 4
b1010001 +
b1010001 3
1'
#380
0'
1(
b10100010 &
b10100010 ,
b110000 %
b110000 *
b100110 g
#385
0F
0M
0Y
1A
0B
0L
0X
0@
1^
0G
0H
1S
0T
1e
1;
0<
1Z
b11010011 0
1_
1:
09
0E
0Q
1W
1c
08
1V
0\
0#
b1101000 !
b1101000 .
b1101000 "
b1101000 1
b1101000 6
b1000001 /
15
b10100010 -
b10100010 4
b110000 +
b110000 3
1'
#390
0'
b1110011 &
b1110011 ,
b1100110 %
b1100110 *
b100111 g
#395
1M
1L
1H
1@
1F
1d
0;
1<
1e
1A
1B
b11011010 0
0G
b11001111 /
1`
19
1Q
1]
0c
1>
1D
0P
1\
b11010011 !
b11010011 .
b11010011 "
b11010011 1
b11010011 6
b1110011 -
b1110011 4
b1100110 +
b1100110 3
1'
#400
0'
0(
b1110110 &
b1110110 ,
b10010101 %
b10010101 *
b101000 g
#405
0F
1d
0B
1`
0@
1X
1^
0<
0G
1;
1A
0S
1T
0Y
1Z
0_
b1011 0
0e
1f
0:
09
1E
18
0>
1P
0V
0\
1b
b11011010 !
b11011010 .
b11011010 "
b11011010 1
b11011010 6
b111101000 /
05
b1110110 -
b1110110 4
b10010101 +
b10010101 3
1'
#410
0'
b1011010 &
b1011010 ,
b110010 %
b110010 *
b101001 g
#415
0S
1G
0R
1F
0L
1M
0N
0;
0A
1B
0H
b10001100 0
1e
b11100100 /
0f
0E
1K
0W
08
1>
0D
1V
0b
1#
b100001011 !
b100001011 .
b1011 "
b1011 1
b1011 6
b1011010 -
b1011010 4
b110010 +
b110010 3
1'
#420
0'
b10100010 &
b10100010 ,
b10111101 %
b10111101 *
b101010 g
#425
0R
0e
1M
0N
0X
0d
0F
0L
1S
0T
0Y
1_
0`
1;
1A
0B
b1011111 0
1G
0H
b101000000 /
1f
0K
0Q
1W
0]
1c
18
0>
1D
1J
1b
0#
b10001100 !
b10001100 .
b10001100 "
b10001100 1
b10001100 6
b10100010 -
b10100010 4
b10111101 +
b10111101 3
1'
#430
0'
1(
b11010110 &
b11010110 ,
b10010101 %
b10010101 *
b101011 g
#435
1F
0A
1B
1Y
0e
1@
1L
1X
0d
0^
0;
1<
1G
1H
0S
1T
1_
0`
b1101100 0
1M
0Z
1:
1E
1Q
0W
1]
0J
0V
1#
b101011111 !
b101011111 .
b1011111 "
b1011111 1
b1011111 6
b100101111 /
15
b11010110 -
b11010110 4
b10010101 +
b10010101 3
1'
#440
0'
0(
b1001101 &
b1001101 ,
b11101111 %
b11101111 *
b101100 g
#445
1S
1R
0X
0^
1d
0e
1f
1N
0T
1Y
0Z
b111100 0
0_
1`
0:
19
0?
1K
0Q
0c
1>
1J
0P
1V
1\
b101101100 !
b101101100 .
b1101100 "
b1101100 1
b1101100 6
b110011110 /
05
b1001101 -
b1001101 4
b11101111 +
b11101111 3
1'
#450
0'
1(
b10101011 &
b10101011 ,
b1100010 %
b1100010 *
b101101 g
#455
0S
0R
0N
0e
1f
0L
1^
1d
1A
0H
0Y
1Z
0_
1`
b1110 0
1M
1:
1?
0E
1W
0]
1c
08
0D
0J
0b
b100111100 !
b100111100 .
b111100 "
b111100 1
b111100 6
b111000111 /
15
b10101011 -
b10101011 4
b1100010 +
b1100010 3
1'
#460
0'
b101 &
b101 ,
b110100 %
b110100 *
b101110 g
#465
0G
0F
0^
1L
0d
0B
1M
1Y
0Z
0e
0f
1H
1S
b111010 0
0_
b1011 /
0`
0?
1E
0K
0W
0c
0>
1D
1P
0\
b100001110 !
b100001110 .
b1110 "
b1110 1
b1110 6
b101 -
b101 4
b110100 +
b110100 3
1'
#470
0'
0(
b10111101 &
b10111101 ,
b11100 %
b11100 *
b101111 g
#475
1_
1^
0A
0Y
1Z
0@
1X
1R
1;
0<
1S
1T
b11011001 0
1e
1N
0:
1K
1Q
1W
1c
1J
0V
0#
b111010 !
b111010 .
b111010 "
b111010 1
b111010 6
b1111000 /
05
b10111101 -
b10111101 4
b11100 +
b11100 3
1'
#480
0'
b11001010 &
b11001010 ,
b11001011 %
b11001011 *
b110000 g
#485
1G
0_
0M
1F
0X
0^
0L
1d
1B
0T
0Y
0Z
0H
1`
b10010101 0
1e
b110010100 /
1f
09
1?
0E
0Q
0W
1]
18
1>
0D
0P
1\
1b
b11011001 !
b11011001 .
b11011001 "
b11011001 1
b11011001 6
b11001010 -
b11001010 4
b11001011 +
b11001011 3
1'
#490
0'
b11101110 &
b11101110 ,
b101100 %
b101100 *
b110001 g
#495
0G
1M
1f
1^
0F
1L
1d
1Z
0;
1A
0B
1H
0_
b111011000 /
1`
b11010 0
0e
1E
1W
08
0>
1D
1V
0\
0b
1#
b110010101 !
b110010101 .
b10010101 "
b10010101 1
b10010101 6
b11101110 -
b11101110 4
b101100 +
b101100 3
1'
#500
0'
b110110 &
b110110 ,
b11101101 %
b11101101 *
b110010 g
#505
1Y
1X
0M
0S
b111111000 /
1T
b100011 0
1;
0K
1Q
0]
0c
18
1\
1b
b100011010 !
b100011010 .
b11010 "
b11010 1
b11010 6
b110110 -
b110110 4
b11101101 +
b11101101 3
1'
#510
0'
1(
b11011011 &
b11011011 ,
b11100110 %
b11100110 *
b110011 g
#515
1^
1Z
1X
0S
1T
1R
0M
1N
1@
1L
1F
1<
0G
1H
0Y
1_
1e
0;
b11000010 0
1A
1B
1:
19
0E
1K
0W
1]
1c
08
1>
0J
b100100011 !
b100100011 .
b100011 "
b100011 1
b100011 6
b111111111 /
15
b11011011 -
b11011011 4
b11100110 +
b11100110 3
1'
#520
0'
b10000010 &
b10000010 ,
b100011 %
b100011 *
b110100 g
#525
0_
0^
1Y
0Z
0f
0R
0X
0d
0L
0M
0N
0S
0T
0`
1G
b111 /
0H
b10100110 0
1e
09
0K
0Q
0]
18
0D
0\
0b
b111000010 !
b111000010 .
b11000010 "
b11000010 1
b11000010 6
b10000010 -
b10000010 4
b100011 +
b100011 3
1'
#530
0'
b1011010 &
b1011010 ,
b10110101 %
b10110101 *
b110101 g
#535
0e
1f
1d
1`
1S
1^
1R
0Y
1Z
1N
1X
1L
0M
1T
0_
0A
b10000 0
0G
b111111111 /
1H
1K
1Q
1]
0c
0>
1D
1P
1b
0#
b10100110 !
b10100110 .
b10100110 "
b10100110 1
b10100110 6
b1011010 -
b1011010 4
b10110101 +
b10110101 3
1'
#540
0'
0(
b10110 &
b10110 ,
b10010101 %
b10010101 *
b110110 g
#545
0F
1A
0B
0S
1e
0f
0@
0R
0d
0^
1;
0<
0G
1M
0N
0_
0`
b10101011 0
1Y
0Z
0:
1E
0K
0]
0V
1#
b100010000 !
b100010000 .
b10000 "
b10000 1
b10000 6
b101000 /
05
b10110 -
b10110 4
b10010101 +
b10010101 3
1'
#550
0'
1(
b100 &
b100 ,
b10111 %
b10111 *
b110111 g
#555
1G
1F
0A
1B
0Y
1@
0X
0;
1<
1S
0T
b11100 0
0e
1:
0?
0Q
1>
0b
0#
b10101011 !
b10101011 .
b10101011 "
b10101011 1
b10101011 6
b1111 /
15
b100 -
b100 4
b10111 +
b10111 3
1'
#560
0'
0(
b10010101 &
b10010101 ,
b1111111 %
b1111111 *
b111000 g
#565
1f
1d
1`
1^
1Z
1X
1R
1S
1T
0e
0M
1N
0Y
b10100 0
0_
0:
19
1Q
1c
1J
1V
1\
b11100 !
b11100 .
b11100 "
b11100 1
b11100 6
b111111110 /
05
b10010101 -
b10010101 4
b1111111 +
b1111111 3
1'
#570
0'
b1101101 &
b1101101 ,
b11000011 %
b11000011 *
b111001 g
#575
0^
1Y
0Z
0X
b110011110 /
0T
0_
b110000 0
0G
1K
0Q
1W
1]
0c
0D
0J
0P
0V
1b
1#
b100010100 !
b100010100 .
b10100 "
b10100 1
b10100 6
b1101101 -
b1101101 4
b11000011 +
b11000011 3
1'
#580
0'
b111000 &
b111000 ,
b10110100 %
b10110100 *
b111010 g
