MPEI_Bachelor/projects/Лр4/КМ4/cnt_position/cnt_FSM.v
module cnt_FSM(input clk, rst_n, output [7:0] Q);

localparam RESET  = 0,
		   COUNT0 = 8'b00000001,
		   COUNT1 = 8'b00000010,
	       COUNT2 = 8'b00000100,
	       COUNT3 = 8'b00001000,
	       COUNT4 = 8'b00010000,
	       COUNT5 = 8'b00100000,
	       COUNT6 = 8'b01000000,
	       COUNT7 = 8'b10000000;

reg [7:0] state, nextstate;

always @(posedge clk or negedge rst_n) //факт переходов
	if(!rst_n)
		state = RESET;
	else
		state = nextstate;

always @(*) //таблица переходов
	case(state)
		RESET  :  nextstate = COUNT0;
		COUNT0 :  nextstate = COUNT1;
		COUNT1 :  nextstate = COUNT2;
		COUNT2 :  nextstate = COUNT3;
		COUNT3 :  nextstate = COUNT4;
		COUNT4 :  nextstate = COUNT5;
		COUNT5 :  nextstate = COUNT6;
		COUNT6 :  nextstate = COUNT7;
		COUNT7 :  nextstate = COUNT0;
		default : nextstate = RESET;
	endcase

//выходная логика
assign Q = (state == RESET)  ? 0           :
		   (state == COUNT0) ? 8'b00000001 :
	       (state == COUNT1) ? 8'b00000010 :
	       (state == COUNT2) ? 8'b00000100 :
	       (state == COUNT3) ? 8'b00001000 :
	       (state == COUNT4) ? 8'b00010000 :
	       (state == COUNT5) ? 8'b00100000 :
	       (state == COUNT6) ? 8'b01000000 :
	       (state == COUNT7) ? 8'b10000000 : 0;

endmodule

MPEI_Bachelor/projects/Лр4/КМ4/cnt_position/tb_cnt_FSM.v
`include "cnt_FSM.v"

`timescale 1ns / 1ns

module tb_cnt_2_10_FSM();

reg iclk, irstn;
wire [7:0] oQ;

cnt_FSM DUT(.clk(iclk), .rst_n(irstn), .Q(oQ));

initial
begin
	iclk = 1'b0;
	irstn = 1'b1;
end

always #10 iclk = ~iclk;

initial
begin
	irstn = #20 ~irstn;
	irstn = #20 ~irstn;
end

initial
begin
	$dumpvars;
	#300 $finish;
end

endmodule

MPEI_Bachelor/projects/Лр4/КМ4/cnt_position/dump.vcd
$date
	Fri Dec 09 23:56:29 2022
$end
$version
	Icarus Verilog
$end
$timescale
	1ns
$end
$scope module tb_cnt_2_10_FSM $end
$var wire 8 ! oQ [7:0] $end
$var reg 1 " iclk $end
$var reg 1 # irstn $end
$scope module DUT $end
$var wire 1 " clk $end
$var wire 1 # rst_n $end
$var wire 8 $ Q [7:0] $end
$var parameter 8 % COUNT0 $end
$var parameter 8 & COUNT1 $end
$var parameter 8 ' COUNT2 $end
$var parameter 8 ( COUNT3 $end
$var parameter 8 ) COUNT4 $end
$var parameter 8 * COUNT5 $end
$var parameter 8 + COUNT6 $end
$var parameter 8 , COUNT7 $end
$var parameter 32 - RESET $end
$var reg 8 . nextstate [7:0] $end
$var reg 8 / state [7:0] $end
$upscope $end
$upscope $end
$enddefinitions $end
$comment Show the parameter values. $end
$dumpall
b0 -
b10000000 ,
b1000000 +
b100000 *
b10000 )
b1000 (
b100 '
b10 &
b1 %
$end
#0
$dumpvars
bx /
bx .
bx $
1#
0"
bx !
$end
#10
1"
#20
b1 .
b0 !
b0 $
b0 /
0"
0#
#30
1"
#40
0"
1#
#50
b10 .
b1 !
b1 $
b1 /
1"
#60
0"
#70
b10 !
b10 $
b100 .
b10 /
1"
#80
0"
#90
b100 !
b100 $
b1000 .
b100 /
1"
#100
0"
#110
b1000 !
b1000 $
b10000 .
b1000 /
1"
#120
0"
#130
b10000 !
b10000 $
b100000 .
b10000 /
1"
#140
0"
#150
b100000 !
b100000 $
b1000000 .
b100000 /
1"
#160
0"
#170
b1000000 !
b1000000 $
b10000000 .
b1000000 /
1"
#180
0"
#190
b10000000 !
b10000000 $
b1 .
b10000000 /
1"
#200
0"
#210
b1 !
b1 $
b10 .
b1 /
1"
#220
0"
#230
b10 !
b10 $
b100 .
b10 /
1"
#240
0"
#250
b100 !
b100 $
b1000 .
b100 /
1"
#260
0"
#270
b1000 !
b1000 $
b10000 .
b1000 /
1"
#280
0"
#290
b10000 !
b10000 $
b100000 .
b10000 /
1"
