MPEI_Bachelor/projects/Лр4/КМ4/Snail_FSM_110/SnailFSM_Mealey_110.v
module SnailFSM_Mealey_110(D, _rst, clk, Q);

localparam SAD = 0, WAIT1 = 1, WAIT2 = 2;

input D;
input _rst, clk;

output reg Q;

reg [1:0] state, nextstate;

reg Q_nonsynch;

reg [63:0] txstate;

always @( state )
  case ( state )
	 SAD    : txstate = "SAD";
	 WAIT1  : txstate = "WAIT1";
   WAIT2  : txstate = "WAIT2";
  endcase

always @(posedge clk, negedge _rst) begin
  if ( !_rst )
    state <= SAD;
  else
    state <= nextstate;
end

always @(*) begin
  case ( state )
    SAD   : nextstate = ((  D ) ? WAIT1 :   SAD );
	  WAIT1 : nextstate = ((  D ) ? WAIT2 :   SAD ); 
    WAIT2 : nextstate = (( !D ) ? SAD   : WAIT1 );   
    default : nextstate = SAD;
  endcase
end


always @(*) begin
  case ( state )
    SAD       : Q_nonsynch = 0;
    WAIT1     : Q_nonsynch = 0;
    WAIT2     : Q_nonsynch = (!D) ? 1'b1 : 1'b0;
    default   : Q_nonsynch = 0;
  endcase
end

always @(posedge clk or negedge _rst)
  if (!_rst)
    Q <= 0;
  else
    Q <= Q_nonsynch;

//assign Q = (D == 1'b1 && state == WAIT1);
endmodule

MPEI_Bachelor/projects/Лр4/КМ4/Snail_FSM_110/tb_SnailFSM_110.v
`include "SnailFSM_Mealey_110.v"
`timescale 1ns / 1ns

module tb_SnailFSM_110;

reg D, _rst, clk;
wire Q;

wire [63:0] state = DUT.txstate;

SnailFSM_Mealey_110 DUT (D, _rst, clk, Q);

initial begin
  clk = 0;
  forever #5 clk = ~clk;
end

initial begin
  _rst = 1;
  repeat(2) #1 _rst = ~_rst;
end

initial begin
  D = 0;
end

always @(posedge clk) #3 D = $random;

initial
  #500 $finish;

initial begin            
    $dumpfile("qqq.vcd");
    $dumpvars;
end

endmodule

MPEI_Bachelor/projects/Лр4/КМ4/Snail_FSM_110/qqq.vcd
$date
	Sat Dec 10 01:22:36 2022
$end
$version
	Icarus Verilog
$end
$timescale
	1ns
$end
$scope module tb_SnailFSM_110 $end
$var wire 64 ! state [63:0] $end
$var wire 1 " Q $end
$var reg 1 # D $end
$var reg 1 $ _rst $end
$var reg 1 % clk $end
$scope module DUT $end
$var wire 1 # D $end
$var wire 1 $ _rst $end
$var wire 1 % clk $end
$var parameter 32 & SAD $end
$var parameter 32 ' WAIT1 $end
$var parameter 32 ( WAIT2 $end
$var reg 1 " Q $end
$var reg 1 ) Q_nonsynch $end
$var reg 2 * nextstate [1:0] $end
$var reg 2 + state [1:0] $end
$var reg 64 , txstate [63:0] $end
$upscope $end
$upscope $end
$enddefinitions $end
$comment Show the parameter values. $end
$dumpall
b10 (
b1 '
b0 &
$end
#0
$dumpvars
bx ,
bx +
b0 *
0)
0%
1$
0#
x"
bx !
$end
#1
b10100110100000101000100 !
b10100110100000101000100 ,
b0 +
0"
0$
#2
1$
#5
1%
#10
0%
#15
1%
#18
b1 *
1#
#20
0%
#25
b10 *
b101011101000001010010010101010000110001 !
b101011101000001010010010101010000110001 ,
b1 +
1%
#30
0%
#35
b1 *
b101011101000001010010010101010000110010 !
b101011101000001010010010101010000110010 ,
b10 +
1%
#40
0%
#45
b10 *
b101011101000001010010010101010000110001 !
b101011101000001010010010101010000110001 ,
b1 +
1%
#50
0%
#55
b1 *
b101011101000001010010010101010000110010 !
b101011101000001010010010101010000110010 ,
b10 +
1%
#60
0%
#65
b10 *
b101011101000001010010010101010000110001 !
b101011101000001010010010101010000110001 ,
b1 +
1%
#70
0%
#75
b1 *
b101011101000001010010010101010000110010 !
b101011101000001010010010101010000110010 ,
b10 +
1%
#78
b0 *
1)
0#
#80
0%
#85
0)
b10100110100000101000100 !
b10100110100000101000100 ,
1"
b0 +
1%
#88
b1 *
1#
#90
0%
#95
b10 *
b101011101000001010010010101010000110001 !
b101011101000001010010010101010000110001 ,
b1 +
0"
1%
#100
0%
#105
b1 *
b101011101000001010010010101010000110010 !
b101011101000001010010010101010000110010 ,
b10 +
1%
#108
1)
b0 *
0#
#110
0%
#115
0)
b10100110100000101000100 !
b10100110100000101000100 ,
b0 +
1"
1%
#118
b1 *
1#
#120
0%
#125
b10 *
b101011101000001010010010101010000110001 !
b101011101000001010010010101010000110001 ,
0"
b1 +
1%
#130
0%
#135
b1 *
b101011101000001010010010101010000110010 !
b101011101000001010010010101010000110010 ,
b10 +
1%
#138
b0 *
1)
0#
#140
0%
#145
0)
b10100110100000101000100 !
b10100110100000101000100 ,
1"
b0 +
1%
#148
b1 *
1#
#150
0%
#155
b10 *
b101011101000001010010010101010000110001 !
b101011101000001010010010101010000110001 ,
b1 +
0"
1%
#158
b0 *
0#
#160
0%
#165
b10100110100000101000100 !
b10100110100000101000100 ,
b0 +
1%
#168
b1 *
1#
#170
0%
#175
b10 *
b101011101000001010010010101010000110001 !
b101011101000001010010010101010000110001 ,
b1 +
1%
#178
b0 *
0#
#180
0%
#185
b10100110100000101000100 !
b10100110100000101000100 ,
b0 +
1%
#188
b1 *
1#
#190
0%
#195
b10 *
b101011101000001010010010101010000110001 !
b101011101000001010010010101010000110001 ,
b1 +
1%
#200
0%
#205
b1 *
b101011101000001010010010101010000110010 !
b101011101000001010010010101010000110010 ,
b10 +
1%
#208
1)
b0 *
0#
#210
0%
#215
0)
b10100110100000101000100 !
b10100110100000101000100 ,
b0 +
1"
1%
#218
b1 *
1#
#220
0%
#225
b10 *
b101011101000001010010010101010000110001 !
b101011101000001010010010101010000110001 ,
0"
b1 +
1%
#228
b0 *
0#
#230
0%
#235
b10100110100000101000100 !
b10100110100000101000100 ,
b0 +
1%
#240
0%
#245
1%
#250
0%
#255
1%
#258
b1 *
1#
#260
0%
#265
b10 *
b101011101000001010010010101010000110001 !
b101011101000001010010010101010000110001 ,
b1 +
1%
#268
b0 *
0#
#270
0%
#275
b10100110100000101000100 !
b10100110100000101000100 ,
b0 +
1%
#278
b1 *
1#
#280
0%
#285
b10 *
b101011101000001010010010101010000110001 !
b101011101000001010010010101010000110001 ,
b1 +
1%
#290
0%
#295
b1 *
b101011101000001010010010101010000110010 !
b101011101000001010010010101010000110010 ,
b10 +
1%
#300
0%
#305
b10 *
b101011101000001010010010101010000110001 !
b101011101000001010010010101010000110001 ,
b1 +
1%
#310
0%
#315
b1 *
b101011101000001010010010101010000110010 !
b101011101000001010010010101010000110010 ,
b10 +
1%
#318
b0 *
1)
0#
#320
0%
#325
0)
b10100110100000101000100 !
b10100110100000101000100 ,
1"
b0 +
1%
#330
0%
#335
0"
1%
#340
0%
#345
1%
#350
0%
#355
1%
#358
b1 *
1#
#360
0%
#365
b10 *
b101011101000001010010010101010000110001 !
b101011101000001010010010101010000110001 ,
b1 +
1%
#368
b0 *
0#
#370
0%
#375
b10100110100000101000100 !
b10100110100000101000100 ,
b0 +
1%
#378
b1 *
1#
#380
0%
#385
b10 *
b101011101000001010010010101010000110001 !
b101011101000001010010010101010000110001 ,
b1 +
1%
#390
0%
#395
b1 *
b101011101000001010010010101010000110010 !
b101011101000001010010010101010000110010 ,
b10 +
1%
#400
0%
#405
b10 *
b101011101000001010010010101010000110001 !
b101011101000001010010010101010000110001 ,
b1 +
1%
#410
0%
#415
b1 *
b101011101000001010010010101010000110010 !
b101011101000001010010010101010000110010 ,
b10 +
1%
#420
0%
#425
b10 *
b101011101000001010010010101010000110001 !
b101011101000001010010010101010000110001 ,
b1 +
1%
#428
b0 *
0#
#430
0%
#435
b10100110100000101000100 !
b10100110100000101000100 ,
b0 +
1%
#440
0%
#445
1%
#448
b1 *
1#
#450
0%
#455
b10 *
b101011101000001010010010101010000110001 !
b101011101000001010010010101010000110001 ,
b1 +
1%
#460
0%
#465
b1 *
b101011101000001010010010101010000110010 !
b101011101000001010010010101010000110010 ,
b10 +
1%
#470
0%
#475
b10 *
b101011101000001010010010101010000110001 !
b101011101000001010010010101010000110001 ,
b1 +
1%
#478
b0 *
0#
#480
0%
#485
b10100110100000101000100 !
b10100110100000101000100 ,
b0 +
1%
