MPEI_Bachelor/bachelor's work/ALU_divider/proverka.v/div_new.v
module div_new(A, B, quotient, reminder, clk, res, load, error);

input       wire                         clk;
input       wire                         res;
input       wire                        load;
input       wire    [ 4 :  0 ]             A;
input       wire    [ 4 :  0 ]             B;
output      reg     [ 4 :  0 ]      quotient;
output      reg     [ 4 :  0 ]      reminder;
output      reg                        error;

reg     signed      [ 9 :  0 ] divisible_copy;
reg     signed      [ 9 :  0 ]  divider_copy;

reg                 [ 4 :  0 ]     divisible;
reg                 [ 4 :  0 ]       divider;
reg                 [ 3 :  0 ]           cnt;

wire    signed      [ 9 :  0 ] w_diff = divisible_copy - divider_copy;
wire ready;

assign ready = cnt == 0;

always @(posedge clk, negedge res) begin
    if(!res) begin
        divisible_copy <= 0;
        divider_copy  <= 0;
        error         <= 0;
        cnt           <= 0; 
        quotient      <= 0;
        reminder      <= 0; 
        divisible     <= 0;
        divider       <= 0;end
    else begin
    if(load) begin
        if ((A !=0) && (B !=0)) begin
            if(A > B) begin
                divisible   <= A;
                divider     <= B; 
                error       <= 1'b0; end
            else if (A < B) begin
                divisible   <= B;
                divider     <= A; 
                error       <= 1'b0; end end
        else begin 
                quotient    <= 5'b0;
                reminder    <= 5'b0;
                error       <= 1'b1; end end
    else if(ready) begin
        cnt <= 4'd5;
        quotient <= {5{1'b0}};
        divisible_copy <= {{5{1'b0}}, divisible};
        divider_copy <= {1'b0, divider, {4{1'b0}}}; 
        reminder = divisible_copy[4:0];  end
    else begin
        cnt <= cnt - 1'b1;
        divider_copy <= divider_copy >> 1;
        if(!w_diff[9]) begin
            divisible_copy <= w_diff;
            quotient <= {quotient[3:0], 1'b1}; end
        else begin
            quotient <= {quotient[3:0], 1'b0};end end
    end end 
endmodule

MPEI_Bachelor/bachelor's work/ALU_divider/proverka.v/tb_top.v
`include "div_new.v"
`timescale 1ns / 1ns  

module tb_div;
 reg  clk, res;
 reg  [4:0] A, B;
 reg      load;

 wire [4:0]quotient;
 wire [4:0]reminder;
 wire         error;
 

div_new DUT (.clk(clk), .res(res), .A(A), .B(B), .quotient(quotient), .reminder(reminder), .load(load), .error(error));

 initial                           
 begin                                                    
  clk = 0;
  res = 1;   
          
  $display("Running testbench"); 
 end

always                            
  #5	   
  clk = !clk;   
 
 initial begin
repeat (2) #2 res = ~res;
end
initial                           
begin       
     load = 1'b1;
     A = 5'b11101;
     B = 5'b01110;
     #50 load = ~ load;

     #50load = 1'b1;
     A = 5'b01010;
     B = 5'b11010;
     #50 load = ~ load;

     #50load = 1'b1;
     A = 5'b00000;
     B = 5'b11010;
     #50 load = ~ load;

     #50load = 1'b1;
     A = 5'b10101;
     B = 5'b00000;
     #50 load = ~ load;   

     #50load = 1'b1;
     A = 5'b10101;
     B = 5'b01101;
     #50 load = ~ load;     

     #50load = 1'b1;
     A = 5'b00000;
     B = 5'b00000;
     #50 load = ~ load;

     #50load = 1'b1;
     A = 5'b11101;
     B = 5'b00011;
     #50 load = ~ load;                             
end      

initial begin                      
	$monitor ("At time %t 'A'=%b and 'B'=%b and 'res'=%d  and 'out'=%b", $time, A, B, res, quotient);
#1000 $display("Testbench is OK!");
       $finish;         
end

initial begin                                      
     $dumpfile("qqq.vcd");
     $dumpvars;
end

endmodule

MPEI_Bachelor/bachelor's work/ALU_divider/proverka.v/qqq.vcd
$date
	Thu Jun 29 01:26:30 2023
$end
$version
	Icarus Verilog
$end
$timescale
	1ns
$end
$scope module tb_div $end
$var wire 5 ! reminder [4:0] $end
$var wire 5 " quotient [4:0] $end
$var wire 1 # error $end
$var reg 5 $ A [4:0] $end
$var reg 5 % B [4:0] $end
$var reg 1 & clk $end
$var reg 1 ' load $end
$var reg 1 ( res $end
$scope module DUT $end
$var wire 5 ) A [4:0] $end
$var wire 5 * B [4:0] $end
$var wire 1 & clk $end
$var wire 1 ' load $end
$var wire 1 ( res $end
$var wire 10 + w_diff [9:0] $end
$var wire 1 , ready $end
$var reg 4 - cnt [3:0] $end
$var reg 5 . divider [4:0] $end
$var reg 10 / divider_copy [9:0] $end
$var reg 5 0 divisible [4:0] $end
$var reg 10 1 divisible_copy [9:0] $end
$var reg 1 # error $end
$var reg 5 2 quotient [4:0] $end
$var reg 5 3 reminder [4:0] $end
$upscope $end
$upscope $end
$enddefinitions $end
$comment Show the parameter values. $end
$dumpall
$end
#0
$dumpvars
bx 3
bx 2
bx 1
bx 0
bx /
bx .
bx -
x,
bx +
b1110 *
b11101 )
1(
1'
0&
b1110 %
b11101 $
x#
bx "
bx !
$end
#2
b0 .
b0 0
b0 !
b0 3
b0 "
b0 2
1,
b0 -
0#
b0 +
b0 /
b0 1
0(
#4
1(
#5
b1110 .
b11101 0
1&
#10
0&
#15
1&
#20
0&
#25
1&
#30
0&
#35
1&
#40
0&
#45
1&
#50
0&
0'
#55
b11100000 /
b1100111101 +
b11101 1
0,
b101 -
1&
#60
0&
#65
b1110101101 +
b1110000 /
b100 -
1&
#70
0&
#75
b1111100101 +
b111000 /
b11 -
1&
#80
0&
#85
b1 +
b11100 /
b10 -
1&
#90
0&
#95
b1 "
b1 2
b1 1
b1111110011 +
b1110 /
b1 -
1&
#100
0&
b11010 %
b11010 *
b1010 $
b1010 )
1'
#105
b1010 .
b11010 0
1&
#110
0&
#115
1&
#120
0&
#125
1&
#130
0&
#135
1&
#140
0&
#145
1&
#150
0&
0'
#155
b10 "
b10 2
b1111111010 +
b111 /
1,
b0 -
1&
#160
0&
#165
b10100000 /
b1101111010 +
b11010 1
b0 "
b0 2
0,
b101 -
b1 !
b1 3
1&
#170
0&
#175
b1111001010 +
b1010000 /
b100 -
1&
#180
0&
#185
b1111110010 +
b101000 /
b11 -
1&
#190
0&
#195
b110 +
b10100 /
b10 -
1&
#200
0&
b0 $
b0 )
1'
#205
1#
b0 !
b0 3
1&
#210
0&
#215
1&
#220
0&
#225
1&
#230
0&
#235
1&
#240
0&
#245
1&
#250
0&
0'
#255
b1 "
b1 2
b110 1
b1111111100 +
b1010 /
b1 -
1&
#260
0&
#265
b10 "
b10 2
b1 +
b101 /
1,
b0 -
1&
#270
0&
#275
b10100000 /
b1101111010 +
b11010 1
b0 "
b0 2
0,
b101 -
b110 !
b110 3
1&
#280
0&
#285
b1111001010 +
b1010000 /
b100 -
1&
#290
0&
#295
b1111110010 +
b101000 /
b11 -
1&
#300
0&
b0 %
b0 *
b10101 $
b10101 )
1'
#305
b0 !
b0 3
1&
#310
0&
#315
1&
#320
0&
#325
1&
#330
0&
#335
1&
#340
0&
#345
1&
#350
0&
0'
#355
b110 +
b10100 /
b10 -
1&
#360
0&
#365
b1 "
b1 2
b110 1
b1111111100 +
b1010 /
b1 -
1&
#370
0&
#375
b10 "
b10 2
b1 +
b101 /
1,
b0 -
1&
#380
0&
#385
b10100000 /
b1101111010 +
b11010 1
b0 "
b0 2
0,
b101 -
b110 !
b110 3
1&
#390
0&
#395
b1111001010 +
b1010000 /
b100 -
1&
#400
0&
b1101 %
b1101 *
1'
#405
0#
b1101 .
b10101 0
1&
#410
0&
#415
1&
#420
0&
#425
1&
#430
0&
#435
1&
#440
0&
#445
1&
#450
0&
0'
#455
b1111110010 +
b101000 /
b11 -
1&
#460
0&
#465
b110 +
b10100 /
b10 -
1&
#470
0&
#475
b1 "
b1 2
b110 1
b1111111100 +
b1010 /
b1 -
1&
#480
0&
#485
b10 "
b10 2
b1 +
b101 /
1,
b0 -
1&
#490
0&
#495
b11010000 /
b1101000101 +
b10101 1
b0 "
b0 2
0,
b101 -
1&
#500
0&
b0 %
b0 *
b0 $
b0 )
1'
#505
1#
b0 !
b0 3
1&
#510
0&
#515
1&
#520
0&
#525
1&
#530
0&
#535
1&
#540
0&
#545
1&
#550
0&
0'
#555
b1110101101 +
b1101000 /
b100 -
1&
#560
0&
#565
b1111100001 +
b110100 /
b11 -
1&
#570
0&
#575
b1111111011 +
b11010 /
b10 -
1&
#580
0&
#585
b1000 +
b1101 /
b1 -
1&
#590
0&
#595
b1 "
b1 2
b1000 1
b10 +
b110 /
1,
b0 -
1&
#600
0&
b11 %
b11 *
b11101 $
b11101 )
1'
#605
0#
b11 .
b11101 0
1&
#610
0&
#615
1&
#620
0&
#625
1&
#630
0&
#635
1&
#640
0&
#645
1&
#650
0&
0'
#655
b110000 /
b1111101101 +
b11101 1
b0 "
b0 2
0,
b101 -
b1000 !
b1000 3
1&
#660
0&
#665
b101 +
b11000 /
b100 -
1&
#670
0&
#675
b1 "
b1 2
b101 1
b1111111001 +
b1100 /
b11 -
1&
#680
0&
#685
b10 "
b10 2
b1111111111 +
b110 /
b10 -
1&
#690
0&
#695
b100 "
b100 2
b10 +
b11 /
b1 -
1&
#700
0&
#705
b1001 "
b1001 2
b10 1
b1 +
b1 /
1,
b0 -
1&
#710
0&
#715
b110000 /
b1111101101 +
b11101 1
b0 "
b0 2
0,
b101 -
b10 !
b10 3
1&
#720
0&
#725
b101 +
b11000 /
b100 -
1&
#730
0&
#735
b1 "
b1 2
b101 1
b1111111001 +
b1100 /
b11 -
1&
#740
0&
#745
b10 "
b10 2
b1111111111 +
b110 /
b10 -
1&
#750
0&
#755
b100 "
b100 2
b10 +
b11 /
b1 -
1&
#760
0&
#765
b1001 "
b1001 2
b10 1
b1 +
b1 /
1,
b0 -
1&
#770
0&
#775
b110000 /
b1111101101 +
b11101 1
b0 "
b0 2
0,
b101 -
1&
#780
0&
#785
b101 +
b11000 /
b100 -
1&
#790
0&
#795
b1 "
b1 2
b101 1
b1111111001 +
b1100 /
b11 -
1&
#800
0&
#805
b10 "
b10 2
b1111111111 +
b110 /
b10 -
1&
#810
0&
#815
b100 "
b100 2
b10 +
b11 /
b1 -
1&
#820
0&
#825
b1001 "
b1001 2
b10 1
b1 +
b1 /
1,
b0 -
1&
#830
0&
#835
b110000 /
b1111101101 +
b11101 1
b0 "
b0 2
0,
b101 -
1&
#840
0&
#845
b101 +
b11000 /
b100 -
1&
#850
0&
#855
b1 "
b1 2
b101 1
b1111111001 +
b1100 /
b11 -
1&
#860
0&
#865
b10 "
b10 2
b1111111111 +
b110 /
b10 -
1&
#870
0&
#875
b100 "
b100 2
b10 +
b11 /
b1 -
1&
#880
0&
#885
b1001 "
b1001 2
b10 1
b1 +
b1 /
1,
b0 -
1&
#890
0&
#895
b110000 /
b1111101101 +
b11101 1
b0 "
b0 2
0,
b101 -
1&
#900
0&
#905
b101 +
b11000 /
b100 -
1&
#910
0&
#915
b1 "
b1 2
b101 1
b1111111001 +
b1100 /
b11 -
1&
#920
0&
#925
b10 "
b10 2
b1111111111 +
b110 /
b10 -
1&
#930
0&
#935
b100 "
b100 2
b10 +
b11 /
b1 -
1&
#940
0&
#945
b1001 "
b1001 2
b10 1
b1 +
b1 /
1,
b0 -
1&
#950
0&
#955
b110000 /
b1111101101 +
b11101 1
b0 "
b0 2
0,
b101 -
1&
#960
0&
#965
b101 +
b11000 /
b100 -
1&
#970
0&
#975
b1 "
b1 2
b101 1
b1111111001 +
b1100 /
b11 -
1&
#980
0&
#985
b10 "
b10 2
b1111111111 +
b110 /
b10 -
1&
#990
0&
#995
b100 "
b100 2
b10 +
b11 /
b1 -
1&
