MPEI_Bachelor/projects/Лр4/КМ4/FSM_traffic_light_btn_red/src/timer.v
module timer #(parameter bit = 5) //чтобы быстро менять входную частоту 
				(clk_50MHz, res,clk_1Hz);

input   clk_50MHz, res;

output  reg clk_1Hz; //делим частоту 

reg [bit:0] cnt; 

always @(posedge clk_50MHz, negedge res) //Блок для получения 1 секунды
if (!res) 
begin
		cnt <= 0;
		clk_1Hz <= 0;
end

else if (cnt == 25)
begin
		cnt <= 0;
		clk_1Hz <= ~clk_1Hz;
end

else 
		cnt = cnt + 1'b1; 

endmodule

MPEI_Bachelor/projects/Лр4/КМ4/FSM_traffic_light_btn_red_and_2yellow/src/traffic_light.v
`include "timer.v"
module traffic_light(clk, res, out_state, btn);

input clk, res, btn;

output [1:0] out_state;

localparam RED = 0, YELLOW1 = 1, GREEN = 2, YELLOW2 = 3;

reg [1:0] state, next_state;
reg [63:0] txstate;

always @(state)
	case (state)
		RED     : txstate = "RED";
		YELLOW1 : txstate = "YELLOW";
		GREEN   : txstate = "GREEN";
		YELLOW2 : txstate = "YELLOW2";
	endcase

reg [5:0] cnt;

wire proverka = (state == RED && cnt == 40) || ((state == YELLOW1 || state == YELLOW2) && cnt == 3) || ((state == GREEN) && cnt == 21);

wire clk_1Hz;

timer one_second(.clk_50MHz(clk), .res(res), .clk_1Hz(clk_1Hz)); //Подключаем таймер 

always @(posedge clk_1Hz, negedge res)
begin
if (!res)
 	cnt <= 0;
else if (proverka)
   cnt <= 0;
else 
	cnt <= cnt + 1;
	
end

always @(*)
	case(state)
		RED     : 
				if(cnt == 40)
					next_state = YELLOW1;
				else if (cnt1 == 3)
					next_state = GREEN;
				else 
					next_state = RED;
		YELLOW1 : next_state = (cnt == 3) ? GREEN : YELLOW1;
		GREEN   : next_state = (cnt ==21) ? YELLOW2 : GREEN;
		YELLOW2 : next_state = (cnt ==3) ? RED : YELLOW2;
	endcase

//Логика переключения из красного в зеленый по нажатию кнопки
reg [1:0] cnt1;
always @(posedge btn, posedge clk_1Hz)
    if (btnD)
        cnt1 <= cnt1 + 1;
	else if (cnt == 37)
		cnt1 <= 0;
	else 
		cnt1 <= 0;

always @(posedge clk_1Hz, negedge res)
begin
if (!res)
 	state <= RED;
else
	state <= next_state;
end

assign out_state = state;

endmodule

MPEI_Bachelor/projects/Лр4/КМ4/FSM_traffic_light_btn_red_and_2yellow/src/traffic_light_top.v
`include "traffic_light.v"
module traffic_light_top(clk,led0, led1, led2, btn_res, btn);

input clk, btn_res, btn;

output led0, led1, led2;
	 
localparam RED = 0, YELLOW1 = 1, GREEN = 2, YELLOW2 = 3;

wire [1:0] state;

traffic_light DUT1(.clk(clk), .out_state(state), .res(btn_res), .btn(btn));

// Логика для светодиодов
assign led0 = state == RED ? 1 : 0;

assign led1 = (state == YELLOW1) | (state == YELLOW2) ? 1 : 0;

assign led2 = state == GREEN ? 1 : 0;

endmodule

MPEI_Bachelor/projects/Лр4/КМ4/FSM_traffic_light_btn_red_and_2yellow/src/tb_traffic_light_top.v
`include "traffic_light_top.v"
`timescale 1ns / 1ns

module tb_traffic_light_top;

reg clk, res, btn;

wire led0, led1, led2;

traffic_light_top DUT (.clk(clk), .btn_res(res), .btn(btn), .led0(led0), .led1(led1), .led2(led2));

initial begin                                                  
  clk = 0;
  $display("Running testbench");
end         
      
initial begin
res = 1;
btn = 0;
repeat (2) #1 res = ~res;
end	  

initial  begin #3000 btn = 1;
               #3010 btn = 0; end
always 
  #1	  clk =  ! clk;                                                 

initial begin
	#30000 $display("Testbench is OK!");
         $finish;
end

//Для симуляция в Iverilog		 
initial begin            
    $dumpfile("qqq.vcd");
    $dumpvars;
end

endmodule

MPEI_Bachelor/projects/Лр4/КМ4/FSM_traffic_light_btn_red_and_2yellow/src/qqq.vcd
$date
	Sun Dec 11 22:05:03 2022
$end
$version
	Icarus Verilog
$end
$timescale
	1ns
$end
$scope module tb_traffic_light_top $end
$var wire 1 ! led2 $end
$var wire 1 " led1 $end
$var wire 1 # led0 $end
$var reg 1 $ btn $end
$var reg 1 % clk $end
$var reg 1 & res $end
$scope module DUT $end
$var wire 1 $ btn $end
$var wire 1 & btn_res $end
$var wire 1 % clk $end
$var wire 2 ' state [1:0] $end
$var wire 1 ! led2 $end
$var wire 1 " led1 $end
$var wire 1 # led0 $end
$var parameter 32 ( GREEN $end
$var parameter 32 ) RED $end
$var parameter 32 * YELLOW1 $end
$var parameter 32 + YELLOW2 $end
$scope module DUT1 $end
$var wire 1 $ btn $end
$var wire 1 % clk $end
$var wire 2 , out_state [1:0] $end
$var wire 1 - proverka $end
$var wire 1 & res $end
$var wire 1 . clk_1Hz $end
$var parameter 32 / GREEN $end
$var parameter 32 0 RED $end
$var parameter 32 1 YELLOW1 $end
$var parameter 32 2 YELLOW2 $end
$var reg 6 3 cnt [5:0] $end
$var reg 2 4 cnt1 [1:0] $end
$var reg 2 5 next_state [1:0] $end
$var reg 2 6 state [1:0] $end
$var reg 64 7 txstate [63:0] $end
$scope module one_second $end
$var wire 1 % clk_50MHz $end
$var wire 1 & res $end
$var parameter 32 8 bit $end
$var reg 1 . clk_1Hz $end
$var reg 6 9 cnt [5:0] $end
$upscope $end
$upscope $end
$upscope $end
$upscope $end
$enddefinitions $end
$comment Show the parameter values. $end
$dumpall
b101 8
b11 2
b1 1
b0 0
b10 /
b11 +
b1 *
b0 )
b10 (
$end
#0
$dumpvars
bx 9
bx 7
bx 6
bx 5
bx 4
bx 3
x.
x-
bx ,
bx '
1&
0%
0$
x#
x"
x!
$end
#1
0-
0"
0!
1#
b0 5
b10100100100010101000100 7
0.
b0 9
b0 3
b0 '
b0 ,
b0 6
1%
0&
#2
0%
1&
#3
b1 9
1%
#4
0%
#5
b10 9
1%
#6
0%
#7
b11 9
1%
#8
0%
#9
b100 9
1%
#10
0%
#11
b101 9
1%
#12
0%
#13
b110 9
1%
#14
0%
#15
b111 9
1%
#16
0%
#17
b1000 9
1%
#18
0%
#19
b1001 9
1%
#20
0%
#21
b1010 9
1%
#22
0%
#23
b1011 9
1%
#24
0%
#25
b1100 9
1%
#26
0%
#27
b1101 9
1%
#28
0%
#29
b1110 9
1%
#30
0%
#31
b1111 9
1%
#32
0%
#33
b10000 9
1%
#34
0%
#35
b10001 9
1%
#36
0%
#37
b10010 9
1%
#38
0%
#39
b10011 9
1%
#40
0%
#41
b10100 9
1%
#42
0%
#43
b10101 9
1%
#44
0%
#45
b10110 9
1%
#46
0%
#47
b10111 9
1%
#48
0%
#49
b11000 9
1%
#50
0%
#51
b11001 9
1%
#52
0%
#53
b0 4
b1 3
1.
b0 9
1%
#54
0%
#55
b1 9
1%
#56
0%
#57
b10 9
1%
#58
0%
#59
b11 9
1%
#60
0%
#61
b100 9
1%
#62
0%
#63
b101 9
1%
#64
0%
#65
b110 9
1%
#66
0%
#67
b111 9
1%
#68
0%
#69
b1000 9
1%
#70
0%
#71
b1001 9
1%
#72
0%
#73
b1010 9
1%
#74
0%
#75
b1011 9
1%
#76
0%
#77
b1100 9
1%
#78
0%
#79
b1101 9
1%
#80
0%
#81
b1110 9
1%
#82
0%
#83
b1111 9
1%
#84
0%
#85
b10000 9
1%
#86
0%
#87
b10001 9
1%
#88
0%
#89
b10010 9
1%
#90
0%
#91
b10011 9
1%
#92
0%
#93
b10100 9
1%
#94
0%
#95
b10101 9
1%
#96
0%
#97
b10110 9
1%
#98
0%
#99
b10111 9
1%
#100
0%
#101
b11000 9
1%
#102
0%
#103
b11001 9
1%
#104
0%
#105
0.
b0 9
1%
#106
0%
#107
b1 9
1%
#108
0%
#109
b10 9
1%
#110
0%
#111
b11 9
1%
#112
0%
#113
b100 9
1%
#114
0%
#115
b101 9
1%
#116
0%
#117
b110 9
1%
#118
0%
#119
b111 9
1%
#120
0%
#121
b1000 9
1%
#122
0%
#123
b1001 9
1%
#124
0%
#125
b1010 9
1%
#126
0%
#127
b1011 9
1%
#128
0%
#129
b1100 9
1%
#130
0%
#131
b1101 9
1%
#132
0%
#133
b1110 9
1%
#134
0%
#135
b1111 9
1%
#136
0%
#137
b10000 9
1%
#138
0%
#139
b10001 9
1%
#140
0%
#141
b10010 9
1%
#142
0%
#143
b10011 9
1%
#144
0%
#145
b10100 9
1%
#146
0%
#147
b10101 9
1%
#148
0%
#149
b10110 9
1%
#150
0%
#151
b10111 9
1%
#152
0%
#153
b11000 9
1%
#154
0%
#155
b11001 9
1%
#156
0%
#157
b10 3
1.
b0 9
1%
#158
0%
#159
b1 9
1%
#160
0%
#161
b10 9
1%
#162
0%
#163
b11 9
1%
#164
0%
#165
b100 9
1%
#166
0%
#167
b101 9
1%
#168
0%
#169
b110 9
1%
#170
0%
#171
b111 9
1%
#172
0%
#173
b1000 9
1%
#174
0%
#175
b1001 9
1%
#176
0%
#177
b1010 9
1%
#178
0%
#179
b1011 9
1%
#180
0%
#181
b1100 9
1%
#182
0%
#183
b1101 9
1%
#184
0%
#185
b1110 9
1%
#186
0%
#187
b1111 9
1%
#188
0%
#189
b10000 9
1%
#190
0%
#191
b10001 9
1%
#192
0%
#193
b10010 9
1%
#194
0%
#195
b10011 9
1%
#196
0%
#197
b10100 9
1%
#198
0%
#199
b10101 9
1%
#200
0%
#201
b10110 9
1%
#202
0%
#203
b10111 9
1%
#204
0%
#205
b11000 9
1%
#206
0%
#207
b11001 9
1%
#208
0%
#209
0.
b0 9
1%
#210
0%
#211
b1 9
1%
#212
0%
#213
b10 9
1%
#214
0%
#215
b11 9
1%
#216
0%
#217
b100 9
1%
#218
0%
#219
b101 9
1%
#220
0%
#221
b110 9
1%
#222
0%
#223
b111 9
1%
#224
0%
#225
b1000 9
1%
#226
0%
#227
b1001 9
1%
#228
0%
#229
b1010 9
1%
#230
0%
#231
b1011 9
1%
#232
0%
#233
b1100 9
1%
#234
0%
#235
b1101 9
1%
#236
0%
#237
b1110 9
1%
#238
0%
#239
b1111 9
1%
#240
0%
#241
b10000 9
1%
#242
0%
#243
b10001 9
1%
#244
0%
#245
b10010 9
1%
#246
0%
#247
b10011 9
1%
#248
0%
#249
b10100 9
1%
#250
0%
#251
b10101 9
1%
#252
0%
#253
b10110 9
1%
#254
0%
#255
b10111 9
1%
#256
0%
#257
b11000 9
1%
#258
0%
#259
b11001 9
1%
#260
0%
#261
b11 3
1.
b0 9
1%
#262
0%
#263
b1 9
1%
#264
0%
#265
b10 9
1%
#266
0%
#267
b11 9
1%
#268
0%
#269
b100 9
1%
#270
0%
#271
b101 9
1%
#272
0%
#273
b110 9
1%
#274
0%
#275
b111 9
1%
#276
0%
#277
b1000 9
1%
#278
0%
#279
b1001 9
1%
#280
0%
#281
b1010 9
1%
#282
0%
#283
b1011 9
1%
#284
0%
#285
b1100 9
1%
#286
0%
#287
b1101 9
1%
#288
0%
#289
b1110 9
1%
#290
0%
#291
b1111 9
1%
#292
0%
#293
b10000 9
1%
#294
0%
#295
b10001 9
1%
#296
0%
#297
b10010 9
1%
#298
0%
#299
b10011 9
1%
#300
0%
#301
b10100 9
1%
#302
0%
#303
b10101 9
1%
#304
0%
#305
b10110 9
1%
#306
0%
#307
b10111 9
1%
#308
0%
#309
b11000 9
1%
#310
0%
#311
b11001 9
1%
#312
0%
#313
0.
b0 9
1%
#314
0%
#315
b1 9
1%
#316
0%
#317
b10 9
1%
#318
0%
#319
b11 9
1%
#320
0%
#321
b100 9
1%
#322
0%
#323
b101 9
1%
#324
0%
#325
b110 9
1%
#326
0%
#327
b111 9
1%
#328
0%
#329
b1000 9
1%
#330
0%
#331
b1001 9
1%
#332
0%
#333
b1010 9
1%
#334
0%
#335
b1011 9
1%
#336
0%
#337
b1100 9
1%
#338
0%
#339
b1101 9
1%
#340
0%
#341
b1110 9
1%
#342
0%
#343
b1111 9
1%
#344
0%
#345
b10000 9
1%
#346
0%
#347
b10001 9
1%
#348
0%
#349
b10010 9
1%
#350
0%
#351
b10011 9
1%
#352
0%
#353
b10100 9
1%
#354
0%
#355
b10101 9
1%
#356
0%
#357
b10110 9
1%
#358
0%
#359
b10111 9
1%
#360
0%
#361
b11000 9
1%
#362
0%
#363
b11001 9
1%
#364
0%
#365
b100 3
1.
b0 9
1%
#366
0%
#367
b1 9
1%
#368
0%
#369
b10 9
1%
#370
0%
#371
b11 9
1%
#372
0%
#373
b100 9
1%
#374
0%
#375
b101 9
1%
#376
0%
#377
b110 9
1%
#378
0%
#379
b111 9
1%
#380
0%
#381
b1000 9
1%
#382
0%
#383
b1001 9
1%
#384
0%
#385
b1010 9
1%
#386
0%
#387
b1011 9
1%
#388
0%
#389
b1100 9
1%
#390
0%
#391
b1101 9
1%
#392
0%
#393
b1110 9
1%
#394
0%
#395
b1111 9
1%
#396
0%
#397
b10000 9
1%
#398
0%
#399
b10001 9
1%
#400
0%
#401
b10010 9
1%
#402
0%
#403
b10011 9
1%
#404
0%
#405
b10100 9
1%
#406
0%
#407
b10101 9
1%
#408
0%
#409
b10110 9
1%
#410
0%
#411
b10111 9
1%
#412
0%
#413
b11000 9
1%
#414
0%
#415
b11001 9
1%
#416
0%
#417
0.
b0 9
1%
#418
0%
#419
b1 9
1%
#420
0%
#421
b10 9
1%
#422
0%
#423
b11 9
1%
#424
0%
#425
b100 9
1%
#426
0%
#427
b101 9
1%
#428
0%
#429
b110 9
1%
#430
0%
#431
b111 9
1%
#432
0%
#433
b1000 9
1%
#434
0%
#435
b1001 9
1%
#436
0%
#437
b1010 9
1%
#438
0%
#439
b1011 9
1%
#440
0%
#441
b1100 9
1%
#442
0%
#443
b1101 9
1%
#444
0%
#445
b1110 9
1%
#446
0%
#447
b1111 9
1%
#448
0%
#449
b10000 9
1%
#450
0%
#451
b10001 9
1%
#452
0%
#453
b10010 9
1%
#454
0%
#455
b10011 9
1%
#456
0%
#457
b10100 9
1%
#458
0%
#459
b10101 9
1%
#460
0%
#461
b10110 9
1%
#462
0%
#463
b10111 9
1%
#464
0%
#465
b11000 9
1%
#466
0%
#467
b11001 9
1%
#468
0%
#469
b101 3
1.
b0 9
1%
#470
0%
#471
b1 9
1%
#472
0%
#473
b10 9
1%
#474
0%
#475
b11 9
1%
#476
0%
#477
b100 9
1%
#478
0%
#479
b101 9
1%
#480
0%
#481
b110 9
1%
#482
0%
#483
b111 9
1%
#484
0%
#485
b1000 9
1%
#486
0%
#487
b1001 9
1%
#488
0%
#489
b1010 9
1%
#490
0%
#491
b1011 9
1%
#492
0%
#493
b1100 9
1%
#494
0%
#495
b1101 9
1%
#496
0%
#497
b1110 9
1%
#498
0%
#499
b1111 9
1%
#500
0%
#501
b10000 9
1%
#502
0%
#503
b10001 9
1%
#504
0%
#505
b10010 9
1%
#506
0%
#507
b10011 9
1%
#508
0%
#509
b10100 9
1%
#510
0%
#511
b10101 9
1%
#512
0%
#513
b10110 9
1%
#514
0%
#515
b10111 9
1%
#516
0%
#517
b11000 9
1%
#518
0%
#519
b11001 9
1%
#520
0%
#521
0.
b0 9
1%
#522
0%
#523
b1 9
1%
#524
0%
#525
b10 9
1%
#526
0%
#527
b11 9
1%
#528
0%
#529
b100 9
1%
#530
0%
#531
b101 9
1%
#532
0%
#533
b110 9
1%
#534
0%
#535
b111 9
1%
#536
0%
#537
b1000 9
1%
#538
0%
#539
b1001 9
1%
#540
0%
#541
b1010 9
1%
#542
0%
#543
b1011 9
1%
#544
0%
#545
b1100 9
1%
#546
0%
#547
b1101 9
1%
#548
0%
#549
b1110 9
1%
#550
0%
#551
b1111 9
1%
#552
0%
#553
b10000 9
1%
#554
0%
#555
b10001 9
1%
#556
0%
#557
b10010 9
1%
#558
0%
#559
b10011 9
1%
#560
0%
#561
b10100 9
1%
#562
0%
#563
b10101 9
1%
#564
0%
#565
b10110 9
1%
#566
0%
#567
b10111 9
1%
#568
0%
#569
b11000 9
1%
#570
0%
#571
b11001 9
1%
#572
0%
#573
b110 3
1.
b0 9
1%
#574
0%
#575
b1 9
1%
#576
0%
#577
b10 9
1%
#578
0%
#579
b11 9
1%
#580
0%
#581
b100 9
1%
#582
0%
#583
b101 9
1%
#584
0%
#585
b110 9
1%
#586
0%
#587
b111 9
1%
#588
0%
#589
b1000 9
1%
#590
0%
#591
b1001 9
1%
#592
0%
#593
b1010 9
1%
#594
0%
#595
b1011 9
1%
#596
0%
#597
b1100 9
1%
#598
0%
#599
b1101 9
1%
#600
0%
#601
b1110 9
1%
#602
0%
#603
b1111 9
1%
#604
0%
#605
b10000 9
1%
#606
0%
#607
b10001 9
1%
#608
0%
#609
b10010 9
1%
#610
0%
#611
b10011 9
1%
#612
0%
#613
b10100 9
1%
#614
0%
#615
b10101 9
1%
#616
0%
#617
b10110 9
1%
#618
0%
#619
b10111 9
1%
#620
0%
#621
b11000 9
1%
#622
0%
#623
b11001 9
1%
#624
0%
#625
0.
b0 9
1%
#626
0%
#627
b1 9
1%
#628
0%
#629
b10 9
1%
#630
0%
#631
b11 9
1%
#632
0%
#633
b100 9
1%
#634
0%
#635
b101 9
1%
#636
0%
#637
b110 9
1%
#638
0%
#639
b111 9
1%
#640
0%
#641
b1000 9
1%
#642
0%
#643
b1001 9
1%
#644
0%
#645
b1010 9
1%
#646
0%
#647
b1011 9
1%
#648
0%
#649
b1100 9
1%
#650
0%
#651
b1101 9
1%
#652
0%
#653
b1110 9
1%
#654
0%
#655
b1111 9
1%
#656
0%
#657
b10000 9
1%
#658
0%
#659
b10001 9
1%
#660
0%
#661
b10010 9
1%
#662
0%
#663
b10011 9
1%
#664
0%
#665
b10100 9
1%
#666
0%
#667
b10101 9
1%
#668
0%
#669
b10110 9
1%
#670
0%
#671
b10111 9
1%
#672
0%
#673
b11000 9
1%
#674
0%
#675
b11001 9
1%
#676
0%
#677
b111 3
1.
b0 9
1%
#678
0%
#679
b1 9
1%
#680
0%
#681
b10 9
1%
#682
0%
#683
b11 9
1%
#684
0%
#685
b100 9
1%
#686
0%
#687
b101 9
1%
#688
0%
#689
b110 9
1%
#690
0%
#691
b111 9
1%
#692
0%
#693
b1000 9
1%
#694
0%
#695
b1001 9
1%
#696
0%
#697
b1010 9
1%
#698
0%
#699
b1011 9
1%
#700
0%
#701
b1100 9
1%
#702
0%
#703
b1101 9
1%
#704
0%
#705
b1110 9
1%
#706
0%
#707
b1111 9
1%
#708
0%
#709
b10000 9
1%
#710
0%
#711
b10001 9
1%
#712
0%
#713
b10010 9
1%
#714
0%
#715
b10011 9
1%
#716
0%
#717
b10100 9
1%
#718
0%
#719
b10101 9
1%
#720
0%
#721
b10110 9
1%
#722
0%
#723
b10111 9
1%
#724
0%
#725
b11000 9
1%
#726
0%
#727
b11001 9
1%
#728
0%
#729
0.
b0 9
1%
#730
0%
#731
b1 9
1%
#732
0%
#733
b10 9
1%
#734
0%
#735
b11 9
1%
#736
0%
#737
b100 9
1%
#738
0%
#739
b101 9
1%
#740
0%
#741
b110 9
1%
#742
0%
#743
b111 9
1%
#744
0%
#745
b1000 9
1%
#746
0%
#747
b1001 9
1%
#748
0%
#749
b1010 9
1%
#750
0%
#751
b1011 9
1%
#752
0%
#753
b1100 9
1%
#754
0%
#755
b1101 9
1%
#756
0%
#757
b1110 9
1%
#758
0%
#759
b1111 9
1%
#760
0%
#761
b10000 9
1%
#762
0%
#763
b10001 9
1%
#764
0%
#765
b10010 9
1%
#766
0%
#767
b10011 9
1%
#768
0%
#769
b10100 9
1%
#770
0%
#771
b10101 9
1%
#772
0%
#773
b10110 9
1%
#774
0%
#775
b10111 9
1%
#776
0%
#777
b11000 9
1%
#778
0%
#779
b11001 9
1%
#780
0%
#781
b1000 3
1.
b0 9
1%
#782
0%
#783
b1 9
1%
#784
0%
#785
b10 9
1%
#786
0%
#787
b11 9
1%
#788
0%
#789
b100 9
1%
#790
0%
#791
b101 9
1%
#792
0%
#793
b110 9
1%
#794
0%
#795
b111 9
1%
#796
0%
#797
b1000 9
1%
#798
0%
#799
b1001 9
1%
#800
0%
#801
b1010 9
1%
#802
0%
#803
b1011 9
1%
#804
0%
#805
b1100 9
1%
#806
0%
#807
b1101 9
1%
#808
0%
#809
b1110 9
1%
#810
0%
#811
b1111 9
1%
#812
0%
#813
b10000 9
1%
#814
0%
#815
b10001 9
1%
#816
0%
#817
b10010 9
1%
#818
0%
#819
b10011 9
1%
#820
0%
#821
b10100 9
1%
#822
0%
#823
b10101 9
1%
#824
0%
#825
b10110 9
1%
#826
0%
#827
b10111 9
1%
#828
0%
#829
b11000 9
1%
#830
0%
#831
b11001 9
1%
#832
0%
#833
0.
b0 9
1%
#834
0%
#835
b1 9
1%
#836
0%
#837
b10 9
1%
#838
0%
#839
b11 9
1%
#840
0%
#841
b100 9
1%
#842
0%
#843
b101 9
1%
#844
0%
#845
b110 9
1%
#846
0%
#847
b111 9
1%
#848
0%
#849
b1000 9
1%
#850
0%
#851
b1001 9
1%
#852
0%
#853
b1010 9
1%
#854
0%
#855
b1011 9
1%
#856
0%
#857
b1100 9
1%
#858
0%
#859
b1101 9
1%
#860
0%
#861
b1110 9
1%
#862
0%
#863
b1111 9
1%
#864
0%
#865
b10000 9
1%
#866
0%
#867
b10001 9
1%
#868
0%
#869
b10010 9
1%
#870
0%
#871
b10011 9
1%
#872
0%
#873
b10100 9
1%
#874
0%
#875
b10101 9
1%
#876
0%
#877
b10110 9
1%
#878
0%
#879
b10111 9
1%
#880
0%
#881
b11000 9
1%
#882
0%
#883
b11001 9
1%
#884
0%
#885
b1001 3
1.
b0 9
1%
#886
0%
#887
b1 9
1%
#888
0%
#889
b10 9
1%
#890
0%
#891
b11 9
1%
#892
0%
#893
b100 9
1%
#894
0%
#895
b101 9
1%
#896
0%
#897
b110 9
1%
#898
0%
#899
b111 9
1%
#900
0%
#901
b1000 9
1%
#902
0%
#903
b1001 9
1%
#904
0%
#905
b1010 9
1%
#906
0%
#907
b1011 9
1%
#908
0%
#909
b1100 9
1%
#910
0%
#911
b1101 9
1%
#912
0%
#913
b1110 9
1%
#914
0%
#915
b1111 9
1%
#916
0%
#917
b10000 9
1%
#918
0%
#919
b10001 9
1%
#920
0%
#921
b10010 9
1%
#922
0%
#923
b10011 9
1%
#924
0%
#925
b10100 9
1%
#926
0%
#927
b10101 9
1%
#928
0%
#929
b10110 9
1%
#930
0%
#931
b10111 9
1%
#932
0%
#933
b11000 9
1%
#934
0%
#935
b11001 9
1%
#936
0%
#937
0.
b0 9
1%
#938
0%
#939
b1 9
1%
#940
0%
#941
b10 9
1%
#942
0%
#943
b11 9
1%
#944
0%
#945
b100 9
1%
#946
0%
#947
b101 9
1%
#948
0%
#949
b110 9
1%
#950
0%
#951
b111 9
1%
#952
0%
#953
b1000 9
1%
#954
0%
#955
b1001 9
1%
#956
0%
#957
b1010 9
1%
#958
0%
#959
b1011 9
1%
#960
0%
#961
b1100 9
1%
#962
0%
#963
b1101 9
1%
#964
0%
#965
b1110 9
1%
#966
0%
#967
b1111 9
1%
#968
0%
#969
b10000 9
1%
#970
0%
#971
b10001 9
1%
#972
0%
#973
b10010 9
1%
#974
0%
#975
b10011 9
1%
#976
0%
#977
b10100 9
1%
#978
0%
#979
b10101 9
1%
#980
0%
#981
b10110 9
1%
#982
0%
#983
b10111 9
1%
#984
0%
#985
b11000 9
1%
#986
0%
#987
b11001 9
1%
#988
0%
#989
b1010 3
1.
b0 9
1%
#990
0%
#991
b1 9
1%
#992
0%
#993
b10 9
1%
#994
0%
#995
b11 9
1%
#996
0%
#997
b100 9
1%
#998
0%
#999
b101 9
1%
#1000
0%
#1001
b110 9
1%
#1002
0%
#1003
b111 9
1%
#1004
0%
#1005
b1000 9
1%
#1006
0%
#1007
b1001 9
1%
#1008
0%
#1009
b1010 9
1%
#1010
0%
#1011
b1011 9
1%
#1012
0%
#1013
b1100 9
1%
#1014
0%
#1015
b1101 9
1%
#1016
0%
#1017
b1110 9
1%
#1018
0%
#1019
b1111 9
1%
#1020
0%
#1021
b10000 9
1%
#1022
0%
#1023
b10001 9
1%
#1024
0%
#1025
b10010 9
1%
#1026
0%
#1027
b10011 9
1%
#1028
0%
#1029
b10100 9
1%
#1030
0%
#1031
b10101 9
1%
#1032
0%
#1033
b10110 9
1%
#1034
0%
#1035
b10111 9
1%
#1036
0%
#1037
b11000 9
1%
#1038
0%
#1039
b11001 9
1%
#1040
0%
#1041
0.
b0 9
1%
#1042
0%
#1043
b1 9
1%
#1044
0%
#1045
b10 9
1%
#1046
0%
#1047
b11 9
1%
#1048
0%
#1049
b100 9
1%
#1050
0%
#1051
b101 9
1%
#1052
0%
#1053
b110 9
1%
#1054
0%
#1055
b111 9
1%
#1056
0%
#1057
b1000 9
1%
#1058
0%
#1059
b1001 9
1%
#1060
0%
#1061
b1010 9
1%
#1062
0%
#1063
b1011 9
1%
#1064
0%
#1065
b1100 9
1%
#1066
0%
#1067
b1101 9
1%
#1068
0%
#1069
b1110 9
1%
#1070
0%
#1071
b1111 9
1%
#1072
0%
#1073
b10000 9
1%
#1074
0%
#1075
b10001 9
1%
#1076
0%
#1077
b10010 9
1%
#1078
0%
#1079
b10011 9
1%
#1080
0%
#1081
b10100 9
1%
#1082
0%
#1083
b10101 9
1%
#1084
0%
#1085
b10110 9
1%
#1086
0%
#1087
b10111 9
1%
#1088
0%
#1089
b11000 9
1%
#1090
0%
#1091
b11001 9
1%
#1092
0%
#1093
b1011 3
1.
b0 9
1%
#1094
0%
#1095
b1 9
1%
#1096
0%
#1097
b10 9
1%
#1098
0%
#1099
b11 9
1%
#1100
0%
#1101
b100 9
1%
#1102
0%
#1103
b101 9
1%
#1104
0%
#1105
b110 9
1%
#1106
0%
#1107
b111 9
1%
#1108
0%
#1109
b1000 9
1%
#1110
0%
#1111
b1001 9
1%
#1112
0%
#1113
b1010 9
1%
#1114
0%
#1115
b1011 9
1%
#1116
0%
#1117
b1100 9
1%
#1118
0%
#1119
b1101 9
1%
#1120
0%
#1121
b1110 9
1%
#1122
0%
#1123
b1111 9
1%
#1124
0%
#1125
b10000 9
1%
#1126
0%
#1127
b10001 9
1%
#1128
0%
#1129
b10010 9
1%
#1130
0%
#1131
b10011 9
1%
#1132
0%
#1133
b10100 9
1%
#1134
0%
#1135
b10101 9
1%
#1136
0%
#1137
b10110 9
1%
#1138
0%
#1139
b10111 9
1%
#1140
0%
#1141
b11000 9
1%
#1142
0%
#1143
b11001 9
1%
#1144
0%
#1145
0.
b0 9
1%
#1146
0%
#1147
b1 9
1%
#1148
0%
#1149
b10 9
1%
#1150
0%
#1151
b11 9
1%
#1152
0%
#1153
b100 9
1%
#1154
0%
#1155
b101 9
1%
#1156
0%
#1157
b110 9
1%
#1158
0%
#1159
b111 9
1%
#1160
0%
#1161
b1000 9
1%
#1162
0%
#1163
b1001 9
1%
#1164
0%
#1165
b1010 9
1%
#1166
0%
#1167
b1011 9
1%
#1168
0%
#1169
b1100 9
1%
#1170
0%
#1171
b1101 9
1%
#1172
0%
#1173
b1110 9
1%
#1174
0%
#1175
b1111 9
1%
#1176
0%
#1177
b10000 9
1%
#1178
0%
#1179
b10001 9
1%
#1180
0%
#1181
b10010 9
1%
#1182
0%
#1183
b10011 9
1%
#1184
0%
#1185
b10100 9
1%
#1186
0%
#1187
b10101 9
1%
#1188
0%
#1189
b10110 9
1%
#1190
0%
#1191
b10111 9
1%
#1192
0%
#1193
b11000 9
1%
#1194
0%
#1195
b11001 9
1%
#1196
0%
#1197
b1100 3
1.
b0 9
1%
#1198
0%
#1199
b1 9
1%
#1200
0%
#1201
b10 9
1%
#1202
0%
#1203
b11 9
1%
#1204
0%
#1205
b100 9
1%
#1206
0%
#1207
b101 9
1%
#1208
0%
#1209
b110 9
1%
#1210
0%
#1211
b111 9
1%
#1212
0%
#1213
b1000 9
1%
#1214
0%
#1215
b1001 9
1%
#1216
0%
#1217
b1010 9
1%
#1218
0%
#1219
b1011 9
1%
#1220
0%
#1221
b1100 9
1%
#1222
0%
#1223
b1101 9
1%
#1224
0%
#1225
b1110 9
1%
#1226
0%
#1227
b1111 9
1%
#1228
0%
#1229
b10000 9
1%
#1230
0%
#1231
b10001 9
1%
#1232
0%
#1233
b10010 9
1%
#1234
0%
#1235
b10011 9
1%
#1236
0%
#1237
b10100 9
1%
#1238
0%
#1239
b10101 9
1%
#1240
0%
#1241
b10110 9
1%
#1242
0%
#1243
b10111 9
1%
#1244
0%
#1245
b11000 9
1%
#1246
0%
#1247
b11001 9
1%
#1248
0%
#1249
0.
b0 9
1%
#1250
0%
#1251
b1 9
1%
#1252
0%
#1253
b10 9
1%
#1254
0%
#1255
b11 9
1%
#1256
0%
#1257
b100 9
1%
#1258
0%
#1259
b101 9
1%
#1260
0%
#1261
b110 9
1%
#1262
0%
#1263
b111 9
1%
#1264
0%
#1265
b1000 9
1%
#1266
0%
#1267
b1001 9
1%
#1268
0%
#1269
b1010 9
1%
#1270
0%
#1271
b1011 9
1%
#1272
0%
#1273
b1100 9
1%
#1274
0%
#1275
b1101 9
1%
#1276
0%
#1277
b1110 9
1%
#1278
0%
#1279
b1111 9
1%
#1280
0%
#1281
b10000 9
1%
#1282
0%
#1283
b10001 9
1%
#1284
0%
#1285
b10010 9
1%
#1286
0%
#1287
b10011 9
1%
#1288
0%
#1289
b10100 9
1%
#1290
0%
#1291
b10101 9
1%
#1292
0%
#1293
b10110 9
1%
#1294
0%
#1295
b10111 9
1%
#1296
0%
#1297
b11000 9
1%
#1298
0%
#1299
b11001 9
1%
#1300
0%
#1301
b1101 3
1.
b0 9
1%
#1302
0%
#1303
b1 9
1%
#1304
0%
#1305
b10 9
1%
#1306
0%
#1307
b11 9
1%
#1308
0%
#1309
b100 9
1%
#1310
0%
#1311
b101 9
1%
#1312
0%
#1313
b110 9
1%
#1314
0%
#1315
b111 9
1%
#1316
0%
#1317
b1000 9
1%
#1318
0%
#1319
b1001 9
1%
#1320
0%
