MPEI_Magistracy/Term_one/digital_design/KM_2_memory/RAM/RAM_32x8.sv
module RAM_32x8 
#(
    parameter  WIDTH = 32,
    parameter  DEPTH = 8
) 
(
    input   logic [ DEPTH - 1 : 0 ]          Addr,
    input   logic [ WIDTH - 1 : 0 ]          Datain,
    input   logic                            We, 
    input   logic                            clk, 
    output  logic [ WIDTH - 1 : 0 ]          Dataout   
);

    logic [WIDTH-1:0] RAM [2**DEPTH];
    
    initial begin
     $readmemb("RAM_32x8.txt",RAM);
     end
 
    always_ff @(posedge clk ) begin
        if (!We)
            Dataout <= RAM[Addr];
        else 
            RAM[Addr] <= Datain;
    end

endmodule

MPEI_Magistracy/Term_1/digital_design/KM_2_memory/RAM/RAM_32x8_tb.sv
`include "RAM_32x8.sv"
`timescale 1 ns / 1 ns
module RAM_32x_8_tb
#(
    parameter WIDTH = 32,
    parameter DEPTH = 8 
);

    logic clk, We;

    logic [(DEPTH)-1:0] Addr;
    logic [WIDTH-1:0] Datain;
    logic [WIDTH-1:0] Dataout;
    
    RAM_32x8 
    #(
        .WIDTH(32),
        .DEPTH(8)
    ) 
    DUT 
    (
        .Addr(Addr),
        .clk(clk),
        .We(We),
        .Datain(Datain),
        .Dataout(Dataout)
    );
    
    initial begin
        $display("Running testbench");
        clk = 0;
        We   = 0;
    end

    always #10  clk =  !clk; 

    initial begin
        We = 0;
        #500;
        We = 1;
        #500;
        We = 0;
        #500;
    end  

    initial begin
        for (int i = 0; i <= 15; i++) begin
          Datain = $urandom_range(0, 2**WIDTH-1);
          #100;                     
        end
    end

    initial begin
        Addr = 34;
        #100;
        Addr = 105;
        #100;
        Addr = 20;
        #100;
        Addr = 227;
        #100;
        Addr = 79;
        #100;
         Addr = 34;
        #100;
        Addr = 105;
        #100;
        Addr = 20;
        #100;
        Addr = 227;
        #100;
        Addr = 79;
        #100;
         Addr = 34;
        #100;
        Addr = 105;
        #100;
        Addr = 20;
        #100;
        Addr = 227;
        #100;
        Addr = 79;
        #100;
    end  

    initial begin
        #1520 $display("Testbench is OK!");
        $finish;
    end

    initial begin
        $dumpfile("RAM_32x8.vcd");
        $dumpvars;
    end

endmodule

MPEI_Magistracy/Term_1/digital_design/KM_2_memory/files/vcd/RAM_32x8.vcd
$date
	Wed Oct 18 00:06:41 2023
$end
$version
	Icarus Verilog
$end
$timescale
	1ns
$end
$scope module RAM_32x_8_tb $end
$var wire 32 ! Dataout [31:0] $end
$var parameter 32 " DEPTH $end
$var parameter 32 # WIDTH $end
$var reg 8 $ Addr [7:0] $end
$var reg 32 % Datain [31:0] $end
$var reg 1 & We $end
$var reg 1 ' clk $end
$scope module DUT $end
$var wire 8 ( Addr [7:0] $end
$var wire 32 ) Datain [31:0] $end
$var wire 1 & We $end
$var wire 1 ' clk $end
$var parameter 32 * DEPTH $end
$var parameter 32 + WIDTH $end
$var reg 32 , Dataout [31:0] $end
$upscope $end
$scope begin $ivl_for_loop0 $end
$var integer 32 - i [31:0] $end
$upscope $end
$upscope $end
$enddefinitions $end
$comment Show the parameter values. $end
$dumpall
b100000 +
b1000 *
b100000 #
b1000 "
$end
#0
$dumpvars
b0 -
bx ,
b10010010000101010011010100100100 )
b100010 (
0'
0&
b10010010000101010011010100100100 %
b100010 $
bx !
$end
#10
b10101011011100111111110100101010 !
b10101011011100111111110100101010 ,
1'
#20
0'
#30
1'
#40
0'
#50
1'
#60
0'
#70
1'
#80
0'
#90
1'
#100
0'
b1101001 $
b1101001 (
b1000000100010010101111010000001 %
b1000000100010010101111010000001 )
b1 -
#110
b10011100110110110111011001011110 !
b10011100110110110111011001011110 ,
1'
#120
0'
#130
1'
#140
0'
#150
1'
#160
0'
#170
1'
#180
0'
#190
1'
#200
0'
b10100 $
b10100 (
b100100001001101011000001001 %
b100100001001101011000001001 )
b10 -
#210
b1000111001110010000011111110101 !
b1000111001110010000011111110101 ,
1'
#220
0'
#230
1'
#240
0'
#250
1'
#260
0'
#270
1'
#280
0'
#290
1'
#300
0'
b11100011 $
b11100011 (
b110001111100000101011001100011 %
b110001111100000101011001100011 )
b11 -
#310
b11101111101001000100101111010110 !
b11101111101001000100101111010110 ,
1'
#320
0'
#330
1'
#340
0'
#350
1'
#360
0'
#370
1'
#380
0'
#390
1'
#400
0'
b1001111 $
b1001111 (
b10000110101110010111101100001101 %
b10000110101110010111101100001101 )
b100 -
#410
b11011000100111000100110000110110 !
b11011000100111000100110000110110 ,
1'
#420
0'
#430
1'
#440
0'
#450
1'
#460
0'
#470
1'
#480
0'
#490
1'
#500
0'
b100010 $
b100010 (
b11000110110111111001100110001101 %
b11000110110111111001100110001101 )
b101 -
1&
#510
1'
#520
0'
#530
1'
#540
0'
#550
1'
#560
0'
#570
1'
#580
0'
#590
1'
#600
0'
b1101001 $
b1101001 (
b110010110000101000010001100101 %
b110010110000101000010001100101 )
b110 -
#610
1'
#620
0'
#630
1'
#640
0'
#650
1'
#660
0'
#670
1'
#680
0'
#690
1'
#700
0'
b10100 $
b10100 (
b1001001101110101001000010010 %
b1001001101110101001000010010 )
b111 -
#710
1'
#720
0'
#730
1'
#740
0'
#750
1'
#760
0'
#770
1'
#780
0'
#790
1'
#800
0'
b11100011 $
b11100011 (
b10000000111100111110001100000001 %
b10000000111100111110001100000001 )
b1000 -
#810
1'
#820
0'
#830
1'
#840
0'
#850
1'
#860
0'
#870
1'
#880
0'
#890
1'
#900
0'
b1001111 $
b1001111 (
b10000110110101111100110100001101 %
b10000110110101111100110100001101 )
b1001 -
#910
1'
#920
0'
#930
1'
#940
0'
#950
1'
#960
0'
#970
1'
#980
0'
#990
1'
#1000
0'
b100010 $
b100010 (
b10111011001000111111000101110110 %
b10111011001000111111000101110110 )
b1010 -
0&
#1010
b11000110110111111001100110001101 !
b11000110110111111001100110001101 ,
1'
#1020
0'
#1030
1'
#1040
0'
#1050
1'
#1060
0'
#1070
1'
#1080
0'
#1090
1'
#1100
0'
b1101001 $
b1101001 (
b10011110100011011100110100111101 %
b10011110100011011100110100111101 )
b1011 -
#1110
b110010110000101000010001100101 !
b110010110000101000010001100101 ,
1'
#1120
0'
#1130
1'
#1140
0'
#1150
1'
#1160
0'
#1170
1'
#1180
0'
#1190
1'
#1200
0'
b10100 $
b10100 (
b11110110110101000101011111101101 %
b11110110110101000101011111101101 )
b1100 -
#1210
b1001001101110101001000010010 !
b1001001101110101001000010010 ,
1'
#1220
0'
#1230
1'
#1240
0'
#1250
1'
#1260
0'
#1270
1'
#1280
0'
#1290
1'
#1300
0'
b11100011 $
b11100011 (
b11000110001011011111011110001100 %
b11000110001011011111011110001100 )
b1101 -
#1310
b10000000111100111110001100000001 !
b10000000111100111110001100000001 ,
1'
#1320
0'
#1330
1'
#1340
0'
#1350
1'
#1360
0'
#1370
1'
#1380
0'
#1390
1'
#1400
0'
b1001111 $
b1001111 (
b11111100111111011110100111111001 %
b11111100111111011110100111111001 )
b1110 -
#1410
b10000110110101111100110100001101 !
b10000110110101111100110100001101 ,
1'
#1420
0'
#1430
1'
#1440
0'
#1450
1'
#1460
0'
#1470
1'
#1480
0'
#1490
1'
#1500
0'
b1100011001101110010010011000110 %
b1100011001101110010010011000110 )
b1111 -
