MPEI_Magistracy/Term_2/ASIC_design/LFSR/LFSR_Galois/src/LFSR_Galois.sv
module LFSR_Galois 
#(
    parameter MAX_LEN = 8
)
(   
    input  logic                         CLK_I,
    input  logic                         RST_N_I,
    input  logic                         EN_I,
    input  logic                         LOAD_I,
    input  logic    [ MAX_LEN - 1 : 0 ]  SEED_I,
    input  logic    [ MAX_LEN - 1 : 0 ]  POLY_I,
    output logic    [ MAX_LEN - 1 : 0 ]  DATA_O
);

    logic [ MAX_LEN - 1 : 0 ] data_reg;
    logic [ MAX_LEN - 1 : 0 ] poly_reg;
    logic                     feedback;

    always_ff @ (posedge CLK_I, negedge RST_N_I) begin
        if(!RST_N_I) begin
            data_reg <= 0;
            poly_reg <= 0;
        end
        else begin
            if (LOAD_I) begin
                data_reg <= SEED_I;
                poly_reg <= POLY_I;
            end
            else begin
                feedback <= data_reg[0];
                for (int i = 0; i < MAX_LEN-1; i++) begin
                    data_reg[i] <= poly_reg[i] ? (data_reg[i+1] ^ feedback) : data_reg[i+1];
                end
            end
        end
    end

    always_comb 
        DATA_O = data_reg;

endmodule

MPEI_Magistracy/Term_2/ASIC_design/LFSR/LFSR_Galois/src/tb.sv
`include "LFSR_Galois.sv"
module tb ();

    `define MAX_LEN     8

    logic                               clk     = 0;
    logic                               load    = 0;
    logic                               rst_n   = 0;
    logic [`MAX_LEN - 1 : 0]            seed    = 8'b11100111;
    logic [`MAX_LEN - 1 : 0]            poly    = 8'b10011001;
    logic [`MAX_LEN - 1 : 0]            data;

    logic [`MAX_LEN - 1 : 0]            calc_seq;
    logic                               new_bit;

    initial forever #5 clk <= ~clk;

    initial begin
        rst_n = 0;
        #10 
        rst_n = 1;
        #100;
        for (int j = 0; j < 20; j++) begin
            @(posedge clk);
            load <= 1;
            @(posedge clk);
            load <= 0;

            for (int i = 0; i < 80; i++) begin
                @(posedge clk);
                $display("SEED = %0b", seed);
                $display("POLY = %0b", poly);
                $display("DATA = %0b", data);
            end
        end
        #10us $finish;
    end

    LFSR_Galois #(
        .MAX_LEN( `MAX_LEN  )
    ) UUT (
        .CLK_I   ( clk       ),
        .RST_N_I ( rst_n     ),
        .EN_I    ( enable    ),
        .LOAD_I  ( load      ),
        .SEED_I  ( seed      ),
        .POLY_I  ( poly      ),
        .DATA_O  ( data      )
    );

    initial begin
        $dumpfile("../dump/wave.vcd");
        $dumpvars();
    end

endmodule

MPEI_Magistracy/Term_2/ASIC_design/LFSR/LFSR_Galois/dump/wave.vcd
$date
	Wed Mar 27 13:16:23 2024
$end
$version
	Icarus Verilog
$end
$timescale
	1s
$end
$scope module tb $end
$var wire 1 ! enable $end
$var wire 8 " data [7:0] $end
$var reg 1 # clk $end
$var reg 1 $ load $end
$var reg 8 % poly [7:0] $end
$var reg 1 & rst_n $end
$var reg 8 ' seed [7:0] $end
$scope module UUT $end
$var wire 1 # CLK_I $end
$var wire 1 ! EN_I $end
$var wire 1 $ LOAD_I $end
$var wire 8 ( POLY_I [7:0] $end
$var wire 1 & RST_N_I $end
$var wire 8 ) SEED_I [7:0] $end
$var parameter 32 * MAX_LEN $end
$var reg 8 + DATA_O [7:0] $end
$var reg 8 , data_reg [7:0] $end
$var reg 1 - feedback $end
$var reg 8 . poly_reg [7:0] $end
$scope begin $ivl_for_loop0 $end
$var integer 32 / i [31:0] $end
$upscope $end
$upscope $end
$scope begin $ivl_for_loop1 $end
$var integer 32 0 j [31:0] $end
$scope begin $ivl_for_loop2 $end
$var integer 32 1 i [31:0] $end
$upscope $end
$upscope $end
$upscope $end
$enddefinitions $end
$comment Show the parameter values. $end
$dumpall
b1000 *
$end
#0
$dumpvars
b0 1
b0 0
b0 /
bx .
x-
bx ,
bx +
b11100111 )
b10011001 (
b11100111 '
0&
b10011001 %
0$
0#
bx "
z!
$end
#5
b0 "
b0 +
b0 .
b0 ,
1#
#10
0#
1&
#15
0-
b111 /
1#
#20
0#
#25
b111 /
1#
#30
0#
#35
b111 /
1#
#40
0#
#45
b111 /
1#
#50
0#
#55
b111 /
1#
#60
0#
#65
b111 /
1#
#70
0#
#75
b111 /
1#
#80
0#
#85
b111 /
1#
#90
0#
#95
b111 /
1#
#100
0#
#105
b111 /
1#
#110
0#
#115
1$
b111 /
1#
#120
0#
#125
b11100111 "
b11100111 +
b10011001 .
b11100111 ,
0$
1#
#130
0#
#135
b11110011 "
b11110011 +
b11110011 ,
1-
b111 /
b1 1
1#
#140
0#
#145
b11100000 "
b11100000 +
b11100000 ,
b111 /
b10 1
1#
#150
0#
#155
b11101001 "
b11101001 +
b11101001 ,
0-
b111 /
b11 1
1#
#160
0#
#165
b11110100 "
b11110100 +
b11110100 ,
1-
b111 /
b100 1
1#
#170
0#
#175
b11100011 "
b11100011 +
b11100011 ,
0-
b111 /
b101 1
1#
#180
0#
#185
b11110001 "
b11110001 +
b11110001 ,
1-
b111 /
b110 1
1#
#190
0#
#195
b11100001 "
b11100001 +
b11100001 ,
b111 /
b111 1
1#
#200
0#
#205
b11101001 "
b11101001 +
b11101001 ,
b111 /
b1000 1
1#
#210
0#
#215
b11101101 "
b11101101 +
b11101101 ,
b111 /
b1001 1
1#
#220
0#
#225
b11101111 "
b11101111 +
b11101111 ,
b111 /
b1010 1
1#
#230
0#
#235
b11101110 "
b11101110 +
b11101110 ,
b111 /
b1011 1
1#
#240
0#
#245
0-
b111 /
b1100 1
1#
#250
0#
#255
b11110111 "
b11110111 +
b11110111 ,
b111 /
b1101 1
1#
#260
0#
#265
b11111011 "
b11111011 +
b11111011 ,
1-
b111 /
b1110 1
1#
#270
0#
#275
b11100100 "
b11100100 +
b11100100 ,
b111 /
b1111 1
1#
#280
0#
#285
b11101011 "
b11101011 +
b11101011 ,
0-
b111 /
b10000 1
1#
#290
0#
#295
b11110101 "
b11110101 +
b11110101 ,
1-
b111 /
b10001 1
1#
#300
0#
#305
b11100011 "
b11100011 +
b11100011 ,
b111 /
b10010 1
1#
#310
0#
#315
b11101000 "
b11101000 +
b11101000 ,
b111 /
b10011 1
1#
#320
0#
#325
b11101101 "
b11101101 +
b11101101 ,
0-
b111 /
b10100 1
1#
#330
0#
#335
b11110110 "
b11110110 +
b11110110 ,
1-
b111 /
b10101 1
1#
#340
0#
#345
b11100010 "
b11100010 +
b11100010 ,
0-
b111 /
b10110 1
1#
#350
0#
#355
b11110001 "
b11110001 +
b11110001 ,
b111 /
b10111 1
1#
#360
0#
#365
b11111000 "
b11111000 +
b11111000 ,
1-
b111 /
b11000 1
1#
#370
0#
#375
b11100101 "
b11100101 +
b11100101 ,
0-
b111 /
b11001 1
1#
#380
0#
#385
b11110010 "
b11110010 +
b11110010 ,
1-
b111 /
b11010 1
1#
#390
0#
#395
b11100000 "
b11100000 +
b11100000 ,
0-
b111 /
b11011 1
1#
#400
0#
#405
b11110000 "
b11110000 +
b11110000 ,
b111 /
b11100 1
1#
#410
0#
#415
b11111000 "
b11111000 +
b11111000 ,
b111 /
b11101 1
1#
#420
0#
#425
b11111100 "
b11111100 +
b11111100 ,
b111 /
b11110 1
1#
#430
0#
#435
b11111110 "
b11111110 +
b11111110 ,
b111 /
b11111 1
1#
#440
0#
#445
b11111111 "
b11111111 +
b11111111 ,
b111 /
b100000 1
1#
#450
0#
#455
1-
b111 /
b100001 1
1#
#460
0#
#465
b11100110 "
b11100110 +
b11100110 ,
b111 /
b100010 1
1#
#470
0#
#475
b11101010 "
b11101010 +
b11101010 ,
0-
b111 /
b100011 1
1#
#480
0#
#485
b11110101 "
b11110101 +
b11110101 ,
b111 /
b100100 1
1#
#490
0#
#495
b11111010 "
b11111010 +
b11111010 ,
1-
b111 /
b100101 1
1#
#500
0#
#505
b11100100 "
b11100100 +
b11100100 ,
0-
b111 /
b100110 1
1#
#510
0#
#515
b11110010 "
b11110010 +
b11110010 ,
b111 /
b100111 1
1#
#520
0#
#525
b11111001 "
b11111001 +
b11111001 ,
b111 /
b101000 1
1#
#530
0#
#535
b11111100 "
b11111100 +
b11111100 ,
1-
b111 /
b101001 1
1#
#540
0#
#545
b11100111 "
b11100111 +
b11100111 ,
0-
b111 /
b101010 1
1#
#550
0#
#555
b11110011 "
b11110011 +
b11110011 ,
1-
b111 /
b101011 1
1#
#560
0#
#565
b11100000 "
b11100000 +
b11100000 ,
b111 /
b101100 1
1#
#570
0#
#575
b11101001 "
b11101001 +
b11101001 ,
0-
b111 /
b101101 1
1#
#580
0#
#585
b11110100 "
b11110100 +
b11110100 ,
1-
b111 /
b101110 1
1#
#590
0#
#595
b11100011 "
b11100011 +
b11100011 ,
0-
b111 /
b101111 1
1#
#600
0#
#605
b11110001 "
b11110001 +
b11110001 ,
1-
b111 /
b110000 1
1#
#610
0#
#615
b11100001 "
b11100001 +
b11100001 ,
b111 /
b110001 1
1#
#620
0#
#625
b11101001 "
b11101001 +
b11101001 ,
b111 /
b110010 1
1#
#630
0#
#635
b11101101 "
b11101101 +
b11101101 ,
b111 /
b110011 1
1#
#640
0#
#645
b11101111 "
b11101111 +
b11101111 ,
b111 /
b110100 1
1#
#650
0#
#655
b11101110 "
b11101110 +
b11101110 ,
b111 /
b110101 1
1#
#660
0#
#665
0-
b111 /
b110110 1
1#
#670
0#
#675
b11110111 "
b11110111 +
b11110111 ,
b111 /
b110111 1
1#
#680
0#
#685
b11111011 "
b11111011 +
b11111011 ,
1-
b111 /
b111000 1
1#
#690
0#
#695
b11100100 "
b11100100 +
b11100100 ,
b111 /
b111001 1
1#
#700
0#
#705
b11101011 "
b11101011 +
b11101011 ,
0-
b111 /
b111010 1
1#
#710
0#
#715
b11110101 "
b11110101 +
b11110101 ,
1-
b111 /
b111011 1
1#
#720
0#
#725
b11100011 "
b11100011 +
b11100011 ,
b111 /
b111100 1
1#
#730
0#
#735
b11101000 "
b11101000 +
b11101000 ,
b111 /
b111101 1
1#
#740
0#
#745
b11101101 "
b11101101 +
b11101101 ,
0-
b111 /
b111110 1
1#
#750
0#
#755
b11110110 "
b11110110 +
b11110110 ,
1-
b111 /
b111111 1
1#
#760
0#
#765
b11100010 "
b11100010 +
b11100010 ,
0-
b111 /
b1000000 1
1#
#770
0#
#775
b11110001 "
b11110001 +
b11110001 ,
b111 /
b1000001 1
1#
#780
0#
#785
b11111000 "
b11111000 +
b11111000 ,
1-
b111 /
b1000010 1
1#
#790
0#
#795
b11100101 "
b11100101 +
b11100101 ,
0-
b111 /
b1000011 1
1#
#800
0#
#805
b11110010 "
b11110010 +
b11110010 ,
1-
b111 /
b1000100 1
1#
#810
0#
#815
b11100000 "
b11100000 +
b11100000 ,
0-
b111 /
b1000101 1
1#
#820
0#
#825
b11110000 "
b11110000 +
b11110000 ,
b111 /
b1000110 1
1#
#830
0#
#835
b11111000 "
b11111000 +
b11111000 ,
b111 /
b1000111 1
1#
#840
0#
#845
b11111100 "
b11111100 +
b11111100 ,
b111 /
b1001000 1
1#
#850
0#
#855
b11111110 "
b11111110 +
b11111110 ,
b111 /
b1001001 1
1#
#860
0#
#865
b11111111 "
b11111111 +
b11111111 ,
b111 /
b1001010 1
1#
#870
0#
#875
1-
b111 /
b1001011 1
1#
#880
0#
#885
b11100110 "
b11100110 +
b11100110 ,
b111 /
b1001100 1
1#
#890
0#
#895
b11101010 "
b11101010 +
b11101010 ,
0-
b111 /
b1001101 1
1#
#900
0#
#905
b11110101 "
b11110101 +
b11110101 ,
b111 /
b1001110 1
1#
#910
0#
#915
b11111010 "
b11111010 +
b11111010 ,
1-
b111 /
b1001111 1
1#
#920
0#
#925
b11100100 "
b11100100 +
b11100100 ,
0-
b111 /
b1 0
b1010000 1
1#
#930
0#
#935
b11110010 "
b11110010 +
b11110010 ,
1$
b111 /
1#
#940
0#
#945
b11100111 "
b11100111 +
b11100111 ,
0$
b0 1
1#
#950
0#
#955
b11110011 "
b11110011 +
b11110011 ,
1-
b111 /
b1 1
1#
#960
0#
#965
b11100000 "
b11100000 +
b11100000 ,
b111 /
b10 1
1#
#970
0#
#975
b11101001 "
b11101001 +
b11101001 ,
0-
b111 /
b11 1
1#
#980
0#
#985
b11110100 "
b11110100 +
b11110100 ,
1-
b111 /
b100 1
1#
#990
0#
#995
b11100011 "
b11100011 +
b11100011 ,
0-
b111 /
b101 1
1#
#1000
0#
#1005
b11110001 "
b11110001 +
b11110001 ,
1-
b111 /
b110 1
1#
#1010
0#
#1015
b11100001 "
b11100001 +
b11100001 ,
b111 /
b111 1
1#
#1020
0#
#1025
b11101001 "
b11101001 +
b11101001 ,
b111 /
b1000 1
1#
#1030
0#
#1035
b11101101 "
b11101101 +
b11101101 ,
b111 /
b1001 1
1#
#1040
0#
#1045
b11101111 "
b11101111 +
b11101111 ,
b111 /
b1010 1
1#
#1050
0#
#1055
b11101110 "
b11101110 +
b11101110 ,
b111 /
b1011 1
1#
#1060
0#
#1065
0-
b111 /
b1100 1
1#
#1070
0#
#1075
b11110111 "
b11110111 +
b11110111 ,
b111 /
b1101 1
1#
#1080
0#
#1085
b11111011 "
b11111011 +
b11111011 ,
1-
b111 /
b1110 1
1#
#1090
0#
#1095
b11100100 "
b11100100 +
b11100100 ,
b111 /
b1111 1
1#
#1100
0#
#1105
b11101011 "
b11101011 +
b11101011 ,
0-
b111 /
b10000 1
1#
#1110
0#
#1115
b11110101 "
b11110101 +
b11110101 ,
1-
b111 /
b10001 1
1#
#1120
0#
#1125
b11100011 "
b11100011 +
b11100011 ,
b111 /
b10010 1
1#
#1130
0#
#1135
b11101000 "
b11101000 +
b11101000 ,
b111 /
b10011 1
1#
#1140
0#
#1145
b11101101 "
b11101101 +
b11101101 ,
0-
b111 /
b10100 1
1#
#1150
0#
#1155
b11110110 "
b11110110 +
b11110110 ,
1-
b111 /
b10101 1
1#
#1160
0#
#1165
b11100010 "
b11100010 +
b11100010 ,
0-
b111 /
b10110 1
1#
#1170
0#
#1175
b11110001 "
b11110001 +
b11110001 ,
b111 /
b10111 1
1#
#1180
0#
#1185
b11111000 "
b11111000 +
b11111000 ,
1-
b111 /
b11000 1
1#
#1190
0#
#1195
b11100101 "
b11100101 +
b11100101 ,
0-
b111 /
b11001 1
1#
#1200
0#
#1205
b11110010 "
b11110010 +
b11110010 ,
1-
b111 /
b11010 1
1#
#1210
0#
#1215
b11100000 "
b11100000 +
b11100000 ,
0-
b111 /
b11011 1
1#
#1220
0#
#1225
b11110000 "
b11110000 +
b11110000 ,
b111 /
b11100 1
1#
#1230
0#
#1235
b11111000 "
b11111000 +
b11111000 ,
b111 /
b11101 1
1#
#1240
0#
#1245
b11111100 "
b11111100 +
b11111100 ,
b111 /
b11110 1
1#
#1250
0#
#1255
b11111110 "
b11111110 +
b11111110 ,
b111 /
b11111 1
1#
#1260
0#
#1265
b11111111 "
b11111111 +
b11111111 ,
b111 /
b100000 1
1#
#1270
0#
#1275
1-
b111 /
b100001 1
1#
#1280
0#
#1285
b11100110 "
b11100110 +
b11100110 ,
b111 /
b100010 1
1#
#1290
0#
#1295
b11101010 "
b11101010 +
b11101010 ,
0-
b111 /
b100011 1
1#
#1300
0#
#1305
b11110101 "
b11110101 +
b11110101 ,
b111 /
b100100 1
1#
#1310
0#
#1315
b11111010 "
b11111010 +
b11111010 ,
1-
b111 /
b100101 1
1#
#1320
0#
#1325
b11100100 "
b11100100 +
b11100100 ,
0-
b111 /
b100110 1
1#
#1330
0#
#1335
b11110010 "
b11110010 +
b11110010 ,
b111 /
b100111 1
1#
#1340
0#
#1345
b11111001 "
b11111001 +
b11111001 ,
b111 /
b101000 1
1#
#1350
0#
#1355
b11111100 "
b11111100 +
b11111100 ,
1-
b111 /
b101001 1
1#
#1360
0#
#1365
b11100111 "
b11100111 +
b11100111 ,
0-
b111 /
b101010 1
1#
#1370
0#
#1375
b11110011 "
b11110011 +
b11110011 ,
1-
b111 /
b101011 1
1#
#1380
0#
#1385
b11100000 "
b11100000 +
b11100000 ,
b111 /
b101100 1
1#
#1390
0#
#1395
b11101001 "
b11101001 +
b11101001 ,
0-
b111 /
b101101 1
1#
#1400
0#
#1405
b11110100 "
b11110100 +
b11110100 ,
1-
b111 /
b101110 1
1#
#1410
0#
#1415
b11100011 "
b11100011 +
b11100011 ,
0-
b111 /
b101111 1
1#
#1420
0#
#1425
b11110001 "
b11110001 +
b11110001 ,
1-
b111 /
b110000 1
1#
#1430
0#
#1435
b11100001 "
b11100001 +
b11100001 ,
b111 /
b110001 1
1#
#1440
0#
#1445
b11101001 "
b11101001 +
b11101001 ,
b111 /
b110010 1
1#
#1450
0#
#1455
b11101101 "
b11101101 +
b11101101 ,
b111 /
b110011 1
1#
#1460
0#
#1465
b11101111 "
b11101111 +
b11101111 ,
b111 /
b110100 1
1#
#1470
0#
#1475
b11101110 "
b11101110 +
b11101110 ,
b111 /
b110101 1
1#
#1480
0#
#1485
0-
b111 /
b110110 1
1#
#1490
0#
#1495
b11110111 "
b11110111 +
b11110111 ,
b111 /
b110111 1
1#
#1500
0#
#1505
b11111011 "
b11111011 +
b11111011 ,
1-
b111 /
b111000 1
1#
#1510
0#
#1515
b11100100 "
b11100100 +
b11100100 ,
b111 /
b111001 1
1#
#1520
0#
#1525
b11101011 "
b11101011 +
b11101011 ,
0-
b111 /
b111010 1
1#
#1530
0#
#1535
b11110101 "
b11110101 +
b11110101 ,
1-
b111 /
b111011 1
1#
#1540
0#
#1545
b11100011 "
b11100011 +
b11100011 ,
b111 /
b111100 1
1#
#1550
0#
#1555
b11101000 "
b11101000 +
b11101000 ,
b111 /
b111101 1
1#
#1560
0#
#1565
b11101101 "
b11101101 +
b11101101 ,
0-
b111 /
b111110 1
1#
#1570
0#
#1575
b11110110 "
b11110110 +
b11110110 ,
1-
b111 /
b111111 1
1#
#1580
0#
#1585
b11100010 "
b11100010 +
b11100010 ,
0-
b111 /
b1000000 1
1#
#1590
0#
#1595
b11110001 "
b11110001 +
b11110001 ,
b111 /
b1000001 1
1#
#1600
0#
#1605
b11111000 "
b11111000 +
b11111000 ,
1-
b111 /
b1000010 1
1#
#1610
0#
#1615
b11100101 "
b11100101 +
b11100101 ,
0-
b111 /
b1000011 1
1#
#1620
0#
#1625
b11110010 "
b11110010 +
b11110010 ,
1-
b111 /
b1000100 1
1#
#1630
0#
#1635
b11100000 "
b11100000 +
b11100000 ,
0-
b111 /
b1000101 1
1#
#1640
0#
#1645
b11110000 "
b11110000 +
b11110000 ,
b111 /
b1000110 1
1#
#1650
0#
#1655
b11111000 "
b11111000 +
b11111000 ,
b111 /
b1000111 1
1#
#1660
0#
#1665
b11111100 "
b11111100 +
b11111100 ,
b111 /
b1001000 1
1#
#1670
0#
#1675
b11111110 "
b11111110 +
b11111110 ,
b111 /
b1001001 1
1#
#1680
0#
#1685
b11111111 "
b11111111 +
b11111111 ,
b111 /
b1001010 1
1#
#1690
0#
#1695
1-
b111 /
b1001011 1
1#
#1700
0#
#1705
b11100110 "
b11100110 +
b11100110 ,
b111 /
b1001100 1
1#
#1710
0#
#1715
b11101010 "
b11101010 +
b11101010 ,
0-
b111 /
b1001101 1
1#
#1720
0#
#1725
b11110101 "
b11110101 +
b11110101 ,
b111 /
b1001110 1
1#
#1730
0#
#1735
b11111010 "
b11111010 +
b11111010 ,
1-
b111 /
b1001111 1
1#
#1740
0#
#1745
b11100100 "
b11100100 +
b11100100 ,
0-
b111 /
b10 0
b1010000 1
1#
#1750
0#
#1755
b11110010 "
b11110010 +
b11110010 ,
1$
b111 /
1#
#1760
0#
#1765
b11100111 "
b11100111 +
b11100111 ,
0$
b0 1
1#
#1770
0#
#1775
b11110011 "
b11110011 +
b11110011 ,
1-
b111 /
b1 1
1#
#1780
0#
#1785
b11100000 "
b11100000 +
b11100000 ,
b111 /
b10 1
1#
#1790
0#
#1795
b11101001 "
b11101001 +
b11101001 ,
0-
b111 /
b11 1
1#
#1800
0#
#1805
b11110100 "
b11110100 +
b11110100 ,
1-
b111 /
b100 1
1#
#1810
0#
#1815
b11100011 "
b11100011 +
b11100011 ,
0-
b111 /
b101 1
1#
#1820
0#
#1825
b11110001 "
b11110001 +
b11110001 ,
1-
b111 /
b110 1
1#
#1830
0#
#1835
b11100001 "
b11100001 +
b11100001 ,
b111 /
b111 1
1#
#1840
0#
#1845
b11101001 "
b11101001 +
b11101001 ,
b111 /
b1000 1
1#
#1850
0#
#1855
b11101101 "
b11101101 +
b11101101 ,
b111 /
b1001 1
1#
#1860
0#
#1865
b11101111 "
b11101111 +
b11101111 ,
b111 /
b1010 1
1#
#1870
0#
#1875
b11101110 "
b11101110 +
b11101110 ,
b111 /
b1011 1
1#
#1880
0#
#1885
0-
b111 /
b1100 1
1#
#1890
0#
#1895
b11110111 "
b11110111 +
b11110111 ,
b111 /
b1101 1
1#
#1900
0#
#1905
b11111011 "
b11111011 +
b11111011 ,
1-
b111 /
b1110 1
1#
#1910
0#
#1915
b11100100 "
b11100100 +
b11100100 ,
b111 /
b1111 1
1#
#1920
0#
#1925
b11101011 "
b11101011 +
b11101011 ,
0-
b111 /
b10000 1
1#
#1930
0#
#1935
b11110101 "
b11110101 +
b11110101 ,
1-
b111 /
b10001 1
1#
#1940
0#
#1945
b11100011 "
b11100011 +
b11100011 ,
b111 /
b10010 1
1#
#1950
0#
#1955
b11101000 "
b11101000 +
b11101000 ,
b111 /
b10011 1
1#
#1960
0#
#1965
b11101101 "
b11101101 +
b11101101 ,
0-
b111 /
b10100 1
1#
#1970
0#
#1975
b11110110 "
b11110110 +
b11110110 ,
1-
b111 /
b10101 1
1#
#1980
0#
#1985
b11100010 "
b11100010 +
b11100010 ,
0-
b111 /
b10110 1
1#
#1990
0#
#1995
b11110001 "
b11110001 +
b11110001 ,
b111 /
b10111 1
1#
#2000
0#
#2005
b11111000 "
b11111000 +
b11111000 ,
1-
b111 /
b11000 1
1#
#2010
0#
#2015
b11100101 "
b11100101 +
b11100101 ,
0-
b111 /
b11001 1
1#
#2020
0#
#2025
b11110010 "
b11110010 +
b11110010 ,
1-
b111 /
b11010 1
1#
#2030
0#
#2035
b11100000 "
b11100000 +
b11100000 ,
0-
b111 /
b11011 1
1#
#2040
0#
#2045
b11110000 "
b11110000 +
b11110000 ,
b111 /
b11100 1
1#
#2050
0#
#2055
b11111000 "
b11111000 +
b11111000 ,
b111 /
b11101 1
1#
#2060
0#
#2065
b11111100 "
b11111100 +
b11111100 ,
b111 /
b11110 1
1#
#2070
0#
#2075
b11111110 "
b11111110 +
b11111110 ,
b111 /
b11111 1
1#
#2080
0#
#2085
b11111111 "
b11111111 +
b11111111 ,
b111 /
b100000 1
1#
#2090
0#
#2095
1-
b111 /
b100001 1
1#
#2100
0#
#2105
b11100110 "
b11100110 +
b11100110 ,
b111 /
b100010 1
1#
#2110
0#
#2115
b11101010 "
b11101010 +
b11101010 ,
0-
b111 /
b100011 1
1#
#2120
0#
#2125
b11110101 "
b11110101 +
b11110101 ,
b111 /
b100100 1
1#
#2130
0#
#2135
b11111010 "
b11111010 +
b11111010 ,
1-
b111 /
b100101 1
1#
#2140
0#
#2145
b11100100 "
b11100100 +
b11100100 ,
0-
b111 /
b100110 1
1#
#2150
0#
#2155
b11110010 "
b11110010 +
b11110010 ,
b111 /
b100111 1
1#
#2160
0#
#2165
b11111001 "
b11111001 +
b11111001 ,
b111 /
b101000 1
1#
#2170
0#
#2175
b11111100 "
b11111100 +
b11111100 ,
1-
b111 /
b101001 1
1#
#2180
0#
#2185
b11100111 "
b11100111 +
b11100111 ,
0-
b111 /
b101010 1
1#
#2190
0#
#2195
b11110011 "
b11110011 +
b11110011 ,
1-
b111 /
b101011 1
1#
#2200
0#
#2205
b11100000 "
b11100000 +
b11100000 ,
b111 /
b101100 1
1#
#2210
0#
#2215
b11101001 "
b11101001 +
b11101001 ,
0-
b111 /
b101101 1
1#
#2220
0#
#2225
b11110100 "
b11110100 +
b11110100 ,
1-
b111 /
b101110 1
1#
#2230
0#
#2235
b11100011 "
b11100011 +
b11100011 ,
0-
b111 /
b101111 1
1#
#2240
0#
#2245
b11110001 "
b11110001 +
b11110001 ,
1-
b111 /
b110000 1
1#
#2250
0#
#2255
b11100001 "
b11100001 +
b11100001 ,
b111 /
b110001 1
1#
#2260
0#
#2265
b11101001 "
b11101001 +
b11101001 ,
b111 /
b110010 1
1#
#2270
0#
#2275
b11101101 "
b11101101 +
b11101101 ,
b111 /
b110011 1
1#
#2280
0#
#2285
b11101111 "
b11101111 +
b11101111 ,
b111 /
b110100 1
1#
#2290
0#
#2295
b11101110 "
b11101110 +
b11101110 ,
b111 /
b110101 1
1#
#2300
0#
#2305
0-
b111 /
b110110 1
1#
#2310
0#
#2315
b11110111 "
b11110111 +
b11110111 ,
b111 /
b110111 1
1#
#2320
0#
#2325
b11111011 "
b11111011 +
b11111011 ,
1-
b111 /
b111000 1
1#
#2330
0#
#2335
b11100100 "
b11100100 +
b11100100 ,
b111 /
b111001 1
1#
#2340
0#
#2345
b11101011 "
b11101011 +
b11101011 ,
0-
b111 /
b111010 1
1#
#2350
0#
#2355
b11110101 "
b11110101 +
b11110101 ,
1-
b111 /
b111011 1
1#
#2360
0#
#2365
b11100011 "
b11100011 +
b11100011 ,
b111 /
b111100 1
1#
#2370
0#
#2375
b11101000 "
b11101000 +
b11101000 ,
b111 /
b111101 1
1#
#2380
0#
#2385
b11101101 "
b11101101 +
b11101101 ,
0-
b111 /
b111110 1
1#
#2390
0#
#2395
b11110110 "
b11110110 +
b11110110 ,
1-
b111 /
b111111 1
1#
#2400
0#
#2405
b11100010 "
b11100010 +
b11100010 ,
0-
b111 /
b1000000 1
1#
#2410
0#
#2415
b11110001 "
b11110001 +
b11110001 ,
b111 /
b1000001 1
1#
#2420
0#
#2425
b11111000 "
b11111000 +
b11111000 ,
1-
b111 /
b1000010 1
1#
#2430
0#
#2435
b11100101 "
b11100101 +
b11100101 ,
0-
b111 /
b1000011 1
1#
#2440
0#
#2445
b11110010 "
b11110010 +
b11110010 ,
1-
b111 /
b1000100 1
1#
#2450
0#
#2455
b11100000 "
b11100000 +
b11100000 ,
0-
b111 /
b1000101 1
1#
#2460
0#
#2465
b11110000 "
b11110000 +
b11110000 ,
b111 /
b1000110 1
1#
#2470
0#
#2475
b11111000 "
b11111000 +
b11111000 ,
b111 /
b1000111 1
1#
#2480
0#
#2485
b11111100 "
b11111100 +
b11111100 ,
b111 /
b1001000 1
1#
#2490
0#
#2495
b11111110 "
b11111110 +
b11111110 ,
b111 /
b1001001 1
1#
#2500
0#
#2505
b11111111 "
b11111111 +
b11111111 ,
b111 /
b1001010 1
1#
#2510
0#
#2515
1-
b111 /
b1001011 1
1#
#2520
0#
#2525
b11100110 "
b11100110 +
b11100110 ,
b111 /
b1001100 1
1#
#2530
0#
#2535
b11101010 "
b11101010 +
b11101010 ,
0-
b111 /
b1001101 1
1#
#2540
0#
#2545
b11110101 "
b11110101 +
b11110101 ,
b111 /
b1001110 1
1#
#2550
0#
#2555
b11111010 "
b11111010 +
b11111010 ,
1-
b111 /
b1001111 1
1#
#2560
0#
#2565
b11100100 "
b11100100 +
b11100100 ,
0-
b111 /
b11 0
b1010000 1
1#
#2570
0#
#2575
b11110010 "
b11110010 +
b11110010 ,
1$
b111 /
1#
#2580
0#
#2585
b11100111 "
b11100111 +
b11100111 ,
0$
b0 1
1#
#2590
0#
#2595
b11110011 "
b11110011 +
b11110011 ,
1-
b111 /
b1 1
1#
#2600
0#
#2605
b11100000 "
b11100000 +
b11100000 ,
b111 /
b10 1
1#
#2610
0#
#2615
b11101001 "
b11101001 +
b11101001 ,
0-
b111 /
b11 1
1#
#2620
0#
#2625
b11110100 "
b11110100 +
b11110100 ,
1-
b111 /
b100 1
1#
#2630
0#
#2635
b11100011 "
b11100011 +
b11100011 ,
0-
b111 /
b101 1
1#
#2640
0#
#2645
b11110001 "
b11110001 +
b11110001 ,
1-
b111 /
b110 1
1#
#2650
0#
#2655
b11100001 "
b11100001 +
b11100001 ,
b111 /
b111 1
1#
#2660
0#
#2665
b11101001 "
b11101001 +
b11101001 ,
b111 /
b1000 1
1#
#2670
0#
#2675
b11101101 "
b11101101 +
b11101101 ,
b111 /
b1001 1
1#
#2680
0#
#2685
b11101111 "
b11101111 +
b11101111 ,
b111 /
b1010 1
1#
#2690
0#
#2695
b11101110 "
b11101110 +
b11101110 ,
b111 /
b1011 1
1#
#2700
0#
#2705
0-
b111 /
b1100 1
1#
#2710
0#
#2715
b11110111 "
b11110111 +
b11110111 ,
b111 /
b1101 1
1#
#2720
0#
#2725
b11111011 "
b11111011 +
b11111011 ,
1-
b111 /
b1110 1
1#
#2730
0#
#2735
b11100100 "
b11100100 +
b11100100 ,
b111 /
b1111 1
1#
#2740
0#
#2745
b11101011 "
b11101011 +
b11101011 ,
0-
b111 /
b10000 1
1#
#2750
0#
#2755
b11110101 "
b11110101 +
b11110101 ,
1-
b111 /
b10001 1
1#
#2760
0#
#2765
b11100011 "
b11100011 +
b11100011 ,
b111 /
b10010 1
1#
#2770
0#
#2775
b11101000 "
b11101000 +
b11101000 ,
b111 /
b10011 1
1#
#2780
0#
#2785
b11101101 "
b11101101 +
b11101101 ,
0-
b111 /
b10100 1
1#
#2790
0#
#2795
b11110110 "
b11110110 +
b11110110 ,
1-
b111 /
b10101 1
1#
#2800
0#
#2805
b11100010 "
b11100010 +
b11100010 ,
0-
b111 /
b10110 1
1#
#2810
0#
#2815
b11110001 "
b11110001 +
b11110001 ,
b111 /
b10111 1
1#
#2820
0#
#2825
b11111000 "
b11111000 +
b11111000 ,
1-
b111 /
b11000 1
1#
#2830
0#
#2835
b11100101 "
b11100101 +
b11100101 ,
0-
b111 /
b11001 1
1#
#2840
0#
#2845
b11110010 "
b11110010 +
b11110010 ,
1-
b111 /
b11010 1
1#
#2850
0#
