MPEI_Magistracy/Term_two/ASIC_design/Scrambler/src/descrambler.sv
module descrambler (

   input  logic  clk ,
   input  logic  rst ,
   input  logic  bit_in,
   output logic	bit_out);


   logic [9:0] 	q ;
   assign feedback =   (q[8] ^ q[2] ^ q[0]);



   always_ff @ (posedge clk or negedge rst) begin
	if (!rst) 
	   q <= 10'b00_1001_0110; 
	else 
	   q <= {feedback,q[9:1]};
     end 

  assign bit_out = feedback ^ bit_in;

	  
endmodule

MPEI_Magistracy/Term_two/ASIC_design/Scrambler/src/scrambler.sv
module scrambler(
	input  logic   clk,
	input  logic   rst,
	input  logic   bit_in,
	output logic   bit_out);



	logic feedback;
	logic [9:0] q;
	assign feedback =  (q[8] ^ q[2] ^ q[0]);
	assign bit_out = feedback ^ bit_in;



	always_ff @(posedge clk or negedge rst) begin
		if (!rst) 
			q <=  10'b00_1001_0110; 
		else
			q <= {feedback,q[9:1]};
	end

endmodule

MPEI_Magistracy/Term_two/ASIC_design/Scrambler/src/top.sv

module top  (
    input  logic clk,
    input  logic rst,
    input  logic  bit_in,
    output logic  bit_out
);

logic a1;
logic a2;

scrambler U(
    .clk (clk),
    .rst (rst),
    .bit_in (bit_in),
    .bit_out(a1)
    );

descrambler U2(
  .clk (clk),
  .rst (rst),
  .bit_in (a1),
  .bit_out(a2)
    );

assign bit_out = a2;

endmodule

MPEI_Magistracy/Term_two/ASIC_design/Scrambler/test/top_tb.sv
`include"top.sv"
`include"scrambler.sv"
`include"descrambler.sv"
`timescale 1ns/1ps //Simulation time unit 1ns, simulation time precision 1ps
module top_tb();

// signal declaration
logic clk;
logic rst;
logic bit_in;
logic bit_out;

//Module instantiation (just connect the declared signals)
top U(
    .clk (clk),
    .rst (rst),
    .bit_in (bit_in),
    .bit_out (bit_out)
    );

always #5 clk = ~clk; //generate clock signal

// assign value to input data
initial begin
    clk = 1;
    rst = 1;
    #10 rst = 0;
    #5 rst = 1;
end

localparam [0 : 10] a        = 11'b1010_0000_101;

initial
  begin
    @ (negedge rst);

    for (int i = 0; i < 11; i ++)
    begin
      @ (posedge clk);
      bit_in <= a [i];
   end
  end

initial begin
    $dumpfile("top.vcd");
    $dumpvars;
    #1000
    $finish();
end



endmodule

MPEI_Magistracy/Term_two/ASIC_design/Scrambler/dump/top.vcd
$date
	Fri Apr 05 01:31:27 2024
$end
$version
	Icarus Verilog
$end
$timescale
	1ps
$end
$scope module top_tb $end
$var wire 1 ! bit_out $end
$var parameter 11 " a $end
$var reg 1 # bit_in $end
$var reg 1 $ clk $end
$var reg 1 % rst $end
$scope module U $end
$var wire 1 # bit_in $end
$var wire 1 ! bit_out $end
$var wire 1 $ clk $end
$var wire 1 % rst $end
$var wire 1 & a2 $end
$var wire 1 ' a1 $end
$scope module U $end
$var wire 1 # bit_in $end
$var wire 1 ' bit_out $end
$var wire 1 $ clk $end
$var wire 1 ( feedback $end
$var wire 1 % rst $end
$var reg 10 ) q [9:0] $end
$upscope $end
$scope module U2 $end
$var wire 1 ' bit_in $end
$var wire 1 & bit_out $end
$var wire 1 $ clk $end
$var wire 1 * feedback $end
$var wire 1 % rst $end
$var reg 10 + q [9:0] $end
$upscope $end
$upscope $end
$scope begin $ivl_for_loop0 $end
$var integer 32 , i [31:0] $end
$upscope $end
$upscope $end
$enddefinitions $end
$comment Show the parameter values. $end
$dumpall
b10100000101 "
$end
#0
$dumpvars
b0 ,
bx +
x*
bx )
x(
x'
x&
1%
1$
x#
x!
$end
#5000
0$
#10000
1*
1(
b10010110 +
b10010110 )
1$
0%
#15000
0$
1%
#20000
1(
1*
1!
1&
0'
b1001001011 )
b1001001011 +
1#
b1 ,
1$
#25000
0$
#30000
0!
0&
1'
b1100100101 +
b1100100101 )
0#
b10 ,
1$
#35000
0$
#40000
1(
1*
1!
1&
0'
b1110010010 )
b1110010010 +
1#
b11 ,
1$
#45000
0$
#50000
0*
0(
0!
0&
0'
b1111001001 +
b1111001001 )
0#
b100 ,
1$
#55000
0$
#60000
0'
0!
0&
0(
0*
b111100100 )
b111100100 +
b101 ,
1$
#65000
0$
#70000
b11110010 +
b11110010 )
b110 ,
1$
#75000
0$
#80000
1'
0!
0&
1(
1*
b1111001 )
b1111001 +
b111 ,
1$
#85000
0$
#90000
1'
1*
1(
b1000111100 +
b1000111100 )
b1000 ,
1$
#95000
0$
#100000
0(
0*
1!
1&
1'
b1100011110 )
b1100011110 +
1#
b1001 ,
1$
#105000
0$
#110000
1*
1(
0!
0&
1'
b110001111 +
b110001111 )
0#
b1010 ,
1$
#115000
0$
#120000
0(
0*
1!
1&
1'
b1011000111 )
b1011000111 +
1#
b1011 ,
1$
#125000
0$
#130000
b101100011 +
b101100011 )
1$
#135000
0$
#140000
0'
1!
1&
1(
1*
b10110001 )
b10110001 +
1$
#145000
0$
#150000
1'
0*
0(
b1001011000 +
b1001011000 )
1$
#155000
0$
#160000
b100101100 )
b100101100 +
1$
#165000
0$
#170000
0'
1*
1(
b10010110 +
b10010110 )
1$
#175000
0$
#180000
0'
1!
1&
1(
1*
b1001001011 )
b1001001011 +
1$
#185000
0$
#190000
b1100100101 +
b1100100101 )
1$
#195000
0$
#200000
0'
1!
1&
1(
1*
b1110010010 )
b1110010010 +
1$
#205000
0$
#210000
1'
0*
0(
b1111001001 +
b1111001001 )
1$
#215000
0$
#220000
1'
1!
1&
0(
0*
b111100100 )
b111100100 +
1$
#225000
0$
#230000
b11110010 +
b11110010 )
1$
#235000
0$
#240000
0'
1!
1&
1(
1*
b1111001 )
b1111001 +
1$
#245000
0$
#250000
0'
1*
1(
b1000111100 +
b1000111100 )
1$
#255000
0$
#260000
1'
1!
1&
0(
0*
b1100011110 )
b1100011110 +
1$
#265000
0$
#270000
0'
1*
1(
b110001111 +
b110001111 )
1$
#275000
0$
#280000
1'
1!
1&
0(
0*
b1011000111 )
b1011000111 +
1$
#285000
0$
#290000
b101100011 +
b101100011 )
1$
#295000
0$
#300000
0'
1!
1&
1(
1*
b10110001 )
b10110001 +
1$
#305000
0$
#310000
1'
0*
0(
b1001011000 +
b1001011000 )
1$
#315000
0$
#320000
b100101100 )
b100101100 +
1$
#325000
0$
#330000
0'
1*
1(
b10010110 +
b10010110 )
1$
#335000
0$
#340000
0'
1!
1&
1(
1*
b1001001011 )
b1001001011 +
1$
#345000
0$
#350000
b1100100101 +
b1100100101 )
1$
#355000
0$
#360000
0'
1!
1&
1(
1*
b1110010010 )
b1110010010 +
1$
#365000
0$
#370000
1'
0*
0(
b1111001001 +
b1111001001 )
1$
#375000
0$
#380000
1'
1!
1&
0(
0*
b111100100 )
b111100100 +
1$
#385000
0$
#390000
b11110010 +
b11110010 )
1$
#395000
0$
#400000
0'
1!
1&
1(
1*
b1111001 )
b1111001 +
1$
#405000
0$
#410000
0'
1*
1(
b1000111100 +
b1000111100 )
1$
#415000
0$
#420000
1'
1!
1&
0(
0*
b1100011110 )
b1100011110 +
1$
#425000
0$
#430000
0'
1*
1(
b110001111 +
b110001111 )
1$
#435000
0$
#440000
1'
1!
1&
0(
0*
b1011000111 )
b1011000111 +
1$
#445000
0$
#450000
b101100011 +
b101100011 )
1$
#455000
0$
#460000
0'
1!
1&
1(
1*
b10110001 )
b10110001 +
1$
#465000
0$
#470000
1'
0*
0(
b1001011000 +
b1001011000 )
1$
#475000
0$
#480000
b100101100 )
b100101100 +
1$
#485000
0$
#490000
0'
1*
1(
b10010110 +
b10010110 )
1$
#495000
0$
#500000
0'
1!
1&
1(
1*
b1001001011 )
b1001001011 +
1$
#505000
0$
#510000
b1100100101 +
b1100100101 )
1$
#515000
0$
#520000
0'
1!
1&
1(
1*
b1110010010 )
b1110010010 +
1$
#525000
0$
#530000
1'
0*
0(
b1111001001 +
b1111001001 )
1$
#535000
0$
#540000
1'
1!
1&
0(
0*
b111100100 )
b111100100 +
1$
#545000
0$
#550000
b11110010 +
b11110010 )
1$
#555000
0$
#560000
0'
1!
1&
1(
1*
b1111001 )
b1111001 +
1$
#565000
0$
#570000
0'
1*
1(
b1000111100 +
b1000111100 )
1$
#575000
0$
#580000
1'
1!
1&
0(
0*
b1100011110 )
b1100011110 +
1$
#585000
0$
#590000
0'
1*
1(
b110001111 +
b110001111 )
1$
#595000
0$
#600000
1'
1!
1&
0(
0*
b1011000111 )
b1011000111 +
1$
#605000
0$
#610000
b101100011 +
b101100011 )
1$
#615000
0$
#620000
0'
1!
1&
1(
1*
b10110001 )
b10110001 +
1$
#625000
0$
#630000
1'
0*
0(
b1001011000 +
b1001011000 )
1$
#635000
0$
#640000
b100101100 )
b100101100 +
1$
#645000
0$
#650000
0'
1*
1(
b10010110 +
b10010110 )
1$
#655000
0$
#660000
0'
1!
1&
1(
1*
b1001001011 )
b1001001011 +
1$
#665000
0$
#670000
b1100100101 +
b1100100101 )
1$
#675000
0$
#680000
0'
1!
1&
1(
1*
b1110010010 )
b1110010010 +
1$
#685000
0$
#690000
1'
0*
0(
b1111001001 +
b1111001001 )
1$
#695000
0$
#700000
1'
1!
1&
0(
0*
b111100100 )
b111100100 +
1$
#705000
0$
#710000
b11110010 +
b11110010 )
1$
#715000
0$
#720000
0'
1!
1&
1(
1*
b1111001 )
b1111001 +
1$
#725000
0$
#730000
0'
1*
1(
b1000111100 +
b1000111100 )
1$
#735000
0$
#740000
1'
1!
1&
0(
0*
b1100011110 )
b1100011110 +
1$
#745000
0$
#750000
0'
1*
1(
b110001111 +
b110001111 )
1$
#755000
0$
#760000
1'
1!
1&
0(
0*
b1011000111 )
b1011000111 +
1$
#765000
0$
#770000
b101100011 +
b101100011 )
1$
#775000
0$
#780000
0'
1!
1&
1(
1*
b10110001 )
b10110001 +
1$
#785000
0$
#790000
1'
0*
0(
b1001011000 +
b1001011000 )
1$
#795000
0$
#800000
b100101100 )
b100101100 +
1$
#805000
0$
#810000
0'
1*
1(
b10010110 +
b10010110 )
1$
#815000
0$
#820000
0'
1!
1&
1(
1*
b1001001011 )
b1001001011 +
1$
#825000
0$
#830000
b1100100101 +
b1100100101 )
1$
#835000
0$
#840000
0'
1!
1&
1(
1*
b1110010010 )
b1110010010 +
1$
#845000
0$
#850000
1'
0*
0(
b1111001001 +
b1111001001 )
1$
#855000
0$
#860000
1'
1!
1&
0(
0*
b111100100 )
b111100100 +
1$
#865000
0$
#870000
b11110010 +
b11110010 )
1$
#875000
0$
#880000
0'
1!
1&
1(
1*
b1111001 )
b1111001 +
1$
#885000
0$
#890000
0'
1*
1(
b1000111100 +
b1000111100 )
1$
#895000
0$
#900000
1'
1!
1&
0(
0*
b1100011110 )
b1100011110 +
1$
#905000
0$
#910000
0'
1*
1(
b110001111 +
b110001111 )
1$
#915000
0$
#920000
1'
1!
1&
0(
0*
b1011000111 )
b1011000111 +
1$
#925000
0$
#930000
b101100011 +
b101100011 )
1$
#935000
0$
#940000
0'
1!
1&
1(
1*
b10110001 )
b10110001 +
1$
#945000
0$
#950000
1'
0*
0(
b1001011000 +
b1001011000 )
1$
#955000
0$
#960000
b100101100 )
b100101100 +
1$
#965000
0$
#970000
0'
1*
1(
b10010110 +
b10010110 )
1$
#975000
0$
#980000
0'
1!
1&
1(
1*
b1001001011 )
b1001001011 +
1$
#985000
0$
#990000
b1100100101 +
b1100100101 )
1$
#995000
0$
#1000000
0'
1!
1&
1(
1*
b1110010010 )
b1110010010 +
1$
