MPEI_Bachelor/projects/Лр3/КМ3/lab3/src/dff.v
module dff(D, clk, res, Q, nQ);

input D;
input clk;
input res;

output Q, nQ;

reg Q;

initial Q = 0;

always @(posedge clk, negedge res) 

if (!res) 
	Q <= 0;
else
	Q <= D;

assign nQ = ~Q;
	
endmodule

MPEI_Bachelor/projects/Лр3/КМ3/lab3/src/JK.v
`include "dff.v" 
module JK (J, K, clk, Q, nQ, res);

input J, K, clk, res;

output  Q;
output nQ;

wire D;

dff DUT1 (.clk(clk),.Q(Q),.nQ(nQ),.D(D),.res(res));

assign D = (nQ & J) | (Q & ~K);

endmodule

MPEI_Bachelor/projects/Лр3/КМ3/lab3/src/JKpov.v
module JKpov(J, K, clk, Q, nQ, res);

input J, K, clk, res;
output Q,nQ;

reg Q;

initial Q = 0;

always @(posedge clk, negedge res)
    if (!res)
		Q<=0;
	else if(J == 0 && K == 0)
		Q <= Q;
    else if(J == 0 && K == 1)
		Q <= 0;
    else if(J == 1 && K == 0)
		Q <= 1;
	else 
		Q <= ~Q; 
		
assign nQ = !Q;


endmodule

MPEI_Bachelor/projects/Лр3/КМ3/lab3/src/tb_JK.v
`include "JKpov.v"
`include "JK.v" 
`timescale 1 ns/ 1 ps

module tb_JK();

reg   clk, res, J, K;
                                          
wire   Q, nQ, Q1, nQ1;
                  
JKpov DUT1 (.K(K),.J(J),.clk(clk),.Q(Q),.nQ(nQ),.res(res));
JK DUT2 (.K(K),.J(J),.clk(clk),.Q(Q1),.nQ(nQ1),.res(res));

initial begin
  $display("Running testbench");                                                  
  clk = 0;
  forever #5 clk = ~clk;
end     

initial begin
  res = 1;
  repeat (2) #1 res = ~res;
end       
      
initial begin
	J = 0; K = 0;
	#10
	J = 1; K = 0;
	#20 J = 0; K = 1;
	#30 J = 1; K = 1;
	#40 J = 0; K = 0;
end      
	 
initial begin
	#500 $display("Testbench is OK!");
	#500 $finish;
end
	 
initial begin            
    $dumpfile("qqq.vcd");
    $dumpvars;
end

endmodule

MPEI_Bachelor/projects/Лр3/КМ3/lab3/src/qqq.vcd
$date
	Mon Nov 21 20:41:08 2022
$end
$version
	Icarus Verilog
$end
$timescale
	1ps
$end
$scope module tb_JK $end
$var wire 1 ! nQ1 $end
$var wire 1 " nQ $end
$var wire 1 # Q1 $end
$var wire 1 $ Q $end
$var reg 1 % J $end
$var reg 1 & K $end
$var reg 1 ' clk $end
$var reg 1 ( res $end
$scope module DUT1 $end
$var wire 1 % J $end
$var wire 1 & K $end
$var wire 1 ' clk $end
$var wire 1 ( res $end
$var wire 1 " nQ $end
$var reg 1 $ Q $end
$upscope $end
$scope module DUT2 $end
$var wire 1 ) D $end
$var wire 1 % J $end
$var wire 1 & K $end
$var wire 1 ' clk $end
$var wire 1 ( res $end
$var wire 1 ! nQ $end
$var wire 1 # Q $end
$scope module DUT1 $end
$var wire 1 ) D $end
$var wire 1 ' clk $end
$var wire 1 ! nQ $end
$var wire 1 ( res $end
$var reg 1 # Q $end
$upscope $end
$upscope $end
$upscope $end
$enddefinitions $end
$comment Show the parameter values. $end
$dumpall
$end
#0
$dumpvars
0)
1(
0'
0&
0%
0$
0#
1"
1!
$end
#1000
0(
#2000
1(
#5000
1'
#10000
1)
0'
1%
#15000
0!
0"
1$
1#
1'
#20000
0'
#25000
1'
#30000
0)
0'
1&
0%
#35000
1!
1"
0$
0#
1'
#40000
0'
#45000
1'
#50000
0'
#55000
1'
#60000
1)
0'
1%
#65000
0)
0!
1#
0"
1$
1'
#70000
0'
#75000
1)
1!
1"
0$
0#
1'
#80000
0'
#85000
0)
0!
1#
0"
1$
1'
#90000
0'
#95000
1)
1!
1"
0$
0#
1'
#100000
0)
0'
0&
0%
