MPEI_Bachelor/projects/Лр4/КМ4/Snail_FSM_unique_11/SnailFSM_unique_11.v
module SnailFSM_unique_11(D, _rst, clk, Q);
localparam SAD = 0, HOPE = 1, HOORAY = 2;

input D;
input _rst, clk;

output reg Q;

reg [1:0] state, nextstate;

reg Q_nonsynch;

reg [63:0] txstate;

always @( state )
  case ( state )
	 SAD    : txstate = "SAD";
	 HOPE   : txstate = "HOPE";
	 HOORAY : txstate = "HOORAY";
  endcase

always @(posedge clk, negedge _rst) begin
  if ( !_rst )
    state <= SAD;
  else
    state <= nextstate;
end

always @(*) begin
  case ( state )
    SAD          : nextstate = (( D ) ? HOPE   : SAD ); 
    HOPE         : nextstate = (( D ) ? HOORAY : SAD );
	  HOORAY       : nextstate = (( D ) ? HOPE : SAD );
    default      : nextstate = SAD;
  endcase
end


always @(*) begin
  case ( state )
    SAD, HOPE : Q_nonsynch = 0;
    HOORAY    : Q_nonsynch = 1;
    default   : Q_nonsynch = 0;
  endcase
end

always @(posedge clk or negedge _rst)
  if (!_rst)
    Q <= 0;
  else
    Q <= Q_nonsynch;

endmodule

MPEI_Bachelor/projects/Лр4/КМ4/Snail_FSM_unique_11/SnailFSM_Mealey_unique_11.v
module SnailFSM_Mealey_unique_11(D, _rst, clk, Q);
localparam SAD = 0, WAIT1 = 1;

input D;
input _rst, clk;

output reg Q;

reg [1:0] state, nextstate;

reg Q_nonsynch;

reg [63:0] txstate;

always @( state )
  case ( state )
	 SAD    : txstate = "SAD";
	 WAIT1  : txstate = "WAIT1";
  endcase

always @(posedge clk, negedge _rst) begin
  if ( !_rst )
    state <= SAD;
  else
    state <= nextstate;
end

always @(*) begin
  case ( state )
    SAD, WAIT1 : nextstate = (( D ) ? WAIT1 : SAD );
	  WAIT1 : nextstate = SAD;
    default : nextstate = SAD;
  endcase
end


always @(*) begin
  case ( state )
    SAD       : Q_nonsynch = 0;
    WAIT1     : Q_nonsynch = (D) ? 1'b1 : 1'b0;
    default   : Q_nonsynch = 0;
  endcase
end

always @(posedge clk or negedge _rst)
  if (!_rst)
    Q <= 0;
  else
    Q <= Q_nonsynch;
endmodule

MPEI_Bachelor/projects/Лр4/КМ4/Snail_FSM_unique_11/tb_SnailFSM_unique_11.v
//`include "SnailFSM_unique_11.v"
`include "SnailFSM_Mealey_unique_11.v"
`timescale 1ns / 1ns

module tb_SnailFSM_unique_11;

reg D, _rst, clk;
wire Q;

wire [63:0] state = DUT.txstate;

//SnailFSM_unique_11 DUT (D, _rst, clk, Q);
SnailFSM_Mealey_unique_11 DUT (D, _rst, clk, Q);

initial begin
  clk = 0;
  forever #5 clk = ~clk;
end

initial begin
  _rst = 1;
  repeat(2) #1 _rst = ~_rst;
end

initial begin
  D = 0;
end

always @(posedge clk) #3 D = $random;

initial
  #300 $finish;

initial begin            
    $dumpfile("qqq.vcd");
    $dumpvars;
end

endmodule

MPEI_Bachelor/projects/Лр4/КМ4/Snail_FSM_unique_11/qqq.vcd
$date
	Sun Dec 18 12:32:16 2022
$end
$version
	Icarus Verilog
$end
$timescale
	1ns
$end
$scope module tb_SnailFSM_unique_11 $end
$var wire 64 ! state [63:0] $end
$var wire 1 " Q $end
$var reg 1 # D $end
$var reg 1 $ _rst $end
$var reg 1 % clk $end
$scope module DUT $end
$var wire 1 # D $end
$var wire 1 $ _rst $end
$var wire 1 % clk $end
$var parameter 32 & SAD $end
$var parameter 32 ' WAIT1 $end
$var reg 1 " Q $end
$var reg 1 ( Q_nonsynch $end
$var reg 2 ) nextstate [1:0] $end
$var reg 2 * state [1:0] $end
$var reg 64 + txstate [63:0] $end
$upscope $end
$upscope $end
$enddefinitions $end
$comment Show the parameter values. $end
$dumpall
b1 '
b0 &
$end
#0
$dumpvars
bx +
bx *
b0 )
0(
0%
1$
0#
x"
bx !
$end
#1
b10100110100000101000100 !
b10100110100000101000100 +
b0 *
0"
0$
#2
1$
#5
1%
#10
0%
#15
1%
#18
b1 )
1#
#20
0%
#25
1(
b101011101000001010010010101010000110001 !
b101011101000001010010010101010000110001 +
b1 *
1%
#30
0%
#35
1"
1%
#40
0%
#45
1%
#50
0%
#55
1%
#60
0%
#65
1%
#70
0%
#75
1%
#78
0(
b0 )
0#
#80
0%
#85
b10100110100000101000100 !
b10100110100000101000100 +
0"
b0 *
1%
#88
b1 )
1#
#90
0%
#95
1(
b101011101000001010010010101010000110001 !
b101011101000001010010010101010000110001 +
b1 *
1%
#100
0%
#105
1"
1%
#108
0(
b0 )
0#
#110
0%
#115
b10100110100000101000100 !
b10100110100000101000100 +
b0 *
0"
1%
#118
b1 )
1#
#120
0%
#125
1(
b101011101000001010010010101010000110001 !
b101011101000001010010010101010000110001 +
b1 *
1%
#130
0%
#135
1"
1%
#138
0(
b0 )
0#
#140
0%
#145
b10100110100000101000100 !
b10100110100000101000100 +
0"
b0 *
1%
#148
b1 )
1#
#150
0%
#155
1(
b101011101000001010010010101010000110001 !
b101011101000001010010010101010000110001 +
b1 *
1%
#158
0(
b0 )
0#
#160
0%
#165
b10100110100000101000100 !
b10100110100000101000100 +
b0 *
1%
#168
b1 )
1#
#170
0%
#175
1(
b101011101000001010010010101010000110001 !
b101011101000001010010010101010000110001 +
b1 *
1%
#178
0(
b0 )
0#
#180
0%
#185
b10100110100000101000100 !
b10100110100000101000100 +
b0 *
1%
#188
b1 )
1#
#190
0%
#195
1(
b101011101000001010010010101010000110001 !
b101011101000001010010010101010000110001 +
b1 *
1%
#200
0%
#205
1"
1%
#208
0(
b0 )
0#
#210
0%
#215
b10100110100000101000100 !
b10100110100000101000100 +
b0 *
0"
1%
#218
b1 )
1#
#220
0%
#225
1(
b101011101000001010010010101010000110001 !
b101011101000001010010010101010000110001 +
b1 *
1%
#228
0(
b0 )
0#
#230
0%
#235
b10100110100000101000100 !
b10100110100000101000100 +
b0 *
1%
#240
0%
#245
1%
#250
0%
#255
1%
#258
b1 )
1#
#260
0%
#265
1(
b101011101000001010010010101010000110001 !
b101011101000001010010010101010000110001 +
b1 *
1%
#268
0(
b0 )
0#
#270
0%
#275
b10100110100000101000100 !
b10100110100000101000100 +
b0 *
1%
#278
b1 )
1#
#280
0%
#285
1(
b101011101000001010010010101010000110001 !
b101011101000001010010010101010000110001 +
b1 *
1%
#290
0%
#295
1"
1%
